Workbook

Sheet INPUT-Y
B1: BALANCE SHEET | C1: 2013 | D1: 2014 | E1: 2015 | F1: 2016 | G1: 2017 | H1: 2018 | I1: 2019 | J1: 2020
B2: A. CURRENT ASSETS | C2: 405.1 | D2: 435.1 | E2: 484.5 | F2: 341.9 | G2: 485.8 | H2: 1229.9 | I2: 1190.4 | J2: 1779.3
B3: I. Cash and Cash Equivalents | C3: 30.1 | D3: 97.8 | E3: 88.7 | F3: 68 | G3: 223 | H3: 609.4 | I3: 105.4 | J3: 135.4
B4: 1. Cash | C4: 26.4 | D4: 80.6 | E4: 17.2 | F4: 15.1 | G4: 79.5 | H4: 48.7 | I4: 41.4 | J4: 69.7
B5: 2. Cash equivalents | C5: 3.7 | D5: 17.2 | E5: 71.5 | F5: 52.9 | G5: 143.5 | H5: 560.7 | I5: 64 | J5: 65.7
B6: II. Short-term Financial Investment | C6: 255.4 | D6: 219 | E6: 0 | F6: 0 | G6: 8.2 | H6: 252 | I6: 12 | J6: 0
B7: 1. Securities available for sale | C7: 0 | D7: 0 | E7: 0 | F7: 0 | G7: 0 | H7: 0 | I7: 0 | J7: 0
B8: 2. Provision for decline in value of investments in securities | C8: -21.9 | D8: -0.3 | E8: 0 | F8: 0 | G8: 0 | H8: 0 | I8: 0 | J8: 0
B9: 3. Securities hold to maturity | C9: 277.3 | D9: 219.3 | E9: 0 | F9: 0 | G9: 8.2 | H9: 252 | I9: 12 | J9: 0
B10: III. Short-term Receivables | C10: 93.3 | D10: 94.5 | E10: 381 | F10: 257 | G10: 227.4 | H10: 245.5 | I10: 688.2 | J10: 1434.3
B11: 1. Short-term receivables from customers | C11: 46.3 | D11: 38.1 | E11: 107.6 | F11: 121.4 | G11: 74.7 | H11: 109.6 | I11: 213.5 | J11: 321.1
B12: 2. Prepaid for suppliers | C12: 42.1 | D12: 52.4 | E12: 96 | F12: 3.2 | G12: 50.1 | H12: 103.3 | I12: 74.3 | J12: 466.2
... B41: 2. Fixed assets of finance leasing | C41: 0 | D41: 0 | E41: 0 | F41: 0 | G41: 0 | H41: 0 | I41: 0 | J41: 27.8
B42: - Cost | C42: 0 | D42: 0 | E42: 0 | F42: 0 | G42: 0 | H42: 0 | I42: 0 | J42: 28.1 | L42: =L390 -> 0
B43: - Accumulated depreciation | C43: 0 | D43: 0 | E43: 0 | F43: 0 | G43: 0 | H43: 0 | I43: 0 | J43: -0.3
B44: 3. Intangible fixed assets | C44: 1.7 | D44: 1.7 | E44: 5.7 | F44: 5.6 | G44: 6.6 | H44: 6.4 | I44: 19.2 | J44: 16.7
B45: - Cost | C45: 2 | D45: 2 | E45: 6.2 | F45: 6.4 | G45: 7.5 | H45: 7.4 | I45: 21.1 | J45: 21.3
B46: - Accumulated depreciation | C46: -0.3 | D46: -0.3 | E46: -0.5 | F46: -0.7 | G46: -0.9 | H46: -1 | I46: -1.9 | J46: -4.6
B47: III. Investment properties | C47: 0 | D47: 0 | E47: 0 | F47: 0 | G47: 0 | H47: 0 | I47: 0 | J47: 0
B48: 1. Cost | C48: 0 | D48: 0 | E48: 0 | F48: 0 | G48: 0 | H48: 0 | I48: 0 | J48: 0
B49: 2. Accumulated depreciation | C49: 0 | D49: 0 | E49: 0 | F49: 0 | G49: 0 | H49: 0 | I49: 0 | J49: 0
B50: IV. Long term assets in progress | C50: 136.9 | D50: 119.6 | E50: 135.2 | F50: 5.6 | G50: 18 | H50: 215.8 | I50: 262.8 | J50: 541.4
B51: 1. Long term work in progress | C51: 0 | D51: 0 | E51: 0 | F51: 0 | G51: 0 | H51: 0 | I51: 0 | J51: 0
B52: 2. Long term construction in progress | C52: 136.9 | D52: 119.6 | E52: 135.2 | F52: 5.6 | G52: 18 | H52: 215.8 | I52: 262.8 | J52: 541.4
B53: V. Long-term investments | C53: 72.5 | D53: 0.7 | E53: 0.9 | F53: 0.2 | G53: 0 | H53: 0 | I53: 2.6 | J53: 0
B54: 1. Investments in subsidiary | C54: 0 | D54: 0 | E54: 0 | F54: 0 | G54: 0 | H54: 0 | I54: 0 | J54: 0
... B118: TOTAL EQUITY | C118: 1725.2 | D118: 1710.3 | E118: 1885.2 | F118: 1551.7 | G118: 1658.6 | H118: 4360.6 | I118: 6763.2 | J118: 7773.1
B120: INCOME STATEMENT
B121: 1. Revenue from sale of goods and services | C121: 307.9 | D121: 338.8 | E121: 354.4 | F121: 431.4 | G121: 539.1 | H121: 559.5 | I121: 1159.4 | J121: 1494.5
B122: 2. Deduction | C122: 0 | D122: 0 | E122: 0 | F122: 0 | G122: 0 | H122: 0 | I122: 0 | J122: 1.2
B123: 3. Net revenue from sale of goods and services | C123: 307.9 | D123: 338.8 | E123: 354.4 | F123: 431.4 | G123: 539.1 | H123: 559.5 | I123: 1159.4 | J123: 1493.3
B124: 4. Costs of goods sold | C124: 118.2 | D124: 134.5 | E124: 157.3 | F124: 212.5 | G124: 227.3 | H124: 253.5 | I124: 509.7 | J124: 732.7
B125: 5. Gross profit | C125: 189.7 | D125: 204.3 | E125: 197 | F125: 218.9 | G125: 311.8 | H125: 306 | I125: 649.7 | J125: 760.7
B126: 6. Income from financial activities | C126: 33.8 | D126: 44.6 | E126: 34.4 | F126: 26.8 | G126: 18 | H126: 19.5 | I126: 24.2 | J126: 30.5
B127: 7. Expenses from financial activities | C127: 97.9 | D127: 76.3 | E127: 41.4 | F127: 45.8 | G127: 24.6 | H127: 41.1 | I127: 257.8 | J127: 371.2
B128: - In which: Interest expenses | C128: 78.3 | D128: 59.5 | E128: 41.1 | F128: 39.1 | G128: 24.4 | H128: 40.2 | I128: 244.9 | J128: 354.4
B129: 8. Share in profits of associates | C129: 6.5 | D129: 0 | E129: 0 | F129: 0 | G129: 0 | H129: 0 | I129: 0 | J129: 0
B130: 9. Selling expenses | C130: 0 | D130: 0.2 | E130: 0 | F130: 0.1 | G130: 1 | H130: 0.6 | I130: 0.6 | J130: 1.7
B131: 10. General and administrative expenses | C131: 30.3 | D131: 40.4 | E131: 42.1 | F131: 51.3 | G131: 65.1 | H131: 76.6 | I131: 111.2 | J131: 114.3
B132: 11. Operating profit | C132: 101.8 | D132: 132.1 | E132: 147.8 | F132: 148.5 | G132: 239.2 | H132: 207.1 | I132: 304.3 | J132: 303.9
... B141: 20. Net profit after tax of parent company | C141: 52 | D141: 76 | E141: 92.7 | F141: 95.1 | G141: 153.8 | H141: 144.7 | I141: 251 | J141: 257.4
B143: CASH FLOW STATEMENT
B144: I. CASH FLOWS FROM OPERATING ACTIVITIES | C144: 66.9 | D144: 345.1 | E144: 71.9 | F144: 168.4 | G144: 243.8 | H144: 141.1 | I144: -332.8 | J144: 420.6
B145: 1. Net profit before tax | C145: 0 | D145: 0 | E145: 148.5 | F145: 149.2 | G145: 230.4 | H145: 206.9 | I145: 303.9 | J145: 308.6
B146: 2. Adjustments for: | C146: 0 | D146: 0 | E146: 0 | F146: 0 | G146: 0 | H146: 0 | I146: 0 | J146: 0
B147: Depreciation and amortisation | C147: 0 | D147: 0 | E147: 74 | F147: 79.8 | G147: 79.5 | H147: 97.5 | I147: 285 | J147: 354
B148: Provision for decline in value of investments | C148: 0 | D148: 0 | E148: -0.4 | F148: 0 | G148: 0.3 | H148: 0.3 | I148: 0.5 | J148: -0.4
B149: Gain (loss) from disposal of equity investments in other entities | C149: 0 | D149: 0 | E149: -34.5 | F149: -27.1 | G149: -11.2 | H149: -19.1 | I149: -23.7 | J149: -25.8
B150: Gain (loss) on foreign exchange | C150: 0 | D150: 0 | E150: 0.2 | F150: 0 | G150: 0 | H150: 0.8 | I150: 0.5 | J150: 1.4
B151: (Gain) loss on disposal of assets | C151: 0 | D151: 0 | E151: 0 | F151: 0 | G151: 0 | H151: 0 | I151: 0 | J151: 0
B152: Interest expenses | C152: 0 | D152: 0 | E152: 41.1 | F152: 39.1 | G152: 24.4 | H152: 40.2 | I152: 247.3 | J152: 357.9
B153: Other adjustment | C153: 0 | D153: 0 | E153: 0 | F153: 0.9 | G153: 0 | H153: 0 | I153: 0 | J153: 0
B154: Interest income | C154: 0 | D154: 0 | E154: 0 | F154: 0 | G154: 0 | H154: 0 | I154: 0 | J154: 0
B155: Goodwill amortization | C155: 0 | D155: 0 | E155: 0 | F155: 0 | G155: 0 | H155: 0 | I155: 0 | J155: 0
... B186: VI. Cash and cash equivalents at the end of the period | C186: 30.1 | D186: 97.8 | E186: 88.7 | F186: 68 | G186: 223 | H186: 609.4 | I186: 105.4 | J186: 135.4

Sheet IS
B1: 2016 | C1: 2017 | D1: 2018 | E1: 2019 | F1: 2020 | G1: 2021F | H1: 2022F | I1: 2023F | J1: 2024F | K1: 2025F
A2: INCOME STATEMENT | B2: HISTORICAL | G2: FORECAST
A4: Net Sales | B4: 431.4 | C4: 539.1 | D4: 559.5 | E4: 1159.4 | F4: 1494.5 | G4: =Forecast!T18 -> 1450 | H4: =Forecast!U18 -> 3182 | I4: =Forecast!V18 -> 3284 | J4: =Forecast!W18 -> 3289 | K4: =Forecast!X18 -> 3299
A5: Cost of goods sold | B5: =-'INPUT-Y'!F124 -> -212.5 | C5: =-'INPUT-Y'!G124 -> -227.3 | D5: =-'INPUT-Y'!H124 -> -253.5 | E5: =-'INPUT-Y'!I124 -> -509.7 | F5: =-'INPUT-Y'!J124 -> -732.7 | G5: =-SUM(Forecast!G118:G122) -> -628.86298 | H5: =-SUM(Forecast!H118:H122) -> -1676.9805 | I5: =-SUM(Forecast!I118:I122) -> -1700.3699 | J5: =-SUM(Forecast!J118:J122) -> -1722.618 | K5: =-SUM(Forecast!K118:K122) -> -1745.9574
A6: Gross profit | B6: =B4+B5 -> 218.9 | C6: =C4+C5 -> 311.8 | D6: =D4+D5 -> 306 | E6: =E4+E5 -> 649.7 | F6: =F4+F5 -> 761.8 | G6: =G4+G5 -> 821.13702 | H6: =H4+H5 -> 1505.0195 | I6: =I4+I5 -> 1583.6301 | ... K6: =K4+K5 -> 1553.0426
A7: Financial income | B7: ='INPUT-Y'!F126 -> 26.8 | C7: ='INPUT-Y'!G126 -> 18 | D7: ='INPUT-Y'!H126 -> 19.5 | E7: ='INPUT-Y'!I126 -> 24.2 | F7: ='INPUT-Y'!J126 -> 30.5 | G7: =G36 -> 36.797895 | H7: =H36 -> 70.70286 | I7: =I36 -> 74.443519 | J7: =J36 -> 77.034999 | K7: =K36 -> 75.118441
A8: Financial Expenses | B8: =-'INPUT-Y'!F127 -> -45.8 | C8: =-'INPUT-Y'!G127 -> -24.6 | D8: =-'INPUT-Y'!H127 -> -41.1 | E8: =-'INPUT-Y'!I127 -> -257.8 | F8: =-'INPUT-Y'!J127 -> -371.2 | G8: =G39 -> -343.64435 | H8: =H39 -> -834.6402 | I8: =I39 -> -805.55427 | J8: =J39 -> -775.37795 | K8: =K39 -> -745.25784
A9: Of which: Interest Expenses | B9: =-'INPUT-Y'!F128 -> -39.1 | C9: =-'INPUT-Y'!G128 -> -24.4 | D9: =-'INPUT-Y'!H128 -> -40.2 | E9: =-'INPUT-Y'!I128 -> -244.9 | F9: =-'INPUT-Y'!J128 -> -354.4 | G9: =G40 -> -327.34458 | H9: =H40 -> -798.87064 | I9: =I40 -> -768.63812 | J9: =J40 -> -738.40559 | K9: =K40 -> -708.17306
A10: Selling Expenses | B10: =-'INPUT-Y'!F130 -> -0.1 | C10: =-'INPUT-Y'!G130 -> -1 | D10: =-'INPUT-Y'!H130 -> -0.6 | E10: =-'INPUT-Y'!I130 -> -0.6 | F10: =-'INPUT-Y'!J130 -> -1.7 | G10: =G29*G4 -> -1.318243 | H10: =H29*H4 -> -2.7197045 | I10: =I29*I4 -> -3.1760141 | J10: =J29*J4 -> -2.9940492 | K10: =K29*K4 -> -3.0044598
A11: General and admin expenses | B11: =-'INPUT-Y'!F131 -> -51.3 | C11: =-'INPUT-Y'!G131 -> -65.1 | D11: =-'INPUT-Y'!H131 -> -76.6 | E11: =-'INPUT-Y'!I131 -> -111.2 | F11: =-'INPUT-Y'!J131 -> -114.3 | G11: =G33*G4 -> -149.49503 | H11: =H33*H4 -> -292.20532 | I11: =I33*I4 -> -297.10475 | J11: =J33*J4 -> -312.89476 | K11: =K33*K4 -> -305.0858
A12: Net Profit/Loss from Operating activities | B12: ='INPUT-Y'!F132 -> 148.5 | C12: ='INPUT-Y'!G132 -> 239.2 | D12: ='INPUT-Y'!H132 -> 207.1 | E12: ='INPUT-Y'!I132 -> 304.3 | F12: ='INPUT-Y'!J132 -> 303.9 | G12: =G6+G7+SUM(G8,G10,G11) -> 363.4773 | H12: =H6+H7+SUM(H8,H10,H11) -> 446.15716 | I12: =I6+I7+SUM(I8,I10,I11) -> 552.23861 | J12: =J6+J7+SUM(J8,J10,J11) -> 552.15026 | K12: =K6+K7+SUM(K8,K10,K11) -> 574.81292
A13: Other profits/(loss) | B13: ='INPUT-Y'!F135 -> 0.7 | C13: ='INPUT-Y'!G135 -> -8.7 | D13: ='INPUT-Y'!H135 -> -0.2 | E13: ='INPUT-Y'!I135 -> -0.3 | F13: ='INPUT-Y'!J135 -> 4.7 | G13: =F13 -> 4.7 | H13: =G13 -> 4.7 | I13: =H13 -> 4.7 | J13: =I13 -> 4.7 | K13: =J13 -> 4.7
A14: Profit or lost from join venture companies | B14: ='INPUT-Y'!F129 -> 0 | C14: ='INPUT-Y'!G129 -> 0 | D14: ='INPUT-Y'!H129 -> 0 | E14: ='INPUT-Y'!I129 -> 0 | F14: ='INPUT-Y'!J129 -> 0 | G14: 0 | H14: 0 | I14: 0 | J14: 0 | K14: 0
A15: Total profit before tax | B15: ='INPUT-Y'!F136 -> 149.2 | C15: ='INPUT-Y'!G136 -> 230.4 | D15: ='INPUT-Y'!H136 -> 206.9 | E15: ='INPUT-Y'!I136 -> 303.9 | F15: ='INPUT-Y'!J136 -> 308.6 | G15: =SUM(G12:G14) -> 368.1773 | H15: =SUM(H12:H14) -> 450.85716 | I15: =SUM(I12:I14) -> 556.93861 | J15: =SUM(J12:J14) -> 556.85026 | K15: =SUM(K12:K14) -> 579.51292
A16: Current Corporate Income Tax Expenses | B16: =-'INPUT-Y'!F137 -> -13.1 | C16: =-'INPUT-Y'!G137 -> -21.4 | D16: =-'INPUT-Y'!H137 -> -20.6 | E16: =-'INPUT-Y'!I137 -> -13.7 | F16: =-'INPUT-Y'!J137 -> -14.1 | G16: =-7.5%*G15 -> -27.613297 | H16: =-7%*H15 -> -31.560001 | I16: =-7%*I15 -> -38.985702 | J16: =-4.5%*J15 -> -25.058262 | K16: =-5%*K15 -> -28.975646
A17: Deferred Income Taxes Expenses | B17: ='INPUT-Y'!F138 -> 1.8 | C17: ='INPUT-Y'!G138 -> -0.3 | D17: ='INPUT-Y'!H138 -> -1 | E17: ='INPUT-Y'!I138 -> -0.3 | F17: ='INPUT-Y'!J138 -> -0.5 | G17: =AVERAGE(D17:F17) -> -0.6 | H17: =AVERAGE(F17:G17) -> -0.55 | I17: =AVERAGE(G17:H17) -> -0.575 | J17: =AVERAGE(H17:I17) -> -0.5625 | K17: =AVERAGE(I17:J17) -> -0.56875
A18: Net profit after tax | B18: ='INPUT-Y'!F139 -> 134.4 | C18: ='INPUT-Y'!G139 -> 209.3 | D18: ='INPUT-Y'!H139 -> 187.3 | E18: ='INPUT-Y'!I139 -> 290.5 | F18: ='INPUT-Y'!J139 -> 295 | G18: =SUM(G15:G17) -> 339.964 | H18: =SUM(H15:H17) -> 418.74716 | I18: =SUM(I15:I17) -> 517.3779 | J18: =SUM(J15:J17) -> 531.2295 | K18: =SUM(K15:K17) -> 549.96853
A19: Benefits of Minitory shareholders | B19: =-'INPUT-Y'!F140 -> -39.3 | C19: =-'INPUT-Y'!G140 -> -55.5 | D19: =-'INPUT-Y'!H140 -> -42.6 | E19: =-'INPUT-Y'!I140 -> -39.5 | F19: =-'INPUT-Y'!J140 -> -37.6 | G19: =AVERAGE(D19:F19) -> -39.9 | H19: =AVERAGE(E19:G19) -> -39 | I19: =AVERAGE(F19:H19) -> -38.833333 | J19: =AVERAGE(G19:I19) -> -39.244444 | K19: =AVERAGE(H19:J19) -> -39.025926
A20: Net profit after tax attributable to parent company shareholders | B20: ='INPUT-Y'!F141 -> 95.1 | C20: ='INPUT-Y'!G141 -> 153.8 | D20: ='INPUT-Y'!H141 -> 144.7 | E20: ='INPUT-Y'!I141 -> 251 | F20: ='INPUT-Y'!J141 -> 257.4 | G20: =SUM(G18:G19) -> 300.064 | H20: =SUM(H18:H19) -> 379.74716 | I20: =SUM(I18:I19) -> 478.54457 | J20: =SUM(J18:J19) -> 491.98506 | K20: =SUM(K18:K19) -> 510.9426
A21: Basic EPS | B21: 1.276 | C21: 1.798 | D21: 1.254 | E21: 1.06 | F21: =1029/1000 -> 1.029 | G21: =G20/Valuation!$F$56 -> 0.98796259 | H21: =H20/Valuation!$F$56 -> 1.2503199 | I21: =I20/Valuation!$F$56 -> 1.575611 | J21: =J20/Valuation!$F$56 -> 1.6198639 | K21: =K20/Valuation!$F$56 -> 1.6822817
A22: Diluted EPS | E22: 1.06 | F22: =1029/1000 -> 1.029
A23: OPERATING ASSUMPTIONS
A24: Revenue growth | B24: 0 | C24: =Forecast!P18/Forecast!O18 -1 -> 0.24965229 | D24: =Forecast!Q18/Forecast!P18 -1 -> 0.037840846 | E24: =Forecast!R18/Forecast!Q18 -1 -> 1.0722073 | F24: =Forecast!S18/Forecast!R18 -1 -> 0.28799379 | G24: =Forecast!T18/Forecast!S18 -1 -> -0.028996183 | H24: =Forecast!U18/Forecast!T18 -1 -> 1.1944828 | I24: =Forecast!V18/Forecast!U18 -1 -> 0.032055311 | J24: =Forecast!W18/Forecast!V18 -1 -> 0.0015225335 | K24: =Forecast!X18/Forecast!W18 -1 -> 0.0030404378
A25: COGS growth | B25: 0 | C25: =Forecast!C117/Forecast!B117 -1 -> 0.11140584 | D25: =Forecast!D117/Forecast!C117 -1 -> 0.063075349 | E25: =Forecast!E117/Forecast!D117 -1 -> 0.63470173 | F25: =Forecast!F117/Forecast!E117 -1 -> 0.43751226 | G25: =Forecast!G117/Forecast!F117 -1 -> -0.14171833 | H25: =Forecast!H117/Forecast!G117 -1 -> 1.6666866 | I25: =Forecast!I117/Forecast!H117 -1 -> 0.013947328 | J25: =Forecast!J117/Forecast!I117 -1 -> 0.013084271 | K25: =Forecast!K117/Forecast!J117 -1 -> 0.013548821
A26: Gross profit margin | B26: 0 | C26: =C6/B6 -1 -> 0.4243947 | D26: =D6/C6 -1 -> -0.018601668 | E26: =E6/D6 -1 -> 1.1232026 | F26: =F6/E6 -1 -> 0.17254117 | G26: =G6/F6 -1 -> 0.077890552 | H26: =H6/G6 -1 -> 0.83284821 | I26: =I6/H6 -1 -> 0.052232282 | J26: =J6/I6 -1 -> -0.010891495 | K26: =K6/J6 -1 -> -0.0085160847
A28: Selling expense
A29: Selling expense/Net revenue | B29: =B10/B4 -> -0.00023180343 | C29: =C10/C4 -> -0.0018549434 | D29: =D10/D4 -> -0.0010723861 | E29: =E10/E4 -> -0.00051750906 | F29: =F10/F4 -> -0.0011375042 | G29: =AVERAGE(D29:F29) -> -0.0009091331 | H29: =AVERAGE(E29:G29) -> -0.00085471545 | I29: =AVERAGE(F29:H29) -> -0.00096711758 | J29: =AVERAGE(G29:I29) -> -0.00091032204 | K29: =AVERAGE(H29:J29) -> -0.00091071835
A30: Growth rate | C30: =C10/B10 -1 -> 9 | D30: =D10/C10 -1 -> -0.4 | E30: =E10/D10 -1 -> 0 | F30: =F10/E10 -1 -> 1.8333333 | G30: 0.235 | H30: 0.125 | I30: 0.112 | J30: 0.127 | K30: 0.116
A32: G&A expense
A33: G&A expense/Net revenue | B33: =B11/B4 -> -0.11891516 | C33: =C11/C4 -> -0.12075682 | D33: =D11/D4 -> -0.13690795 | E33: =E11/E4 -> -0.095911678 | F33: =F11/F4 -> -0.076480428 | G33: =AVERAGE(D33:F33) -> -0.10310002 | H33: =AVERAGE(E33:G33) -> -0.091830709 | I33: =AVERAGE(F33:H33) -> -0.090470386 | J33: =AVERAGE(G33:I33) -> -0.095133705 | K33: =AVERAGE(H33:J33) -> -0.092478267
A34: Growth rate | C34: =C11/B11 -1 -> 0.26900585 | D34: =D11/C11 -1 -> 0.17665131 | E34: =E11/D11 -1 -> 0.45169713 | F34: =F11/E11 -1 -> 0.027877698 | G34: =G11/F11 -1 -> 0.30791801 | H34: =H11/G11 -1 -> 0.9546156 | I34: =I11/H11 -1 -> 0.016767084 | J34: =J11/I11 -1 -> 0.053146269 | K34: =K11/J11 -1 -> -0.024957127
A36: Financial income | B36: =B7 -> 26.8 | C36: =C7 -> 18 | D36: =D7 -> 19.5 | E36: =E7 -> 24.2 | F36: =F7 -> 30.5 | G36: =G37*G4 -> 36.797895 | H36: =H37*H4 -> 70.70286 | I36: =I37*I4 -> 74.443519 | J36: =J37*J4 -> 77.034999 | K36: =K37*K4 -> 75.118441
A37: Financial income/Net revenue | B37: =B36/B4 -> 0.062123319 | C37: =C36/C4 -> 0.033388982 | D37: =D36/D4 -> 0.034852547 | E37: =E36/E4 -> 0.020872865 | F37: =F36/F4 -> 0.020408163 | G37: =AVERAGE(D37:F37) -> 0.025377858 | H37: =AVERAGE(E37:G37) -> 0.022219629 | I37: =AVERAGE(F37:H37) -> 0.02266855 | J37: =AVERAGE(G37:I37) -> 0.023422013 | K37: =AVERAGE(H37:J37) -> 0.022770064
A39: Financial expenses | B39: =B8 -> -45.8 | C39: =C8 -> -24.6 | D39: =D8 -> -41.1 | E39: =E8 -> -257.8 | F39: =F8 -> -371.2 | G39: =SUM(G40:G41) -> -343.64435 | H39: =SUM(H40:H41) -> -834.6402 | I39: =SUM(I40:I41) -> -805.55427 | J39: =SUM(J40:J41) -> -775.37795 | K39: =SUM(K40:K41) -> -745.25784
A40: Interest expense | B40: =B9 -> -39.1 | C40: =C9 -> -24.4 | D40: =D9 -> -40.2 | E40: =E9 -> -244.9 | F40: =F9 -> -354.4 | G40: =-Debt!J55/1000000 -> -327.34458 | H40: =-Debt!K55/1000000 -> -798.87064 | I40: =-Debt!L55/1000000 -> -768.63812 | J40: =-Debt!M55/1000000 -> -738.40559 | K40: =-Debt!N55/1000000 -> -708.17306
A41: Other financial expense | B41: =B39-B40 -> -6.7 | C41: =C39-C40 -> -0.2 | D41: =D39-D40 -> -0.9 | E41: =E39-E40 -> -12.9 | F41: =F39-F40 -> -16.8 | G41: =G42*G4 -> -16.299766 | H41: =H42*H4 -> -35.769555 | I41: =I42*I4 -> -36.916159 | J41: =J42*J4 -> -36.972365 | K41: =K42*K4 -> -37.084778
A42: Other financial expense/Net revenue | B42: =B41/B4 -> -0.01553083 | C42: =C41/C4 -> -0.00037098868 | D42: =D41/D4 -> -0.0016085791 | E42: =E41/E4 -> -0.011126445 | F42: =F41/F4 -> -0.011241218 | G42: =F42 -> -0.011241218 | H42: =G42 -> -0.011241218 | I42: =H42 -> -0.011241218 | J42: =I42 -> -0.011241218 | K42: =J42 -> -0.011241218

Sheet BS
B1: 2016A | C1: 2017A | D1: 2018A | E1: 2019A | F1: 2020A | G1: 2021F | H1: 2022F | I1: 2023F | J1: 2024F | K1: 2025F
A2: BALANCE SHEET (Billion VND) | B2: HISTORICAL | G2: FORECAST
A4: TOTAL ASSET | B4: ='INPUT-Y'!F65 -> 1551.7 | C4: ='INPUT-Y'!G65 -> 1658.6 | D4: ='INPUT-Y'!H65 -> 4360.6 | E4: ='INPUT-Y'!I65 -> 6763.2 | F4: ='INPUT-Y'!J65 -> 7773.1 | G4: =SUM(G5:G15) -> 16014.356 | H4: =SUM(H5:H15) -> 18523.998 | I4: =SUM(I5:I15) -> 18079.07 | J4: =SUM(J5:J15) -> 17686.418 | K4: =SUM(K5:K15) -> 16776.881
A5: Cash and Cash Equivalents | B5: ='INPUT-Y'!F3 -> 68 | C5: ='INPUT-Y'!G3 -> 223 | D5: ='INPUT-Y'!H3 -> 609.4 | E5: ='INPUT-Y'!I3 -> 105.4 | F5: ='INPUT-Y'!J3 -> 135.4 | G5: =CF!G44 -> 624.6134 | H5: =CF!H44 -> 36.557809 | I5: =CF!I44 -> 46.163367 | J5: =CF!J44 -> 154.57385 | K5: =CF!K44 -> 359.25194
A6: Short term financial investment | B6: ='INPUT-Y'!F6 -> 0 | C6: ='INPUT-Y'!G6 -> 8.2 | D6: ='INPUT-Y'!H6 -> 252 | E6: ='INPUT-Y'!I6 -> 12 | F6: ='INPUT-Y'!J6 -> 0 | G6: =F6 -> 0 | H6: =G6 -> 0 | I6: =H6 -> 0 | J6: =I6 -> 0 | K6: =J6 -> 0
A7: Account Receivables | B7: ='INPUT-Y'!F10 -> 257 | C7: ='INPUT-Y'!G10 -> 227.4 | D7: ='INPUT-Y'!H10 -> 245.5 | E7: ='INPUT-Y'!I10 -> 688.2 | F7: ='INPUT-Y'!J10 -> 1434.3 | G7: =G47*IS!G4 -> 957.15038 | H7: =H47*IS!H4 -> 1941.35 | I7: =I47*IS!I4 -> 1839.3806 | J7: =J47*IS!J4 -> 1677.7311 | K7: =K47*IS!K4 -> 1517.8822
A8: Inventory | B8: ='INPUT-Y'!F19 -> 16.2 | C8: ='INPUT-Y'!G19 -> 26.2 | D8: ='INPUT-Y'!H19 -> 24.7 | E8: ='INPUT-Y'!I19 -> 314.3 | F8: ='INPUT-Y'!J19 -> 152 | G8: =-IS!G5*(G52) -> 231.55152 | H8: =-IS!H5*(H52) -> 406.70973 | I8: =-IS!I5*(I52) -> 463.1404 | J8: =-IS!J5*(J52) -> 528.45203 | K8: =-IS!K5*(K52) -> 526.6112
A9: Other Current Assets | B9: ='INPUT-Y'!F22 -> 0.7 | C9: ='INPUT-Y'!G22 -> 1.1 | D9: ='INPUT-Y'!H22 -> 98.2 | E9: ='INPUT-Y'!I22 -> 70.5 | F9: ='INPUT-Y'!J22 -> 57.6 | G9: =AVERAGE(D9:F9) -> 75.433333 | H9: =AVERAGE(E9:G9) -> 67.844444 | I9: =AVERAGE(F9:H9) -> 66.959259 | J9: =AVERAGE(G9:I9) -> 70.079012 | K9: =AVERAGE(H9:J9) -> 68.294239
A10: Tangible Fixed Assets | B10: ='INPUT-Y'!F38 -> 1163.7 | C10: ='INPUT-Y'!G38 -> 1107.4 | D10: ='INPUT-Y'!H38 -> 2871.2 | E10: ='INPUT-Y'!I38 -> 5239.7 | F10: ='INPUT-Y'!J38 -> 5330.2 | G10: ='PP&E'!G8 -> 10111.45 | H10: ='PP&E'!H8 -> 14947.45 | I10: ='PP&E'!I8 -> 13998.45 | J10: ='PP&E'!J8 -> 13049.45 | K10: ='PP&E'!K8 -> 12100.45
A11: Financial leases fixed assets | B11: ='INPUT-Y'!F41 -> 0 | C11: ='INPUT-Y'!G41 -> 0 | D11: ='INPUT-Y'!H41 -> 0 | E11: ='INPUT-Y'!I41 -> 0 | F11: ='INPUT-Y'!J41 -> 27.8 | G11: 27.8 | H11: 27.8 | I11: 27.8 | J11: 27.8 | K11: 27.8
A12: Intangible Fixed Asset | B12: ='INPUT-Y'!F44 -> 5.6 | C12: ='INPUT-Y'!G44 -> 6.6 | D12: ='INPUT-Y'!H44 -> 6.4 | E12: ='INPUT-Y'!I44 -> 19.2 | F12: ='INPUT-Y'!J44 -> 16.7 | G12: ='PP&E'!G44 -> 7.6570313 | H12: ='PP&E'!H44 -> 10.085547 | I12: ='PP&E'!I44 -> 10.97627 | J12: ='PP&E'!J44 -> 12.132251 | K12: ='PP&E'!K44 -> 10.39129
A13: Construction in progress | B13: ='INPUT-Y'!F50 -> 5.6 | C13: ='INPUT-Y'!G50 -> 18 | D13: ='INPUT-Y'!H50 -> 215.8 | E13: ='INPUT-Y'!I50 -> 262.8 | F13: ='INPUT-Y'!J50 -> 541.4 | G13: ='PP&E'!G35 -> 3839.9 | H13: ='PP&E'!H35 -> 947.4 | I13: ='PP&E'!I35 -> 1487.4 | J13: ='PP&E'!J35 -> 2027.4 | K13: ='PP&E'!K35 -> 2027.4
A14: Long term Finacial Investments | B14: ='INPUT-Y'!F53 -> 0.2 | C14: ='INPUT-Y'!G53 -> 0 | D14: ='INPUT-Y'!H53 -> 0 | E14: ='INPUT-Y'!I53 -> 2.6 | F14: ='INPUT-Y'!J53 -> 0 | G14: =87 -> 87 | H14: =G14 -> 87 | I14: =H14 -> 87 | J14: =I14 -> 87 | K14: =J14 -> 87
A15: Other long term assets | B15: ='INPUT-Y'!F59 -> 34 | C15: ='INPUT-Y'!G59 -> 29.8 | D15: ='INPUT-Y'!H59 -> 36.5 | E15: ='INPUT-Y'!I59 -> 47.9 | F15: ='INPUT-Y'!J59 -> 51.8 | G15: =F15 -> 51.8 | H15: =G15 -> 51.8 | I15: =H15 -> 51.8 | J15: =I15 -> 51.8 | K15: =J15 -> 51.8
A17: LIABILITIES | B17: ='INPUT-Y'!F66 -> 401 | C17: ='INPUT-Y'!G66 -> 340.6 | D17: ='INPUT-Y'!H66 -> 1952.6 | E17: ='INPUT-Y'!I66 -> 4183.6 | F17: ='INPUT-Y'!J66 -> 4305.2 | G17: =SUM(G18:G23) -> 11874.588 | H17: =SUM(H18:H23) -> 13907.156 | I17: =SUM(I18:I23) -> 12837.723 | J17: =SUM(J18:J23) -> 11905.551 | K17: =SUM(K18:K23) -> 10436.556
A18: Account Payables | B18: ='INPUT-Y'!F67-'INPUT-Y'!F77 -> 89.9 | C18: ='INPUT-Y'!G67-'INPUT-Y'!G77 -> 97.5 | D18: ='INPUT-Y'!H67-'INPUT-Y'!H77 -> 421.8 | E18: ='INPUT-Y'!I67-'INPUT-Y'!I77 -> 282.8 | F18: ='INPUT-Y'!J67-'INPUT-Y'!J77 -> 500.2 | G18: 2500 | H18: =-IS!H5*H57 -> 2800.2076 | I18: =-IS!I5*I57 -> 2271.4104 | J18: =-IS!J5*J57 -> 1840.9041 | K18: =-IS!K5*K57 -> 1492.677
A19: Short-term borrowings | B19: ='INPUT-Y'!F77 -> 45.2 | C19: ='INPUT-Y'!G77 -> 5.9 | D19: ='INPUT-Y'!H77 -> 106.4 | E19: ='INPUT-Y'!I77 -> 553.6 | F19: ='INPUT-Y'!J77 -> 600.9 | G19: =G64 -> 660.99 | H19: =H64 -> 727.089 | I19: =I64 -> 799.7979 | J19: =J64 -> 879.77769 | K19: =K64 -> 967.75546
A20: Other long-term payables | B20: ='INPUT-Y'!F83+'INPUT-Y'!F88+ 'INPUT-Y'!F94 -> 0.5 | C20: ='INPUT-Y'!G83+'INPUT-Y'!G88+ 'INPUT-Y'!G94 -> 3.9 | D20: ='INPUT-Y'!H83+'INPUT-Y'!H88+ 'INPUT-Y'!H94 -> 3.6 | E20: ='INPUT-Y'!I83+'INPUT-Y'!I88+ 'INPUT-Y'!I94 -> 3.5 | F20: ='INPUT-Y'!J83+'INPUT-Y'!J88+ 'INPUT-Y'!J94 -> 3.2 | G20: =F20 -> 3.2 | H20: =G20 -> 3.2 | I20: =H20 -> 3.2 | J20: =I20 -> 3.2 | K20: =J20 -> 3.2
A21: Long-term borrowings | B21: ='INPUT-Y'!F90 -> 264.5 | C21: ='INPUT-Y'!G90 -> 232.4 | D21: ='INPUT-Y'!H90 -> 1420.3 | E21: ='INPUT-Y'!I90 -> 3343.1 | F21: ='INPUT-Y'!J90 -> 3200.6 | G21: =Debt!J52/1000000 -> 8672.3132 | H21: =Debt!K52/1000000 -> 10336.701 | I21: =Debt!L52/1000000 -> 9721.388 | J21: =Debt!M52/1000000 -> 9137.6753 | K21: =Debt!N52/1000000 -> 7926.7605
A22: Bonus and welfare funds | B22: ='INPUT-Y'!F79 -> 13.6 | C22: ='INPUT-Y'!G79 -> 17.3 | D22: ='INPUT-Y'!H79 -> 20.8 | E22: ='INPUT-Y'!I79 -> 31.6 | F22: ='INPUT-Y'!J79 -> 35.7 | G22: =F22*1.05 -> 37.485 | H22: =G22*1.05 -> 39.35925 | I22: =H22*1.05 -> 41.327213 | J22: =I22*1.05 -> 43.393573 | K22: =J22*1.05 -> 45.563252
A23: Technology-science development fund | B23: ='INPUT-Y'!F95 -> 0.9 | C23: ='INPUT-Y'!G95 -> 0.9 | D23: ='INPUT-Y'!H95 -> 0.6 | E23: ='INPUT-Y'!I95 -> 0.6 | F23: ='INPUT-Y'!J95 -> 0.3 | G23: =$E$23 -> 0.6 | H23: =$E$23 -> 0.6 | I23: =$E$23 -> 0.6 | J23: =$E$23 -> 0.6 | K23: =$E$23 -> 0.6
A25: OWNERS EQUITY | B25: ='INPUT-Y'!F96 -> 1150.7 | C25: ='INPUT-Y'!G96 -> 1318 | D25: ='INPUT-Y'!H96 -> 2408 | E25: ='INPUT-Y'!I96 -> 2579.6 | F25: ='INPUT-Y'!J96 -> 3467.9 | G25: =SUM(G26:G33) -> 4139.7675 | H25: =SUM(H26:H33) -> 4616.8411 | I25: =SUM(I26:I33) -> 5241.3464 | J25: =SUM(J26:J33) -> 5780.8675 | K25: =SUM(K26:K33) -> 6340.3246
A26: Common stock | B26: ='INPUT-Y'!F99 -> 744.9 | C26: ='INPUT-Y'!G99 -> 970.9 | D26: ='INPUT-Y'!H99 -> 1941.8 | E26: ='INPUT-Y'!I99 -> 2038.9 | F26: ='INPUT-Y'!J99 -> 2711.8 | G26: 3037 | H26: =G26 -> 3037 | I26: =H26 -> 3037 | J26: =I26 -> 3037 | K26: =J26 -> 3037
A27: Share premium | B27: ='INPUT-Y'!F101 -> 2 | C27: ='INPUT-Y'!G101 -> 28.9 | D27: ='INPUT-Y'!H101 -> 29 | E27: ='INPUT-Y'!I101 -> 38.7 | F27: ='INPUT-Y'!J101 -> 38.2 | G27: =F27 -> 38.2 | H27: =G27 -> 38.2 | I27: =H27 -> 38.2 | J27: =I27 -> 38.2 | K27: =J27 -> 38.2
A28: Other capitals of Owners Equity | B28: ='INPUT-Y'!F103 -> 0 | C28: ='INPUT-Y'!G103 -> 0 | D28: ='INPUT-Y'!H103 -> 0 | E28: ='INPUT-Y'!I103 -> 0 | F28: ='INPUT-Y'!J103 -> 0 | G28: =F28 -> 0 | H28: =G28 -> 0 | I28: =H28 -> 0 | J28: =I28 -> 0 | K28: =J28 -> 0
A29: Treasury stock | B29: ='INPUT-Y'!F104 -> 0 | C29: ='INPUT-Y'!G104 -> 0 | D29: ='INPUT-Y'!H104 -> 0 | E29: ='INPUT-Y'!I104 -> 0 | F29: ='INPUT-Y'!J104 -> 0 | G29: =F29 -> 0 | H29: =G29 -> 0 | I29: =H29 -> 0 | J29: =I29 -> 0 | K29: =J29 -> 0
A30: Development and Investment Fund | B30: ='INPUT-Y'!F107 -> 49.1 | C30: ='INPUT-Y'!G107 -> 56.3 | D30: ='INPUT-Y'!H107 -> 61 | E30: ='INPUT-Y'!I107 -> 78.8 | F30: ='INPUT-Y'!J107 -> 87.3 | G30: =F30*1.05 -> 91.665 | H30: =G30*1.05 -> 96.24825 | I30: =H30*1.05 -> 101.06066 | J30: =I30*1.05 -> 106.1137 | K30: =J30*1.05 -> 111.41938
A31: Retained earnings | B31: ='INPUT-Y'!F110 -> 168.4 | C31: ='INPUT-Y'!G110 -> 120 | D31: ='INPUT-Y'!H110 -> 145.1 | E31: ='INPUT-Y'!I110 -> 164.8 | F31: ='INPUT-Y'!J110 -> 220 | G31: ='Owners equity'!G29 -> 559.964 | H31: ='Owners equity'!H29 -> 978.71116 | I31: ='Owners equity'!I29 -> 1496.0891 | J31: ='Owners equity'!J29 -> 2027.3186 | K31: ='Owners equity'!K29 -> 2577.2871
A32: Minority interest | B32: ='INPUT-Y'!F114 -> 186.4 | C32: ='INPUT-Y'!G114 -> 141.8 | D32: ='INPUT-Y'!H114 -> 231.1 | E32: ='INPUT-Y'!I114 -> 258.5 | F32: ='INPUT-Y'!J114 -> 410.7 | G32: =(0.5*G73*IS!G18)+F32 -> 412.8825 | H32: =(0.5*H73*IS!H18)+G32 -> 415.17413 | I32: =(0.5*I73*IS!I18)+H32 -> 417.58033 | J32: =(0.5*J73*IS!J18)+I32 -> 420.10685 | K32: =(0.5*K73*IS!K18)+J32 -> 422.75969
A33: Forecasting Discrepancies | G33: =-SUM(G26:G32)-SUM(G18:G23)+SUM(G5:G15) -> 0.055957917 | H33: =-SUM(H26:H32)-SUM(H18:H23)+SUM(H5:H15) -> 51.507571 | I33: =-SUM(I26:I32)-SUM(I18:I23)+SUM(I5:I15) -> 151.41634 | J33: =-SUM(J26:J32)-SUM(J18:J23)+SUM(J5:J15) -> 152.12842 | K33: =-SUM(K26:K32)-SUM(K18:K23)+SUM(K5:K15) -> 153.65846
A34: Balance check | B34: =SUM(B25,B17)-B4 -> 0 | C34: =SUM(C25,C17)-C4 -> 0 | D34: =SUM(D25,D17)-D4 -> 0 | E34: =SUM(E25,E17)-E4 -> 0 | F34: =SUM(F25,F17)-F4 -> 0 | G34: =SUM(G25,G17)-G4 -> 0 | H34: =SUM(H25,H17)-H4 -> 0 | I34: =SUM(I25,I17)-I4 -> 0 | ... K34: =SUM(K25,K17)-K4 -> 0
A44: WORKING CAPITAL
A46: Account receivable
A47: Account receivable/Net revenue | C47: =AVERAGE(B7:C7)/IS!C4 -> 0.4492673 | D47: =AVERAGE(C7:D7)/IS!D4 -> 0.42260947 | E47: =AVERAGE(D7:E7)/IS!E4 -> 0.40266517 | F47: =AVERAGE(E7:F7)/IS!F4 -> 0.71010371 | G47: =F47-5% -> 0.66010371 | H47: =G47-5% -> 0.61010371 | I47: =H47-5% -> 0.56010371 | J47: =I47-5% -> 0.51010371 | K47: =J47-5% -> 0.46010371
A48: Receivable turnover | C48: =IS!C4/AVERAGE(B7:C7) -> 2.2258464 | D48: =IS!D4/AVERAGE(C7:D7) -> 2.3662508 | E48: =IS!E4/AVERAGE(D7:E7) -> 2.4834529 | F48: =IS!F4/AVERAGE(E7:F7) -> 1.408245 | G48: =1/G47 -> 1.5149135 | H48: =1/H47 -> 1.6390656 | I48: =1/I47 -> 1.7853836 | J48: =1/J47 -> 1.9603856 | K48: =1/K47 -> 2.173423
A49: Days of sales outstanding (DSO) | C49: =365/C48 -> 163.98256 | D49: =365/D48 -> 154.25246 | E49: =365/E48 -> 146.97279 | F49: =365/F48 -> 259.18786 | G49: =360/G48 -> 237.63734 | H49: =360/H48 -> 219.63734 | I49: =360/I48 -> 201.63734 | J49: =360/J48 -> 183.63734 | K49: =360/K48 -> 165.63734
A51: Inventory
A52: Inventory/COGS | C52: =AVERAGE(B8:C8)/-IS!C5 -> 0.093268808 | D52: =AVERAGE(C8:D8)/-IS!D5 -> 0.10039448 | E52: =AVERAGE(D8:E8)/-IS!E5 -> 0.33254856 | F52: =AVERAGE(E8:F8)/-IS!F5 -> 0.31820663 | G52: =$F$52+5% -> 0.36820663 | H52: =AVERAGE(C52:G52) -> 0.24252502 | I52: =AVERAGE(D52:H52) -> 0.27237626 | J52: =AVERAGE(E52:I52) -> 0.30677262 | K52: =AVERAGE(F52:J52) -> 0.30161743
A53: Inventory turnover | C53: =-IS!C5/AVERAGE(B8:C8) -> 10.721698 | D53: =-IS!D5/AVERAGE(C8:D8) -> 9.9607073 | E53: =-IS!E5/AVERAGE(D8:E8) -> 3.0070796 | F53: =-IS!F5/AVERAGE(E8:F8) -> 3.1426121 | G53: =1/G52 -> 2.7158663 | H53: =1/H52 -> 4.1232859 | I53: =1/I52 -> 3.6713919 | J53: =1/J52 -> 3.2597433 | K53: =1/K52 -> 3.3154582
A54: Days of inventory on hand (DOH) | C54: =360/C53 -> 33.576771 | D54: =360/D53 -> 36.142012 | E54: =360/E53 -> 119.71748 | F54: =360/F53 -> 114.55439 | G54: =360/G53 -> 132.55439 | H54: =360/H53 -> 87.309008 | I54: =360/I53 -> 98.055455 | J54: =360/J53 -> 110.43814 | K54: =360/K53 -> 108.58228
A56: Account payable
A57: Account payable/COGS | C57: =AVERAGE(B18:C18)/-IS!C5 -> 0.41223053 | D57: =AVERAGE(C18:D18)/-IS!D5 -> 1.0242604 | E57: =AVERAGE(D18:E18)/-IS!E5 -> 0.6911909 | F57: =AVERAGE(E18:F18)/-IS!F5 -> 0.5343251 | G57: =AVERAGE(F18:G18)/-IS!G5 -> 2.3854163 | H57: =G57*0.7 -> 1.6697914 | I57: =H57*0.8 -> 1.3358331 | J57: =I57*0.8 -> 1.0686665 | K57: =J57*0.8 -> 0.8549332
A58: Payables turnover | C58: =-IS!C5/AVERAGE(B18:C18) -> 2.4258271 | D58: =-IS!D5/AVERAGE(C18:D18) -> 0.97631427 | E58: =-IS!E5/AVERAGE(D18:E18) -> 1.4467783 | F58: =-IS!F5/AVERAGE(E18:F18) -> 1.8715198 | G58: =1/G57 -> 0.41921404 | H58: =1/H57 -> 0.5988772 | I58: =1/I57 -> 0.7485965 | J58: =1/J57 -> 0.93574562 | K58: =1/K57 -> 1.169682
A59: Days payable outstanding (DPO) | C59: =360/C58 -> 148.40299 | D59: =360/D58 -> 368.73373 | E59: =360/E58 -> 248.82872 | F59: =360/F58 -> 192.35704 | G59: =360/G58 -> 858.74987 | H59: =360/H58 -> 601.12491 | I59: =360/I58 -> 480.89993 | J59: =360/J58 -> 384.71994 | K59: =360/K58 -> 307.77595
A61: Short term borrowings
A62: Beginning of period | B62: 0 | C62: =B19 -> 45.2 | D62: =C19 -> 5.9 | E62: =D19 -> 106.4 | F62: =E19 -> 553.6 | G62: =F64 -> 600.9 | H62: =G64 -> 660.99 | I62: =H64 -> 727.089 | J62: =I64 -> 799.7979 | K62: =J64 -> 879.77769
A63: Increases / (decreases) | B63: 0 | C63: =C64-C62 -> -39.3 | D63: =D64-D62 -> 100.5 | E63: =E64-E62 -> 447.2 | F63: =F64-F62 -> 47.3 | G63: =0.1*G62 -> 60.09 | H63: =0.1*H62 -> 66.099 | I63: =0.1*I62 -> 72.7089 | J63: =0.1*J62 -> 79.97979 | K63: =0.1*K62 -> 87.977769
A64: End of period | B64: 0 | C64: =C19 -> 5.9 | D64: =D19 -> 106.4 | E64: =E19 -> 553.6 | F64: =F19 -> 600.9 | G64: =SUM(G62:G63) -> 660.99 | H64: =SUM(H62:H63) -> 727.089 | I64: =SUM(I62:I63) -> 799.7979 | J64: =SUM(J62:J63) -> 879.77769 | K64: =SUM(K62:K63) -> 967.75546
A66: Bonus and welfare funds
A67: Bonus and welfare funds (from Net income) | C67: =(C22-B22)/IS!C18 -> 0.017677974 | D67: =(D22-C22)/IS!D18 -> 0.018686599 | E67: =(E22-D22)/IS!E18 -> 0.037177281 | F67: =(F22-E22)/IS!F18 -> 0.013898305 | G67: =(G22-F22)/IS!G18 -> 0.005250556 | H67: =(H22-G22)/IS!H18 -> 0.0044758513 | I67: =(I22-H22)/IS!I18 -> 0.0038037235 | J67: =(J22-I22)/IS!J18 -> 0.0038897701 | K67: =(K22-J22)/IS!K18 -> 0.003945096
A69: Technology-science development fund
A70: %Increase/Net income | C70: =(C23-B23)/IS!C18 -> 0 | D70: =(D23-C23)/IS!D18 -> -0.0016017085 | E70: =(E23-D23)/IS!E18 -> 0 | F70: =(F23-E23)/IS!F18 -> -0.0010169492 | G70: =(G23-F23)/IS!G18 -> 0.00088244638 | H70: =(H23-G23)/IS!H18 -> 0 | I70: =(I23-H23)/IS!I18 -> 0 | J70: =(J23-I23)/IS!J18 -> 0 | K70: =(K23-J23)/IS!K18 -> 0
A72: Development and Investment Fund | C72: =C37 -> 0 | D72: =D37 -> 0 | E72: =E37 -> 0 | F72: =F37 -> 0
A73: %Increase/Net income | C73: =(C30-B30)/IS!C18 -> 0.034400382 | D73: =(D30-C30)/IS!D18 -> 0.025093433 | E73: =(E30-D30)/IS!E18 -> 0.061273666 | F73: =(F30-E30)/IS!F18 -> 0.028813559 | G73: =(G30-F30)/IS!G18 -> 0.012839595 | H73: =(H30-G30)/IS!H18 -> 0.010945149 | I73: =(I30-H30)/IS!I18 -> 0.0093015424 | J73: =(J30-I30)/IS!J18 -> 0.0095119588 | K73: =(K30-J30)/IS!K18 -> 0.0096472516
A78: 438.94662 | B78: 579.83525 | C78: 307.08794 | D78: 467.06507 | E78: 666.84079
A82: APCapex | C82: =AVERAGE(B18:C18)/-CF!B25 -> 2.3135802 | D82: =AVERAGE(C18:D18)/-CF!C25 -> 5.5480769 | E82: =AVERAGE(D18:E18)/-CF!D25 -> 0.19464088 | F82: =AVERAGE(E18:F18)/-CF!E25 -> 0.14675563 | G82: =AVERAGE(F18:G18)/-CF!F25 -> 1.9249326 | H82: =AVERAGE(G18:H18)/-CF!G25 -> 0.3158834 | I82: =AVERAGE(H18:I18)/-CF!H25 -> 0.88278817 | J82: =AVERAGE(I18:J18)/-CF!I25 -> 3.9541486 | K82: =AVERAGE(J18:K18)/-CF!J25 -> 3.2053664
A83: Ar/capex | C83: =AVERAGE(B7:C7)/-CF!B25 -> 5.9802469 | D83: =AVERAGE(C7:D7)/-CF!C25 -> 5.0523504 | E83: =AVERAGE(D7:E7)/-CF!D25 -> 0.25792818 | F83: =AVERAGE(E7:F7)/-CF!E25 -> 0.3978146 | G83: =AVERAGE(F7:G7)/-CF!F25 -> 1.534358 | H83: =AVERAGE(G7:H7)/-CF!G25 -> 0.17274572 | I83: =AVERAGE(H7:I7)/-CF!H25 -> 0.65809062 | J83: =AVERAGE(I7:J7)/-CF!I25 -> 3.3818382 | K83: =AVERAGE(J7:K7)/-CF!J25 -> 3.0727051

Sheet CF
B1: 2016 | C1: 2017 | D1: 2018 | E1: 2019 | F1: 2020 | G1: 2021F | H1: 2022F | I1: 2023F | J1: 2024F | K1: 2025F
A2: CASH FLOW STATEMENT | B2: HISTORICAL | G2: FORECAST
A4: I. CASH FLOWS FROM OPERATING ACTIVITIES (INDIRECT MEHOD)
A5: Total profit before tax | B5: ='INPUT-Y'!F145 -> 149.2 | C5: ='INPUT-Y'!G145 -> 230.4 | D5: ='INPUT-Y'!H145 -> 206.9 | E5: ='INPUT-Y'!I145 -> 303.9 | F5: ='INPUT-Y'!J145 -> 308.6 | G5: =IS!G15 -> 368.1773 | H5: =IS!H15 -> 450.85716 | I5: =IS!I15 -> 556.93861 | J5: =IS!J15 -> 556.85026 | K5: =IS!K15 -> 579.51292
A6: Adjustments | B6: ='INPUT-Y'!F146 -> 0 | C6: ='INPUT-Y'!G146 -> 0 | D6: ='INPUT-Y'!H146 -> 0 | E6: ='INPUT-Y'!I146 -> 0 | F6: ='INPUT-Y'!J146 -> 0
A7: 1. Depreciation of Fixed Assets Expenses | B7: ='INPUT-Y'!F147 -> 79.8 | C7: ='INPUT-Y'!G147 -> 79.5 | D7: ='INPUT-Y'!H147 -> 97.5 | E7: ='INPUT-Y'!I147 -> 285 | F7: ='INPUT-Y'!J147 -> 354 | G7: =Forecast!G120 -> 349.75 | H7: =Forecast!H120 -> 969 | I7: =Forecast!I120 -> 969 | J7: =Forecast!J120 -> 969 | K7: =Forecast!K120 -> 969
A8: 2. Provisions | B8: ='INPUT-Y'!F148 -> 0 | C8: ='INPUT-Y'!G148 -> 0.3 | D8: ='INPUT-Y'!H148 -> 0.3 | E8: ='INPUT-Y'!I148 -> 0.5 | F8: ='INPUT-Y'!J148 -> -0.4
A9: 3. Unrealised foreign exchange gain/(loss) | B9: ='INPUT-Y'!F150 -> 0 | C9: ='INPUT-Y'!G150 -> 0 | D9: ='INPUT-Y'!H150 -> 0.8 | E9: ='INPUT-Y'!I150 -> 0.5 | F9: ='INPUT-Y'!J150 -> 1.4 | G9: =F9 -> 1.4 | H9: =G9 -> 1.4 | I9: =H9 -> 1.4 | J9: =I9 -> 1.4 | K9: =J9 -> 1.4
A10: 4. Profit/(loss) from liquidating fixed assets | B10: ='INPUT-Y'!F151 -> 0 | C10: ='INPUT-Y'!G151 -> 0 | D10: ='INPUT-Y'!H151 -> 0 | E10: ='INPUT-Y'!I151 -> 0 | F10: ='INPUT-Y'!J151 -> 0
A11: 5. Interest Expenses | B11: ='INPUT-Y'!F152 -> 39.1 | C11: ='INPUT-Y'!G152 -> 24.4 | D11: ='INPUT-Y'!H152 -> 40.2 | E11: ='INPUT-Y'!I152 -> 247.3 | F11: ='INPUT-Y'!J152 -> 357.9 | G11: =-IS!G9 -> 327.34458 | H11: =-IS!H9 -> 798.87064 | I11: =-IS!I9 -> 768.63812 | J11: =-IS!J9 -> 738.40559 | K11: =-IS!K9 -> 708.17306
A12: 6. Other deductions | B12: ='INPUT-Y'!F153 -> 0.9 | C12: ='INPUT-Y'!G153 -> 0 | D12: ='INPUT-Y'!H153 -> 0 | E12: ='INPUT-Y'!I153 -> 0 | F12: ='INPUT-Y'!J153 -> 0
A13: Operating profit/(loss) before changes in Working Capital | B13: ='INPUT-Y'!F157 -> 242 | C13: ='INPUT-Y'!G157 -> 323.5 | D13: ='INPUT-Y'!H157 -> 326.6 | E13: ='INPUT-Y'!I157 -> 813.5 | F13: ='INPUT-Y'!J157 -> 995.7 | G13: =SUM(G5:G11) -> 1046.6719 | H13: =SUM(H5:H11) -> 2220.1278 | I13: =SUM(I5:I11) -> 2295.9767 | J13: =SUM(J5:J11) -> 2265.6559 | K13: =SUM(K5:K11) -> 2258.086
A14: Other adjustments | B14: ='INPUT-Y'!F158 -> -11.2 | C14: ='INPUT-Y'!G158 -> -18.1 | D14: ='INPUT-Y'!H158 -> -95.2 | E14: ='INPUT-Y'!I158 -> -295.7 | F14: ='INPUT-Y'!J158 -> -667.3 | G14: =-(BS!G7-BS!F7) -> 477.14962 | H14: =-(BS!H7-BS!G7) -> -984.19963 | I14: =-(BS!I7-BS!H7) -> 101.96942 | J14: =-(BS!J7-BS!I7) -> 161.64948 | K14: =-(BS!K7-BS!J7) -> 159.84896
A15: 1. (Increase)/decrease in receivables | B15: ='INPUT-Y'!F160 -> -5.9 | C15: ='INPUT-Y'!G160 -> -10 | D15: ='INPUT-Y'!H160 -> 0.8 | E15: ='INPUT-Y'!I160 -> -289.4 | F15: ='INPUT-Y'!J160 -> 161.8 | G15: =-(BS!G8-BS!F8) -> -79.55152 | H15: =-(BS!H8-BS!G8) -> -175.15821 | I15: =-(BS!I8-BS!H8) -> -56.430668 | J15: =-(BS!J8-BS!I8) -> -65.311638 | K15: =-(BS!K8-BS!J8) -> 1.8408355
A16: 2. (Increase)/decrease in inventories | B16: ='INPUT-Y'!F161 -> 10 | C16: ='INPUT-Y'!G161 -> 3.1 | D16: ='INPUT-Y'!H161 -> 7.7 | E16: ='INPUT-Y'!I161 -> -282.4 | F16: ='INPUT-Y'!J161 -> 324.8 | G16: =BS!G18-BS!F18 -> 1999.8 | H16: =BS!H18-BS!G18 -> 300.20761 | I16: =BS!I18-BS!H18 -> -528.79719 | J16: =BS!J18-BS!I18 -> -430.50628 | K16: =BS!K18-BS!J18 -> -348.22716
A17: 3. Increase/(decrease) in payables | B17: =-('INPUT-Y'!F22-'INPUT-Y'!E22) -> 4.4 | C17: =-('INPUT-Y'!G22-'INPUT-Y'!F22) -> -0.4 | D17: =-('INPUT-Y'!H22-'INPUT-Y'!G22) -> -97.1 | E17: =-('INPUT-Y'!I22-'INPUT-Y'!H22) -> 27.7 | F17: =-('INPUT-Y'!J22-'INPUT-Y'!I22) -> 12.9 | G17: =BS!G9-BS!F9 -> 17.833333 | H17: =BS!H9-BS!G9 -> -7.5888889 | I17: =BS!I9-BS!H9 -> -0.88518519 | J17: =BS!J9-BS!I9 -> 3.1197531 | K17: =BS!K9-BS!J9 -> -1.7847737
A18: 6. Interest paid | B18: ='INPUT-Y'!F163 -> -42.6 | C18: ='INPUT-Y'!G163 -> -31.3 | D18: ='INPUT-Y'!H163 -> -50.1 | E18: ='INPUT-Y'!I163 -> -246.7 | F18: ='INPUT-Y'!J163 -> -356.2 | G18: =IS!G9 + 74 -> -253.34458 | H18: =IS!H9 - 19 -> -817.87064 | I18: =IS!I9 - 32 -> -800.63812 | J18: =IS!J9 - 39 -> -777.40559 | K18: =IS!K9 - 25 -> -733.17306
A19: 7. Income Tax paid | B19: ='INPUT-Y'!F164 -> -19.4 | C19: ='INPUT-Y'!G164 -> -16.9 | D19: ='INPUT-Y'!H164 -> -25.8 | E19: ='INPUT-Y'!I164 -> -13 | F19: ='INPUT-Y'!J164 -> -11.3 | G19: =IS!G16 -> -27.613297 | H19: =IS!H16 -> -31.560001 | I19: =IS!I16 -> -38.985702 | J19: =IS!J16 -> -25.058262 | K19: =IS!K16 -> -28.975646
A20: 8. Other Incomes from Operating Activities | B20: ='INPUT-Y'!F165 -> 0 | C20: ='INPUT-Y'!G165 -> 0 | D20: ='INPUT-Y'!H165 -> 0 | E20: ='INPUT-Y'!I165 -> 0 | F20: ='INPUT-Y'!J165 -> 0
A21: 9. Other Expenses from Operating Activities | B21: ='INPUT-Y'!F166 -> -6.4 | C21: ='INPUT-Y'!G166 -> -10.9 | D21: ='INPUT-Y'!H166 -> -12.3 | E21: ='INPUT-Y'!I166 -> -5.9 | F21: ='INPUT-Y'!J166 -> -18.4
A22: Net cashflow from operating activities | B22: ='INPUT-Y'!F144 -> 168.4 | C22: ='INPUT-Y'!G144 -> 243.8 | D22: ='INPUT-Y'!H144 -> 141.1 | E22: ='INPUT-Y'!I144 -> -332.8 | F22: ='INPUT-Y'!J144 -> 420.6 | G22: =SUM(G13:G19) -> 3180.9454 | H22: =SUM(H13:H19) -> 503.95804 | I22: =SUM(I13:I19) -> 972.20928 | J22: =SUM(J13:J19) -> 1132.1433 | K22: =SUM(K13:K19) -> 1307.6151
A24: II. CASH FLOWS FROM INVESTING ACTIVITIES
A25: 1. Purchases of fixed assets and other long term assets | B25: ='INPUT-Y'!F168 -> -40.5 | C25: ='INPUT-Y'!G168 -> -46.8 | D25: ='INPUT-Y'!H168 -> -1810 | E25: ='INPUT-Y'!I168 -> -2667.7 | F25: ='INPUT-Y'!J168 -> -779.3 | G25: =-(BS!G15-BS!F15-'PP&E'!G6+'PP&E'!G30+'PP&E'!G41) -> -8389.5 | H25: =-(BS!H15-BS!G15-'PP&E'!H6+'PP&E'!H30+'PP&E'!H41) -> -2872.5 | I25: =-(BS!I15-BS!H15-'PP&E'!I6+'PP&E'!I30+'PP&E'!I41) -> -520 | J25: =-(BS!J15-BS!I15-'PP&E'!J6+'PP&E'!J30+'PP&E'!J41) -> -520 | K25: =-(BS!K15-BS!J15-'PP&E'!K6+'PP&E'!K30+'PP&E'!K41) -> 20
A26: 2. Proceeds from disposal of fixed assets | B26: ='INPUT-Y'!F169 -> 0.9 | C26: ='INPUT-Y'!G169 -> 2.7 | D26: ='INPUT-Y'!H169 -> 0.2 | E26: ='INPUT-Y'!I169 -> 2.8 | F26: ='INPUT-Y'!J169 -> 32.1
A27: 3. Changes in ST-LT Financial Investments | B27: =-('INPUT-Y'!F6+'INPUT-Y'!F53-'INPUT-Y'!E53-'INPUT-Y'!E6) -> 0.7 | C27: =-('INPUT-Y'!G6+'INPUT-Y'!G53-'INPUT-Y'!F53-'INPUT-Y'!F6) -> -8 | D27: =-('INPUT-Y'!H6+'INPUT-Y'!H53-'INPUT-Y'!G53-'INPUT-Y'!G6) -> -243.8 | E27: =-('INPUT-Y'!I6+'INPUT-Y'!I53-'INPUT-Y'!H53-'INPUT-Y'!H6) -> 237.4 | F27: =-('INPUT-Y'!J6+'INPUT-Y'!J53-'INPUT-Y'!I53-'INPUT-Y'!I6) -> 14.6 | G27: =- ((BS!G6-BS!F6)+(BS!G14-BS!F14)) -> -87 | H27: =- ((BS!H6-BS!G6)+(BS!H14-BS!G14)) -> 0 | I27: =- ((BS!I6-BS!H6)+(BS!I14-BS!H14)) -> 0 | J27: =- ((BS!J6-BS!I6)+(BS!J14-BS!I14)) -> 0 | K27: =- ((BS!K6-BS!J6)+(BS!K14-BS!J14)) -> 0
A28: 4. Interest, dividends, shared profit from investments | B28: ='INPUT-Y'!F174 -> 15.7 | C28: ='INPUT-Y'!G174 -> 21.4 | D28: ='INPUT-Y'!H174 -> 13.9 | E28: ='INPUT-Y'!I174 -> 22.7 | F28: ='INPUT-Y'!J174 -> 20.4 | G28: 14
A29: 5. Changes in other LT assets | B29: ='INPUT-Y'!F167 - SUM(B25:B28) -> 114.1 | C29: ='INPUT-Y'!G167 - SUM(C25:C28) -> 35.3 | D29: ='INPUT-Y'!H167 - SUM(D25:D28) -> 93.8 | E29: ='INPUT-Y'!I167 - SUM(E25:E28) -> -237.3 | F29: ='INPUT-Y'!J167 - SUM(F25:F28) -> -225
A30: Net Cash flow from Investing activities | B30: ='INPUT-Y'!F167 -> 90.9 | C30: ='INPUT-Y'!G167 -> 4.6 | D30: ='INPUT-Y'!H167 -> -1945.9 | E30: ='INPUT-Y'!I167 -> -2642.1 | F30: ='INPUT-Y'!J167 -> -937.2 | G30: =SUM(G25:G29) -> -8462.5 | H30: =SUM(H25:H29) -> -2872.5 | I30: =SUM(I25:I29) -> -520 | J30: =SUM(J25:J29) -> -520 | K30: =SUM(K25:K29) -> 20
A32: III. CASH FLOWS FROM FINANCING ACTIVITIES
A33: Proceeds from issue of shares | B33: ='INPUT-Y'!F177 -> 0 | C33: ='INPUT-Y'!G177 -> 1 | D33: ='INPUT-Y'!H177 -> 1049.8 | E33: ='INPUT-Y'!I177 -> 270.3 | F33: ='INPUT-Y'!J177 -> 673.3 | G33: =BS!G26-BS!F26 -> 325.2 | H33: =BS!H26-BS!G26 -> 0 | I33: =BS!I26-BS!H26 -> 0 | J33: =BS!J26-BS!I26 -> 0 | K33: =BS!K26-BS!J26 -> 0
A34: Payments for share returns and repurchases | B34: ='INPUT-Y'!F104-'INPUT-Y'!E104 -> 0 | C34: ='INPUT-Y'!G104-'INPUT-Y'!F104 -> 0 | D34: ='INPUT-Y'!H104-'INPUT-Y'!G104 -> 0 | E34: ='INPUT-Y'!I104-'INPUT-Y'!H104 -> 0 | F34: ='INPUT-Y'!J104-'INPUT-Y'!I104 -> 0
A35: Increase / (Pay-off) of ST loans | B35: ='INPUT-Y'!F77-'INPUT-Y'!E77 -> -57.3 | C35: =BS!C19-BS!B19 -> -39.3 | D35: =BS!D19-BS!C19 -> 100.5 | E35: =BS!E19-BS!D19 -> 447.2 | F35: =BS!F19-BS!E19 -> 47.3 | G35: =BS!G19-BS!F19 -> 60.09 | H35: =BS!H19-BS!G19 -> 66.099 | I35: =BS!I19-BS!H19 -> 72.7089 | J35: =BS!J19-BS!I19 -> 79.97979 | K35: =BS!K19-BS!J19 -> 87.977769
A36: Increase / (Pay-off) of LT loans | B36: ='INPUT-Y'!F90-'INPUT-Y'!E90 -> -253 | C36: =BS!C21-BS!B21 -> -32.1 | D36: =BS!D21-BS!C21 -> 1187.9 | E36: =BS!E21-BS!D21 -> 1922.8 | F36: =BS!F21-BS!E21 -> -142.5 | G36: =BS!G21-BS!F21 -> 5471.7132 | H36: =BS!H21-BS!G21 -> 1664.3874 | I36: =BS!I21-BS!H21 -> -615.31262 | J36: =BS!J21-BS!I21 -> -583.71262 | K36: =BS!K21-BS!J21 -> -1210.9148
A37: Dividends paid | B37: ='INPUT-Y'!F182 -> -39.5 | C37: ='INPUT-Y'!G182 -> -29.5 | D37: ='INPUT-Y'!H182 -> -150.7 | E37: ='INPUT-Y'!I182 -> -166.9 | F37: ='INPUT-Y'!J182 -> -35.6 | G37: =-'Owners equity'!G30 -> -86.23524 | H37: =-'Owners equity'!H30 -> 0 | I37: =-'Owners equity'!I30 -> 0 | J37: =-'Owners equity'!J30 -> 0 | K37: =-'Owners equity'!K30 -> 0
A38: Changes in other LT liabilities | B38: =-('INPUT-Y'!F82-'INPUT-Y'!F90)-('INPUT-Y'!E82-'INPUT-Y'!E90)-('INPUT-Y'!F94-'INPUT-Y'!E94) -> -1.9 | C38: =-('INPUT-Y'!G82-'INPUT-Y'!G90)-('INPUT-Y'!F82-'INPUT-Y'!F90)-('INPUT-Y'!G94-'INPUT-Y'!F94) -> -9.7 | D38: =-('INPUT-Y'!H82-'INPUT-Y'!H90)-('INPUT-Y'!G82-'INPUT-Y'!G90)-('INPUT-Y'!H94-'INPUT-Y'!G94) -> -8.9 | E38: =-('INPUT-Y'!I82-'INPUT-Y'!I90)-('INPUT-Y'!H82-'INPUT-Y'!H90)-('INPUT-Y'!I94-'INPUT-Y'!H94) -> -8.2 | F38: =-('INPUT-Y'!J82-'INPUT-Y'!J90)-('INPUT-Y'!I82-'INPUT-Y'!I90)-('INPUT-Y'!J94-'INPUT-Y'!I94) -> -7.3
A39: Other distribution from equity | B39: ='INPUT-Y'!F176 - SUM(B33:B38) -> 71.7 | C39: ='INPUT-Y'!G176 - SUM(C33:C38) -> 16.2 | D39: ='INPUT-Y'!H176 - SUM(D33:D38) -> 12.6 | E39: ='INPUT-Y'!I176 - SUM(E33:E38) -> 5.9 | F39: ='INPUT-Y'!J176 - SUM(F33:F38) -> 11.5
A40: Net Cashflow from Financing activities | B40: ='INPUT-Y'!F176 -> -280 | C40: ='INPUT-Y'!G176 -> -93.4 | D40: ='INPUT-Y'!H176 -> 2191.2 | E40: ='INPUT-Y'!I176 -> 2471.1 | F40: ='INPUT-Y'!J176 -> 546.7 | G40: =SUM(G33:G39) -> 5770.768 | H40: =SUM(H33:H39) -> 1730.4864 | I40: =SUM(I33:I39) -> -542.60372 | J40: =SUM(J33:J39) -> -503.73283 | K40: =SUM(K33:K39) -> -1122.937
A42: Net Cash and Cash equivalents during the period | B42: ='INPUT-Y'!F184 -> -20.7 | C42: ='INPUT-Y'!G184 -> 155 | D42: ='INPUT-Y'!H184 -> 386.4 | E42: ='INPUT-Y'!I184 -> -503.7 | F42: ='INPUT-Y'!J184 -> 30.1 | G42: =SUM(G40,G30,G22) -> 489.2134 | H42: =SUM(H40,H30,H22) -> -638.05559 | I42: =SUM(I40,I30,I22) -> -90.394442 | J42: =SUM(J40,J30,J22) -> 108.41048 | K42: =SUM(K40,K30,K22) -> 204.67809
A43: Cash and cash equivalents at beginning of year | B43: ='INPUT-Y'!F185 -> 88.7 | C43: =B44 -> 68 | D43: =C44 -> 223 | E43: =D44 -> 609.4 | F43: =E44 -> 105.4 | G43: =F44 -> 135.4 | H43: =G44+50 -> 674.6134 | I43: =H44+100 -> 136.55781 | J43: =I44 -> 46.163367 | K43: =J44 -> 154.57385
A44: Cash and Cash equivalents at end of year | B44: ='INPUT-Y'!F186 -> 68 | C44: ='INPUT-Y'!G186 -> 223 | D44: ='INPUT-Y'!H186 -> 609.4 | E44: ='INPUT-Y'!I186 -> 105.4 | F44: ='INPUT-Y'!J186 -> 135.4 | G44: =SUM(G42:G43) -> 624.6134 | H44: =SUM(H42:H43) -> 36.557809 | I44: =SUM(I42:I43) -> 46.163367 | J44: =SUM(J42:J43) -> 154.57385 | K44: =SUM(K42:K43) -> 359.25194

Sheet Valuation
A1: VALUATION SUMMARY | F1: WACC
A2: Valuation Date: | B2: 44545 | F2: Beta | G2: =WACC!H2 -> 0.74372848
A3: Company Name: | B3: GEC | F3: Risk free rate | G3: =WACC!H3 -> 0.037
A4: Share Price: | B4: 20.28 | F4: Premium | G4: =WACC!H4 -> 0.0821
A5: Basic Shares Outstanding (mil shares): | B5: 303.715 | F5: D | G5: =WACC!H5 -> 0.57223053
F6: E | G6: =WACC!H6 -> 0.42776947
F7: Marginal tax rate | G7: =WACC!H7 -> 0.07
F8: Cost of equity | G8: =WACC!H8 -> 0.098060108
F9: Cost of debt | G9: =WACC!H9 -> 0.09
F10: WACC | G10: =WACC!H10 -> 0.089842816
A14: MUTIPLE METHOD
A15: P/E
A16: COMPANY | B16: COUNTRY | C16: Market capitalisation | D16: ROE (TTM) | E16: ROA (TTM) | F16: P/B (Q) | G16: P/E (TTM)
A17: SAHACOGEN CHONBURI | B17: Thailand | C17: 3286 | D17: 0.093 | E17: 0.062 | F17: 10.75 | G17: 26.8
A18: GEPIC ENERGY | B18: Chinese | C18: 11291.5 | D18: 0.066 | E18: 0.026 | F18: 14.33 | G18: 19.5
A19: Guizhou Qianyu | B19: Chinese | C19: 21787 | D19: 0.143 | E19: 0.026 | F19: 3.4 | G19: 15.4
A20: Guangzhou Heng | B20: Chinese | C20: 20500 | D20: 0.077 | E20: 0.031 | F20: 1.3 | G20: 14.1
A21: PetroVietnam Power Nhon Trach 2 JSC | B21: Vietnam | C21: 7456 | D21: 0.15 | E21: 0.091 | F21: 1.8 | G21: 12.1
A22: Vinh Son - Song Hinh Hydropower JSC | B22: Vietnam | C22: 6803 | D22: 0.102 | E22: 0.037 | F22: 1.8 | G22: 19.1
A23: Power Generation Joint Stock Corporation 2 | B23: Vietnam | C23: 36786 | D23: N/A | E23: N/A | F23: 1.8 | G23: 21.7
A24: PetroVietnam Power Corporation | B24: Vietnam | C24: 40046 | D24: 0.096 | E24: 0.054 | F24: 1.2 | G24: 14.7
A25: MEDIAN | C25: =MEDIAN(C17:C24) -> 15895.75 | D25: =MEDIAN(D17:D24) -> 0.096 | E25: =MEDIAN(E17:E24) -> 0.037 | F25: =MEDIAN(F21:F24) -> 1.8 | G25: =MEDIAN(G17:G24) -> 17.25
A26: GIA LAI ELECTRICITY JSC (GEG) | B26: Vietnam | C26: 5937 | D26: 0.096 | E26: 0.031 | F26: 1.7 | G26: 22.8
A28: EPS | B28: =IS!G18/B5 -> 1.119352
A29: P/E | B29: =G25 -> 17.25
A30: Target Price ( 1000 VNĐ) | B30: =B28*B29 -> 19.308822
A36: FCFF PROJECTION | B36: 2021F | C36: 2022F | D36: 2023F | E36: 2024F | F36: 2025F
A37: Operating profit | B37: =IS!G6+IS!G10+IS!G11 -> 670.32375 | C37: =IS!H6+IS!H10+IS!H11 -> 1210.0945 | D37: =IS!I6+IS!I10+IS!I11 -> 1283.3494 | E37: =IS!J6+IS!J10+IS!J11 -> 1250.4932 | F37: =IS!K6+IS!K10+IS!K11 -> 1244.9523
A38: Tax | B38: =IS!G16+IS!G17 -> -28.213297 | C38: =IS!H16+IS!H17 -> -32.110001 | D38: =IS!I16+IS!I17 -> -39.560702 | E38: =IS!J16+IS!J17 -> -25.620762 | F38: =IS!K16+IS!K17 -> -29.544396
A39: Depreciation | B39: =CF!G7 -> 349.75 | C39: =CF!H7 -> 969 | D39: =CF!I7 -> 969 | E39: =CF!J7 -> 969 | F39: =CF!K7 -> 969
A40: Change in net working capital | B40: =SUM(CF!I8:I10,CF!I14:I16) -> -481.85844 | C40: =SUM(CF!J8:J10,CF!J14:J16) -> -332.76844 | D40: =SUM(CF!K8:K10,CF!K14:K16) -> -185.13736 | E40: =SUM(CF!L8:L10,CF!L14:L16) -> 0 | F40: =SUM(CF!M8:M10,CF!M14:M16) -> 0
A41: Capex | B41: =CF!G25 -> -8389.5 | C41: =CF!H25 -> -2872.5 | D41: =CF!I25 -> -520 | E41: =CF!J25 -> -520 | F41: =CF!K25 -> 20
A42: FCFF | B42: =SUM(B37:B41) -> -7879.498 | C42: =SUM(C37:C41) -> -1058.2839 | D42: =SUM(D37:D41) -> 1507.6513 | E42: =SUM(E37:E41) -> 1673.8725 | F42: =SUM(F37:F41) -> 2204.4079
A43: WACC | B43: =G10 -> 0.089842816
A44: Mid Point | B44: =1/12 -> 0.083333333 | C44: =1+B44 -> 1.0833333 | D44: =1+C44 -> 2.0833333 | E44: =1+D44 -> 3.0833333 | F44: =1+E44 -> 4.0833333
A45: Discount Factor | B45: =1/(1+$B$43)^B44 -> 0.99285618 | C45: =1/(1+$B$43)^C44 -> 0.9110086 | D45: =1/(1+$B$43)^D44 -> 0.83590825 | E45: =1/(1+$B$43)^E44 -> 0.76699891 | F45: =1/(1+$B$43)^F44 -> 0.70377021
A46: Present value of FCFF | B46: =B45*B42 -> -7823.2083 | C46: =C45*C42 -> -964.10578 | D46: =D45*D42 -> 1260.2582 | E46: =E45*E42 -> 1283.8584 | F46: =F45*F42 -> 1551.3966
A49: Enterprise Value (MillionVND) | D49: Implied Enterprise Value and Share Price
A50: Cumulative Present Value of FCFF | B50: =SUM(B46:F46) -> -4691.8009 | D50: Enterprise Value | F50: =B60 -> 11253.479
D51: Less: Total Debt | F51: =BS!F19+BS!F21 -> 3801.5
A52: FCFE Terminal Value (by growth rate) | D52: Plus: Cash and Cash Equivalent | F52: =BS!F5 -> 135.4
D53: Plus: Non-operating assets after tax
A54: Growth rate | B54: 0.02 | D54: Implied Enterprise Value | F54: =F50-F51+F52 -> 7587.3794
A55: Terminal Value | B55: =F46*(1+B54)/(B43-B54) -> 22656.941
A56: Discount Factor | B56: =F45 -> 0.70377021 | D56: Number of Shares | F56: 303.72
A57: PV of Terminal Value | B57: =B55*B56 -> 15945.28 | D57: Implied Price per Share | F57: =F54/F56 -> 24.981494
A60: Enterprise Value | B60: =B57+B50 -> 11253.479
A63: RESULT
A64: METHOD | B64: PROPORTION | C64: PRICE (Thousand VND)
A65: P/E | B65: 0.4 | C65: =B30 -> 19.308822
A66: FCFF | B66: 0.6 | C66: =F57 -> 24.981494
A68: RECOMMENDATION
A69: CURRENT PRICE (15/12/2021, thousand VND) | B69: =B4 -> 20.28
A70: TARGET PRICE (Thousand VND) | B70: =B65*C65+B66*C66 -> 22.712425
A71: CHANGE | B71: =(B70-B69)/B69 -> 0.11994208
A75: SENSITIVITY ANALYSIS
A76: WACC | B76: g
B77: =F57 -> 24.981494 | C77: 0.015 | D77: 0.0175 | E77: 0.02 | F77: 0.0225 | G77: 0.025
B78: =B79-0.25% -> 0.0848 | C78: 26.946978 | D78: 29.102482 | E78: 31.424305 | F78: 33.932471 | G78: 36.650349
B79: =B80-0.25% -> 0.0873 | C79: 24.007309 | D79: 25.980917 | E79: 28.101153 | F79: 30.384987 | G79: 32.852114
B80: =8.98% -> 0.0898 | C80: 21.278999 | D80: 23.090617 | E80: 25.032007 | F80: 27.117631 | G80: 29.364183
B81: =B80+0.25% -> 0.0923 | C81: 18.741182 | D81: 20.408021 | E81: 22.190133 | F81: 24.099902 | G81: 26.151557
B82: =B81+0.25% -> 0.0948 | C82: 16.375615 | D82: 17.912625 | E82: 19.552377 | F82: 21.305529 | G82: 23.184264

Sheet PP&E
A1: PROPERTY, PLANT, AND EQUIPMENT (PP&E)
B2: 2016 | C2: 2017 | D2: 2018 | E2: 2019 | F2: 2020 | G2: 2021 | H2: 2022 | I2: 2023 | J2: 2024 | K2: 2025
A3: Tangible Fixed Assets
A4: Beginning of period | C4: =B8 -> 1163.7 | D4: =C8 -> 1107.4 | E4: =D8 -> 2871.2 | F4: =E8 -> 5239.7 | G4: =F8 -> 5330.2 | H4: =G8 -> 10111.45 | I4: =H8 -> 14947.45 | J4: =I8 -> 13998.45 | K4: =J8 -> 13049.45
A5: Plus: Transfer from Construction in progress | F5: =-F31 -> 400.7 | G5: =-G31 -> 5111 | H5: =-H31 -> 5785 | I5: =-I31 -> 0 | J5: =-J31 -> 0 | K5: =-K31 -> 0
A6: Plus: Purchase/Liquidate | F6: =83.4 -35.5-24.2 -> 23.7 | G6: =20 -> 20 | H6: =20 -> 20 | I6: =20 -> 20 | J6: =20 -> 20 | K6: =20 -> 20
A7: Less: Depreciation | B7: =B52 -> 0 | C7: =C52 -> -74 | D7: =D52 -> -95.4 | E7: =E52 -> -277.3 | F7: =F52 -> -333.9 | G7: =G26 -> -349.75 | H7: =H26 -> -969 | I7: =I26 -> -969 | J7: =J26 -> -969 | K7: =AVERAGE(H7:J7) -> -969
A8: End of period | B8: ='INPUT-Y'!F38 -> 1163.7 | C8: ='INPUT-Y'!G38 -> 1107.4 | D8: ='INPUT-Y'!H38 -> 2871.2 | E8: ='INPUT-Y'!I38 -> 5239.7 | F8: =SUM(F4:F7) -> 5330.2 | G8: =SUM(G4:G7) -> 10111.45 | H8: =SUM(H4:H7) -> 14947.45 | I8: =SUM(I4:I7) -> 13998.45 | J8: =SUM(J4:J7) -> 13049.45 | K8: =SUM(K4:K7) -> 12100.45
A9: Fixed assets' average depreciable life | B9: =F84 -> 19.659778
A10: Increase in year | B10: =ROUND(B9,0) -> 20
A11: Charge for every year | B11: =F7 -> -333.9
A12: Acummulated depr. | D12: =D16 -> -622.9 | E12: =E16 -> -900.2 | F12: =F16 -> -1234.1 | G12: =$B$11+F12 -> -1568 | H12: =$B$11+G12 -> -1901.9 | I12: =$B$11+H12 -> -2235.8 | J12: =$B$11+I12 -> -2569.7 | K12: =$B$11+J12 -> -2903.6
A13: Net asset value | D13: =$D$15+D12 -> 2871.2 | E13: =$D$15+E12 -> 2593.9 | F13: =$D$15+F12 -> 2260 | G13: =$D$15+G12 -> 1926.1 | H13: =$D$15+H12 -> 1592.2 | I13: =$D$15+I12 -> 1258.3 | J13: =$D$15+J12 -> 924.4 | K13: =$D$15+K12 -> 590.5
A14: Old tangible assets
A15: Gross tangible assets | C15: =C49 -> 1634.9 | D15: =D49 -> 3494.1 | E15: =E49 -> 6139.9 | F15: =F49 -> 6564.4 | G15: =$F$15 -> 6564.4 | H15: =$F$15 -> 6564.4 | I15: =$F$15 -> 6564.4 | J15: =$F$15 -> 6564.4 | K15: =$F$15 -> 6564.4
A16: Accumulated depreciation | C16: =C51 -> -527.5 | D16: =D51 -> -622.9 | E16: =E51 -> -900.2 | F16: =F51 -> -1234.1 | G16: =F16+G17 -> -1568 | H16: =G16+H17 -> -1971.9 | I16: =H16+I17 -> -2375.8 | J16: =I16+J17 -> -2779.7 | K16: =J16+K17 -> -3183.6
A17: Depreciation from old tangible assets | C17: =C7 -> -74 | D17: =D7 -> -95.4 | E17: =E7 -> -277.3 | F17: =F7 -> -333.9 | G17: =IF(AND(G13<0,F13<0),0,IF(AND(G13<0,F13>0),-(G$15+F$12),$B$11)) -> -333.9 | H17: =IF(AND(H13<0,G13<0),0,IF(AND(H13<0,G13>0),-(H$15+G$12),$B$11-70)) -> -403.9 | I17: =IF(AND(I13<0,H13<0),0,IF(AND(I13<0,H13>0),-(I$15+H$12),$B$11-70)) -> -403.9 | J17: =IF(AND(J13<0,I13<0),0,IF(AND(J13<0,I13>0),-(J$15+I$12),$B$11-70)) -> -403.9 | K17: =IF(AND(K13<0,J13<0),0,IF(AND(K13<0,J13>0),-(K$15+J$12),$B$11-70)) -> -403.9
A19: Depreciation from new tangible assets
A20: Tan Phu Dong 2 wind farm | G20: =-SLN(2242,0,$B$10)+110 -> -2.1 | H20: =-SLN(2242,0,$B$10) -> -112.1 | I20: =-SLN(2242,0,$B$10) -> -112.1 | J20: =-SLN(2242,0,$B$10) -> -112.1 | K20: =-SLN(2242,0,$B$10) -> -112.1
A21: VPL1 wind farm | G21: =-SLN(1320,0,$B$10)+60 -> -6 | H21: =-SLN(1320,0,$B$10) -> -66 | I21: =-SLN(1320,0,$B$10) -> -66 | J21: =-SLN(1320,0,$B$10) -> -66 | K21: =-SLN(1320,0,$B$10) -> -66
A22: IA Bang 1 wind farm | G22: =-SLN(1955,0,$B$10)+90 -> -7.75 | H22: =-SLN(1955,0,$B$10) -> -97.75 | I22: =-SLN(1955,0,$B$10) -> -97.75 | J22: =-SLN(1955,0,$B$10) -> -97.75 | K22: =-SLN(1955,0,$B$10) -> -97.75
A23: Tan Phu Dong 1 wind farm | H23: =-SLN(4465,0,$B$10) -> -223.25 | I23: =-SLN(4465,0,$B$10) -> -223.25 | J23: =-SLN(4465,0,$B$10) -> -223.25 | K23: =-SLN(4465,0,$B$10) -> -223.25
A24: VPL2 wind farm | H24: =-SLN(1320,0,$B$10) -> -66 | I24: =-SLN(1320,0,$B$10) -> -66 | J24: =-SLN(1320,0,$B$10) -> -66 | K24: =-SLN(1320,0,$B$10) -> -66
A25: Total depreciation from new CAPEX | G25: =SUM(G20:G24) -> -15.85 | H25: =SUM(H20:H24) -> -565.1 | I25: =SUM(I20:I24) -> -565.1 | J25: =SUM(J20:J24) -> -565.1 | K25: =SUM(K20:K24) -> -565.1
A26: Total tangible assets depreciation | G26: =G17+G25 -> -349.75 | H26: =H17+H25 -> -969 | I26: =I17+I25 -> -969 | J26: =J17+J25 -> -969 | K26: =K17+K25 -> -969
A28: Construction in progress (all)
A29: Beginning balance | C29: =B35 -> 5.6 | D29: =C35 -> 18 | E29: =D35 -> 215.8 | F29: =E35 -> 262.8 | G29: =F35 -> 541.4 | H29: =G35 -> 3839.9 | I29: =H35 -> 947.4 | J29: =I35 -> 1487.4 | K29: =J35 -> 2027.4
A30: New construction at the beginning of the year | F30: 675.3 | G30: =5517+5785/2 -> 8409.5 | H30: =2892.5 -> 2892.5 | I30: 540 | J30: 540
A31: Transfer to tangible fixed assets (enter as -) | F31: -400.7 | G31: -5111 | H31: =-5785 -> -5785 | J31: 0 | K31: 0
A32: Transfer to intangible fixed assets (enter as -) | F32: -0.7 | J32: 0 | K32: 0
A33: Transfer to investment properties (enter as -) | J33: 0 | K33: 0
A34: Other changes | F34: =6.3-0.2-1.4 -> 4.7 | J34: 0 | K34: 0
A35: Ending balance | B35: ='INPUT-Y'!F52 -> 5.6 | C35: ='INPUT-Y'!G52 -> 18 | D35: ='INPUT-Y'!H52 -> 215.8 | E35: ='INPUT-Y'!I52 -> 262.8 | F35: =SUM(F29:F34) -> 541.4 | G35: =SUM(G29:G31) -> 3839.9 | H35: =SUM(H29:H31) -> 947.4 | I35: =SUM(I29:I31) -> 1487.4 | J35: =SUM(J29:J31) -> 2027.4 | K35: =SUM(K29:K31) -> 2027.4
A37: Intangible fixed assets
A38: Beginning balance | C38: =B44 -> 5.6 | D38: =C44 -> 6.6 | E38: =D44 -> 6.4 | F38: =E44 -> 19.2 | G38: =F44 -> 16.7 | H38: =G44 -> 7.6570313 | I38: =H44 -> 10.085547 | J38: =I44 -> 10.97627 | K38: =J44 -> 12.132251
A39: - Original price | B39: ='INPUT-Y'!E45 -> 6.2 | C39: ='INPUT-Y'!F45 -> 6.4 | D39: ='INPUT-Y'!G45 -> 7.5 | E39: ='INPUT-Y'!H45 -> 7.4 | F39: ='INPUT-Y'!I45 -> 21.1 | G39: =AVERAGE(C39:F39) -> 10.6 | H39: =AVERAGE(D39:G39) -> 11.65 | I39: =AVERAGE(E39:H39) -> 12.6875 | J39: =AVERAGE(F39:I39) -> 14.009375 | K39: =AVERAGE(G39:J39) -> 12.236719
A40: - % Amortization/Intangible assets | C40: =-C43/C38 -> 0.035714286 | D40: =-D43/D38 -> 0.015151515 | E40: =-E43/E38 -> 0.140625 | F40: =-F43/F38 -> 0.140625 | G40: =F40 -> 0.140625 | H40: =G40 -> 0.140625 | I40: =H40 -> 0.140625 | J40: =I40 -> 0.140625 | K40: =J40 -> 0.140625
A41: - Purchases of intangible assets | C41: =C60 -> 1.1 | D41: =D60 -> -0.1 | E41: =E60 -> 13.7 | F41: =F60 -> 0.2 | G41: 0 | H41: 0 | I41: 0 | J41: 0 | K41: 0
A42: - Accumulated depreciation | B42: =B61 -> -0.7 | C42: =C61 -> -0.9 | D42: =D61 -> -1 | E42: =E61 -> -1.9 | F42: =F61 -> -4.6 | G42: =G40*-AVERAGE(SUM(F39,F41),SUM(G39,G41))+F32 -> -2.9429687 | H42: =H40*-AVERAGE(SUM(G39,G41),SUM(H39,H41))+G32 -> -1.5644531 | I42: =I40*-AVERAGE(SUM(H39,H41),SUM(I39,I41))+H32 -> -1.7112305 | J42: =J40*-AVERAGE(SUM(I39,I41),SUM(J39,J41))+I32 -> -1.877124 | K42: =K40*-AVERAGE(SUM(J39,J41),SUM(K39,K41))+J32 -> -1.8454285
A43: Gain/(loss) in depreciation | B43: -0.2 | C43: =C42-B42 -> -0.2 | D43: =D42-C42 -> -0.1 | E43: =E42-D42 -> -0.9 | F43: =F42-E42 -> -2.7 | G43: =G42-F42 -> 1.6570313 | H43: =H42-G42 -> 1.3785156 | I43: =I42-H42 -> -0.14677734 | J43: =J42-I42 -> -0.16589355 | K43: =K42-J42 -> 0.031695557
A44: Ending balance | B44: =B58 -> 5.6 | C44: =SUM(C39,C41,C42) -> 6.6 | D44: =SUM(D39,D41,D42) -> 6.4 | E44: =SUM(E39,E41,E42) -> 19.2 | F44: =SUM(F39,F41,F42) -> 16.7 | G44: =SUM(G39,G41,G42) -> 7.6570313 | H44: =SUM(H39,H41,H42) -> 10.085547 | I44: =SUM(I39,I41,I42) -> 10.97627 | J44: =SUM(J39,J41,J42) -> 12.132251 | K44: =SUM(K39,K41,K42) -> 10.39129
A47: CAPEX
A48: Tangible fixed assets | B48: ='INPUT-Y'!F38 -> 1163.7 | C48: ='INPUT-Y'!G38 -> 1107.4 | D48: ='INPUT-Y'!H38 -> 2871.2 | E48: ='INPUT-Y'!I38 -> 5239.7 | F48: ='INPUT-Y'!J38 -> 5330.2
A49: Cost of tangible fixed assets | B49: ='INPUT-Y'!F39 -> 1617.2 | C49: ='INPUT-Y'!G39 -> 1634.9 | D49: ='INPUT-Y'!H39 -> 3494.1 | E49: ='INPUT-Y'!I39 -> 6139.9 | F49: ='INPUT-Y'!J39 -> 6564.4
A50: Additions of tangible fixed assets | C50: =C49-B49 -> 17.7 | D50: =D49-C49 -> 1859.2 | E50: =E49-D49 -> 2645.8 | F50: =F49-E49 -> 424.5
A51: Accumulated depreciation of tangible fixed assets | B51: ='INPUT-Y'!F40 -> -453.5 | C51: ='INPUT-Y'!G40 -> -527.5 | D51: ='INPUT-Y'!H40 -> -622.9 | E51: ='INPUT-Y'!I40 -> -900.2 | F51: ='INPUT-Y'!J40 -> -1234.1
A52: Charge for the year of tangible fixed assets | C52: =C51-B51 -> -74 | D52: =D51-C51 -> -95.4 | E52: =E51-D51 -> -277.3 | F52: =F51-E51 -> -333.9
A53: Finance lease assets | B53: ='INPUT-Y'!F41 -> 0 | C53: ='INPUT-Y'!G41 -> 0 | D53: ='INPUT-Y'!H41 -> 0 | E53: ='INPUT-Y'!I41 -> 0 | F53: ='INPUT-Y'!J41 -> 27.8
A54: Cost of finance lease assets | B54: ='INPUT-Y'!F42 -> 0 | C54: ='INPUT-Y'!G42 -> 0 | D54: ='INPUT-Y'!H42 -> 0 | E54: ='INPUT-Y'!I42 -> 0 | F54: ='INPUT-Y'!J42 -> 28.1
A55: Additions of finance lease assets | C55: =C54-B54 -> 0 | D55: =D54-C54 -> 0 | E55: =E54-D54 -> 0 | F55: =F54-E54 -> 28.1
A56: Accumulated depreciation of finance lease assets | B56: ='INPUT-Y'!F43 -> 0 | C56: ='INPUT-Y'!G43 -> 0 | D56: ='INPUT-Y'!H43 -> 0 | E56: ='INPUT-Y'!I43 -> 0 | F56: ='INPUT-Y'!J43 -> -0.3
A57: Charge for the year of finance lease assets | C57: =C56-B56 -> 0 | D57: =D56-C56 -> 0 | E57: =E56-D56 -> 0 | F57: =F56-E56 -> -0.3
A58: Intangible fixed assets | B58: ='INPUT-Y'!F44 -> 5.6 | C58: ='INPUT-Y'!G44 -> 6.6 | D58: ='INPUT-Y'!H44 -> 6.4 | E58: ='INPUT-Y'!I44 -> 19.2 | F58: ='INPUT-Y'!J44 -> 16.7
A59: Cost of intangible fixed assets | B59: ='INPUT-Y'!F45 -> 6.4 | C59: ='INPUT-Y'!G45 -> 7.5 | D59: ='INPUT-Y'!H45 -> 7.4 | E59: ='INPUT-Y'!I45 -> 21.1 | F59: ='INPUT-Y'!J45 -> 21.3
A60: Additions of intangible fixed assets | C60: =C59-B59 -> 1.1 | D60: =D59-C59 -> -0.1 | E60: =E59-D59 -> 13.7 | F60: =F59-E59 -> 0.2
A61: Accumulated depreciation of intangible fixed assets | B61: ='INPUT-Y'!F46 -> -0.7 | C61: ='INPUT-Y'!G46 -> -0.9 | D61: ='INPUT-Y'!H46 -> -1 | E61: ='INPUT-Y'!I46 -> -1.9 | F61: ='INPUT-Y'!J46 -> -4.6
A62: Charge for the year of intangible fixed assets | C62: =C61-B61 -> -0.2 | D62: =D61-C61 -> -0.1 | E62: =E61-D61 -> -0.9 | F62: =F61-E61 -> -2.7
A63: Investment properties | B63: 0 | C63: 0 | D63: 0 | E63: 0 | F63: 0
A64: Cost of investment properties assets | B64: 0 | C64: 0 | D64: 0 | E64: 0 | F64: 0
A65: Additions of investment properties assets | B65: 0 | C65: 0 | D65: 0 | E65: 0 | F65: 0
A66: Accumulated depreciation of investment properties assets | B66: 0 | C66: 0 | D66: 0 | E66: 0 | F66: 0
A67: Charge for the year of investment properties assets | B67: 0 | C67: 0 | D67: 0 | E67: 0 | F67: 0
A68: Construction in progress | B68: ='INPUT-Y'!F50 -> 5.6 | C68: ='INPUT-Y'!G50 -> 18 | D68: ='INPUT-Y'!H50 -> 215.8 | E68: ='INPUT-Y'!I50 -> 262.8 | F68: ='INPUT-Y'!J50 -> 541.4
A69: Good will | B69: ='INPUT-Y'!C64 -> 3.5 | C69: ='INPUT-Y'!D64 -> 16.9 | D69: ='INPUT-Y'!E64 -> 14.6 | E69: ='INPUT-Y'!F64 -> 12.3 | F69: ='INPUT-Y'!G64 -> 9.7
A70: Amortisation of goodwill | B70: 0 | C70: 0 | D70: 0 | E70: 0 | F70: 0
A71: Capital expenditure | C71: =C50 -> 17.7 | D71: =D50 -> 1859.2 | E71: =E50 -> 2645.8 | F71: =F50 -> 424.5
A72: Total additional assets | C72: =C50+C55+C60+C65 -> 18.8 | D72: =D50+D55+D60+D65 -> 1859.1 | E72: =E50+E55+E60+E65 -> 2659.5 | F72: =F50+F55+F60+F65 -> 452.8
A73: Total accumulated depreciation | B73: =B51+B56+B61+B66 -> -454.2 | C73: =C51+C56+C61+C66 -> -528.4 | D73: =D51+D56+D61+D66 -> -623.9 | E73: =E51+E56+E61+E66 -> -902.1 | F73: =F51+F56+F61+F66 -> -1239
A74: Total depreciation | B74: =B52+B57+B62+B67 -> 0 | C74: =C52+C57+C62+C67 -> -74.2 | D74: =D52+D57+D62+D67 -> -95.5 | E74: =E52+E57+E62+E67 -> -278.2 | F74: =F52+F57+F62+F67 -> -336.9
A75: Depreciation and amortisation | B75: =-'INPUT-Y'!F147 -> -79.8 | C75: =-'INPUT-Y'!G147 -> -79.5 | D75: =-'INPUT-Y'!H147 -> -97.5 | E75: =-'INPUT-Y'!I147 -> -285 | F75: =-'INPUT-Y'!J147 -> -354
A76: % Depreciation/Tangible assets | C76: =-C52/AVERAGE(B49:C49) -> 0.045509056 | D76: =-D52/AVERAGE(C49:D49) -> 0.037200234 | E76: =-E52/AVERAGE(D49:E49) -> 0.05756695 | F76: =-F52/AVERAGE(E49:F49) -> 0.05256488
A77: % Depreciation/Finance lease assets | C77: 0 | D77: 0 | E77: 0 | F77: 0
A78: % Amortization/Intangible assets | C78: =C40 -> 0.035714286 | D78: =D40 -> 0.015151515 | E78: =E40 -> 0.140625 | F78: =F40 -> 0.140625
A79: % Depreciation/Investment properties | C79: 0 | D79: 0 | E79: 0 | F79: 0
A80: %Amortization/Goodwill | C80: 0 | D80: 0 | E80: 0 | F80: 0
A81: % Depreciation/Total assets | C81: =-C75/(0.5*SUM((B49:C49),B54:C54,B59:C59,B64:C64)) -> 0.048683405 | D81: =-D75/(0.5*SUM((C49:D49),C54:D54,C59:D59,C64:D64)) -> 0.03790898 | E81: =-E75/(0.5*SUM((D49:E49),D54:E54,D59:E59,D64:E64)) -> 0.058990944 | F81: =-F75/(0.5*SUM((E49:F49),E54:F54,E59:F59,E64:F64)) -> 0.055421611
A82: Fixed assets' average age | C82: =C51/C52 -> 7.1283784 | D82: =D51/D52 -> 6.5293501 | E82: =E51/E52 -> 3.2463036 | F82: =F51/F52 -> 3.6960168
A83: Fixed assets' relative age | C83: =-C51/C49 -> 0.3226497 | D83: =-D51/D49 -> 0.17827194 | E83: =-E51/E49 -> 0.14661477 | F83: =-F51/F49 -> 0.1879989
A84: Fixed assets' average depreciable life | C84: =-C49/C52 -> 22.093243 | D84: =-D49/D52 -> 36.625786 | E84: =-E49/E52 -> 22.141724 | F84: =-F49/F52 -> 19.659778

Sheet Assumption
A1: CÔNG TY CỔ PHẦN ĐIỆN GIA LAI - GIA LAI ELECTRICITY JOINT STOCK COMPANY BẢNG GIẢ ĐỊNH - ASSUMPTION
B3: Income Statement Assumptions
A4: Solar power | B4: Solar radiation falling on Vietnam is forecasted to increase sharply in the coming years, especially in the Central and Southern regions. GEG is developing a team of experienced technicians to run factories better. EVN will upgrade the power transmission line to meet the electricity output according to Circular 55. Therefore, we forecast that the actual output divided by theory (Qr/Q) of the solar power array will be 105% from 2023 onward. Duc Hue 1-Long An solar power plant alone will be 115% from 2023 because the demand for electricity in the South and heat radiation in this area will increase sharply. In the two years 2021 and 2022, due to the complicated situation of the Covid epidemic, we have set the Qr/Q level at 90% and 100% respectively.
A6: Wind power | B6: In 2021, 3 wind power plants will officially come into operation and enjoy preferential FIT prices: Ia Bang 1, Tan Phu Dong 2 and VPL1-Ben Tre. In which, Ia Bang 1 is an onshore project, so the FIT price is 8.5 cents/kwh; Tan Phu Dong 2 and VPL1 are nearshore projects, so the FIT price 9.8 iscents/kwh. We forecast that the output of these 3 factories will be 16% compared to the average output in 2021 (Since these factories will come into operation in Q4/2021 when the epidemic situation is under control, industrial zones are gradually reopening, leading to a recovery in electricity demand) and 100% for the following years due to GEG's improvement in operating quality, EVN's upgrade of power transmission lines and favorable location in strong wind area. The remaining 2 plants, VPL2-Tien Giang and Tan Phu Dong 1 (2 projects near the shore) are still waiting to finalize electricity prices. According to the company's forecast, the price is expected to decrease by 10% compared to the nearshore FIT price.
A8: Hydroeclectricity | B8: For the hydropower segment, we forecast to operate at a Qr/Q (real volume/average volume) level of 90% in 2021 due to La Nina and down to 80% in 2022 and 77% onward due to the phenomenon La Nina phasing out.
A10: Construction | B10: We forecast that revenue from this segment will account for 5% in 2021 due to the COVID-19 pandemic; and maintained at 5% onward as the GEG is focusing on the renewable energy segment.
A12: Gross Profit Margin | B12: We expect gross profit margin to grow at a CAGR of 13% from 2021-2025. In which, gross profit margin will decrease to 47% in the period 2021-2022 due to the sharp increase in depreciation expense from new factories.
A14: COGS | B14: We forecast material cost will increase 2% per year due to inflation. Labor costs in 2021 decreased sharply due to GEG's personnel restructuring. Previously, in 2019 when GEG carried out the construction of solar power plants, it also restructured once. That's why we set the 2021 labor cost at 10 VND/kwh. The following years is 100 VND/kwh We estimate the cost of outsourcing will decrease by 10% per year from 2021 as GEG is upgrading the in-house technician team to maintain the factories without having to outsource them.
B17: Balance Sheet Assumptions
A18: Day Receivable/Revenue | B18: 5% reduction (compared to the previous year) from 2021 onward due to the implementation of TPD1, VPL2 projects by enterprises.
A20: DOH/Revenue | B20: Increase 5% point in 2021 (according to the company's expected data) and we take the average of 5 previous years for the next forecast
A22: Long-term Debt | B22: Besides assuming the company will gradually repay its debt in the future, we believe that the company will add about VND 2 trillion in long-term debt in 2022 to finance 2 wind power projects VPL2 and Tan Phu Dong 1 in Tien Giang (Total investment is about 5 trillion, 70% financed by debt, about 3.5 trillion, in 2021, 1.5 trillion has been disbursed)
A24: Short-term Debt | B24: Increase 10% each year
A26: %Cash Dividend | B26: GEG is in the investment phase so we expect the cash dividend to drop to 3% per year

Sheet Forecast
A1: FORECAST | B1: 2016 | C1: 2017 | D1: 2018 | E1: 2019 | F1: 2020 | G1: 2021F | H1: 2022F | I1: 2023F | J1: 2024F | K1: 2025F | O1: Sản lượng bình quân của mảng điện mặt trời
A3: Solar Energy
A4: Phong Điền-Huế | O4: 2016 | P4: 2017 | Q4: 2018 | R4: 2019 | S4: 2020 | T4: 2021F | U4: 2022F | V4: 2023F | W4: 2024F | X4: 2025F
A5: Average volume (Q) | E5: 60 | F5: 60 | G5: 60 | H5: 60 | I5: 60 | J5: 60 | K5: 60 | N5: Solar energy revenue | Q5: 37.3 | R5: 678 | S5: 895 | T5: 827 | U5: 942 | V5: 987 | W5: 987 | X5: 987
A6: As percentage (%) of total volume | E6: =E5/$P$19 -> 0.14814815 | F6: =F5/$P$19 -> 0.14814815 | G6: =G5/$P$19 -> 0.14814815 | H6: =H5/$P$19 -> 0.14814815 | I6: =I5/$P$19 -> 0.14814815 | J6: =J5/$P$19 -> 0.14814815 | K6: =K5/$P$19 -> 0.14814815 | N6: Average volume | Q6: 23.6 | R6: 272 | S6: 405 | T6: 405 | U6: 405 | V6: 405 | W6: 405 | X6: 405
A7: Real vloumne (Qr) | E7: 68 | F7: =58.52 -> 58.52 | G7: =G5*G8 -> 54 | H7: =H5*H8 -> 60 | I7: =I5*I8 -> 63 | J7: =J5*J8 -> 63 | K7: =K5*K8 -> 63 | N7: Real volume (Qr) | Q7: 17.7 | R7: 315 | S7: 395 | T7: 364.5 | U7: 415.01 | V7: 434.9 | W7: 434.9 | X7: 434.9
A8: Qr/Q | E8: =E7/E5 -> 1.1333333 | F8: =F7/F5 -> 0.97533333 | G8: =90% -> 0.9 | H8: =100% -> 1 | I8: 1.05 | J8: 1.05 | K8: 1.05
A9: FIT price | E9: =E10/E7 -> 2.1764706 | F9: =$F$10/$F$7 -> 2.2940875 | G9: =$F$10/$F$7 -> 2.2940875 | H9: =$F$10/$F$7 -> 2.2940875 | I9: =$F$10/$F$7 -> 2.2940875 | J9: =$F$10/$F$7 -> 2.2940875 | K9: =$F$10/$F$7 -> 2.2940875
A10: Revenue (YTD) | E10: =148 -> 148 | F10: =15%*S5 -> 134.25 | G10: =G9*G7 -> 123.88072 | H10: =H9*H7 -> 137.64525 | I10: =I9*I7 -> 144.52751 | J10: =J9*J7 -> 144.52751 | K10: =K9*K7 -> 144.52751 | N10: Wind power revenue | T10: 142 | U10: 1686 | V10: 1704 | W10: 1704 | X10: 1704
A11: As percentage (%) of solar revenue | E11: =E10/$S$5 -> 0.16536313 | F11: =F10/$S$5 -> 0.15 | G11: =G10/T5 -> 0.14979531 | H11: =H10/U5 -> 0.14612022 | I11: =I10/V5 -> 0.14643112 | J11: =J10/W5 -> 0.14643112 | K11: =K10/X5 -> 0.14643112 | N11: Average volume | T11: 66 | U11: 806.9 | V11: 814.6 | W11: 814.6 | X11: 814.6
N12: Real volume (Qr) | T12: 66 | U12: 806.9 | V12: 814.6 | W12: 814.6 | X12: 814.6
A13: Krong Pa-Gia Lai
A14: Average volume (Q) | E14: 103 | F14: 103 | G14: 103 | H14: 103 | I14: 103 | J14: 103 | K14: 103 | N14: Hydroelectric revenue | P14: 484 | Q14: 446 | R14: 380 | S14: 396 | T14: 409 | U14: 391 | V14: 427 | W14: 433 | X14: 440
A15: As percentage (%) of total volume | E15: =E14/R6 -> 0.37867647 | F15: =$F$14/$S$6 -> 0.25432099 | G15: =$F$14/$S$6 -> 0.25432099 | H15: =$F$14/$S$6 -> 0.25432099 | I15: =$F$14/$S$6 -> 0.25432099 | J15: =$F$14/$S$6 -> 0.25432099 | K15: =$F$14/$S$6 -> 0.25432099 | N15: Average volume | P15: 367 | Q15: 367 | R15: 367 | S15: 367 | T15: 367 | U15: 367 | V15: 367 | W15: 367 | X15: 367
A16: Real vloumne (Qr) | E16: 105 | F16: =F15*S7 -> 100.45679 | G16: =G17*G14 -> 92.7 | H16: =H17*H14 -> 103 | I16: =I17*I14 -> 108.15 | J16: =J17*J14 -> 108.15 | K16: =K17*K14 -> 108.15 | N16: Real volume (Qr) | P16: 426 | Q16: 363 | R16: 278 | S16: 321 | T16: 321 | U16: 307 | V16: 316 | W16: 314 | X16: 312
A17: Qr/Q | E17: =E16/E14 -> 1.0194175 | F17: =F16/F14 -> 0.97530864 | G17: =90% -> 0.9 | H17: =100% -> 1 | I17: 1.05 | J17: 1.05 | K17: 1.05
A18: FIT price | E18: =226/E16 -> 2.152381 | F18: =$F$19/$F$16 -> 2.2658228 | G18: =$F$19/$F$16 -> 2.2658228 | H18: =$F$19/$F$16 -> 2.2658228 | I18: =$F$19/$F$16 -> 2.2658228 | J18: =$F$19/$F$16 -> 2.2658228 | K18: =$F$19/$F$16 -> 2.2658228 | N18: Total revenue | O18: 431.4 | P18: 539.1 | Q18: 559.5 | R18: 1159.4 | S18: 1493.3 | T18: 1450 | U18: 3182 | V18: 3284 | W18: 3289 | X18: 3299
A19: Revenue (YTD) | E19: 226 | F19: =F15*S5 -> 227.61728 | G19: =G18*G16 -> 210.04177 | H19: =H18*H16 -> 233.37975 | I19: =I18*I16 -> 245.04873 | J19: =J18*J16 -> 245.04873 | K19: =K18*K16 -> 245.04873 | N19: Total solar energy volume in 2020 (MWp) | P19: 405
A20: As percentage (%) of solar revenue | E20: =E19/R5 -> 0.33333333 | F20: =F19/S5 -> 0.25432099 | G20: =G15 -> 0.25432099 | H20: =H15 -> 0.25432099 | I20: =I15 -> 0.25432099 | J20: =J15 -> 0.25432099 | K20: =K15 -> 0.25432099
A22: Đức Huệ 1-Long An
A23: Average volume (Q) | E23: =73*0.5 -> 36.5 | F23: =E23*2 -> 73 | G23: =73 -> 73 | H23: =73 -> 73 | I23: =73 -> 73 | J23: =73 -> 73 | K23: =73 -> 73
A24: As percentage (%) of total volume | E24: =E23/R6 -> 0.13419118 | F24: =$F$23/$S$6 -> 0.18024691 | G24: =$F$23/$S$6 -> 0.18024691 | H24: =$F$23/$S$6 -> 0.18024691 | I24: =$F$23/$S$6 -> 0.18024691 | J24: =$F$23/$S$6 -> 0.18024691 | K24: =$F$23/$S$6 -> 0.18024691
A25: Real vloumne (Qr) | E25: 52 | F25: =F24*S7 -> 71.197531 | G25: =G26*G23 -> 65.7 | H25: =H26*H23 -> 83.95 | I25: =I26*I23 -> 83.95 | J25: =J26*J23 -> 83.95 | K25: =K26*K23 -> 83.95
A26: Qr/Q | E26: =E25/E23 -> 1.4246575 | F26: =F25/F23 -> 0.97530864 | G26: =0.9 -> 0.9 | H26: =100%+15% -> 1.15 | I26: =100%+15% -> 1.15 | J26: =100%+15% -> 1.15 | K26: =100%+15% -> 1.15
A27: FIT price | E27: =E28/E25 -> 2.1730769 | F27: =$F$28/$F$25 -> 2.2658228 | G27: =$F$28/$F$25 -> 2.2658228 | H27: =$F$28/$F$25 -> 2.2658228 | I27: =$F$28/$F$25 -> 2.2658228 | J27: =$F$28/$F$25 -> 2.2658228 | K27: =$F$28/$F$25 -> 2.2658228
A28: Revenue (YTD) | E28: =113 -> 113 | F28: =F24*S5 -> 161.32099 | G28: =G27*G25 -> 148.86456 | H28: =H27*H25 -> 190.21582 | I28: =I27*I25 -> 190.21582 | J28: =J27*J25 -> 190.21582 | K28: =K27*K25 -> 190.21582
A29: As percentage (%) of solar revenue | E29: =E28/R5 -> 0.16666667 | F29: =F28/S5 -> 0.18024691 | G29: =G24 -> 0.18024691 | H29: =H24 -> 0.18024691 | I29: =I24 -> 0.18024691 | J29: =J24 -> 0.18024691 | K29: =K24 -> 0.18024691
A31: Hàm Phú 2-Bình Thuận
A32: Average volume (Q) | E32: =77/2 -> 38.5 | F32: =77 -> 77 | G32: =77 -> 77 | H32: =77 -> 77 | I32: =77 -> 77 | J32: =77 -> 77 | K32: =77 -> 77
A33: As percentage (%) of total volume | E33: =E32/R6 -> 0.14154412 | F33: =$F$32/$S$6 -> 0.19012346 | G33: =$F$32/$S$6 -> 0.19012346 | H33: =$F$32/$S$6 -> 0.19012346 | I33: =$F$32/$S$6 -> 0.19012346 | J33: =$F$32/$S$6 -> 0.19012346 | K33: =$F$32/$S$6 -> 0.19012346
A34: Real vloumne (Qr) | E34: =55 -> 55 | F34: =F33*S7 -> 75.098765 | G34: =G35*G32 -> 69.3 | H34: =H35*H32 -> 77 | I34: =I35*I32 -> 80.85 | J34: =J35*J32 -> 80.85 | K34: =K35*K32 -> 80.85
A35: Qr/Q | E35: =E34/E32 -> 1.4285714 | F35: =F34/F32 -> 0.97530864 | G35: =90% -> 0.9 | H35: =100% -> 1 | I35: 1.05 | J35: 1.05 | K35: 1.05
A36: FIT price | E36: =E37/E34 -> 2.1454545 | F36: =$F$37/$F$34 -> 2.2658228 | G36: =$F$37/$F$34 -> 2.2658228 | H36: =$F$37/$F$34 -> 2.2658228 | I36: =$F$37/$F$34 -> 2.2658228 | J36: =$F$37/$F$34 -> 2.2658228 | K36: =$F$37/$F$34 -> 2.2658228
A37: Revenue (YTD) | E37: =118 -> 118 | F37: =F33*S5 -> 170.16049 | G37: =G36*G34 -> 157.02152 | H37: =H36*H34 -> 174.46835 | I37: =I36*I34 -> 183.19177 | J37: =J36*J34 -> 183.19177 | K37: =K36*K34 -> 183.19177
A38: As percentage (%) of solar revenue | E38: =E37/R5 -> 0.1740413 | F38: =F37/S5 -> 0.19012346 | G38: =G33 -> 0.19012346 | H38: =H33 -> 0.19012346 | I38: =I33 -> 0.19012346 | J38: =J33 -> 0.19012346 | K38: =K33 -> 0.19012346
A40: Trúc Sơn-Bình Thuận
A41: Average volume (Q) | E41: =68/2 -> 34 | F41: 45 | G41: 45 | H41: 45 | I41: 45 | J41: 45 | K41: 45
A42: As percentage (%) of total volume | E42: =E41/R6 -> 0.125 | F42: =$F$41/$S$6 -> 0.11111111 | G42: =$F$41/$S$6 -> 0.11111111 | H42: =$F$41/$S$6 -> 0.11111111 | I42: =$F$41/$S$6 -> 0.11111111 | J42: =$F$41/$S$6 -> 0.11111111 | K42: =$F$41/$S$6 -> 0.11111111
A43: Real vloumne (Qr) | E43: =34 -> 34 | F43: =F42*S7 -> 43.888889 | G43: =G44*G41 -> 40.5 | H43: =H44*H41 -> 45 | I43: =I44*I41 -> 47.25 | J43: =J44*J41 -> 47.25 | K43: =K44*K41 -> 47.25
A44: Qr/Q | E44: =E43/E41 -> 1 | F44: =F43/F41 -> 0.97530864 | G44: =90% -> 0.9 | H44: =100% -> 1 | I44: 1.05 | J44: 1.05 | K44: 1.05
A45: FIT price | E45: =E46/E43 -> 2.1470588 | F45: =$F$46/$F$43 -> 2.2658228 | G45: =$F$46/$F$43 -> 2.2658228 | H45: =$F$46/$F$43 -> 2.2658228 | I45: =$F$46/$F$43 -> 2.2658228 | J45: =$F$46/$F$43 -> 2.2658228 | K45: =$F$46/$F$43 -> 2.2658228
A46: Revenue (YTD) | E46: =73 -> 73 | F46: =F42*S5 -> 99.444444 | G46: =G45*G43 -> 91.765823 | H46: =H45*H43 -> 101.96203 | I46: =I45*I43 -> 107.06013 | J46: =J45*J43 -> 107.06013 | K46: =K45*K43 -> 107.06013
A47: As percentage (%) of solar revenue | E47: =E46/R5 -> 0.10766962 | F47: =F46/S5 -> 0.11111111 | G47: =G42 -> 0.11111111 | H47: =H42 -> 0.11111111 | I47: =I42 -> 0.11111111 | J47: =J42 -> 0.11111111 | K47: =K42 -> 0.11111111
A49: Rooftop
A50: Average volume (Q) | F50: 47 | G50: 47 | H50: 47 | I50: 47 | J50: 47 | K50: 47
A51: As percentage (%) of total volume | F51: =47/$S$6 -> 0.11604938 | G51: =47/$S$6 -> 0.11604938 | H51: =47/$S$6 -> 0.11604938 | I51: =47/$S$6 -> 0.11604938 | J51: =47/$S$6 -> 0.11604938 | K51: =47/$S$6 -> 0.11604938
A52: Real vloumne (Qr) | F52: =F51*S7 -> 45.839506 | G52: =G53*G50 -> 42.3 | H52: =H53*H50 -> 46.06 | I52: =I53*I50 -> 51.7 | J52: =J53*J50 -> 51.7 | K52: =K53*K50 -> 51.7
A53: Qr/Q | F53: =F52/F50 -> 0.97530864 | G53: 0.9 | H53: =98% -> 0.98 | I53: 1.1 | J53: 1.1 | K53: 1.1
A54: FIT price | F54: =$F$55/$F$52 -> 2.2658228 | G54: =$F$55/$F$52 -> 2.2658228 | H54: =$F$55/$F$52 -> 2.2658228 | I54: =$F$55/$F$52 -> 2.2658228 | J54: =$F$55/$F$52 -> 2.2658228 | K54: =$F$55/$F$52 -> 2.2658228
A55: Revenue (YTD) | F55: =F51*S5 -> 103.8642 | G55: =G54*G52 -> 95.844304 | H55: =H54*H52 -> 104.3638 | I55: =I54*I52 -> 117.14304 | J55: =J54*J52 -> 117.14304 | K55: =K54*K52 -> 117.14304
A56: As percentage (%) of solar revenue | F56: =F51 -> 0.11604938 | G56: =G51 -> 0.11604938 | H56: =H51 -> 0.11604938 | I56: =I51 -> 0.11604938 | J56: =J51 -> 0.11604938 | K56: =K51 -> 0.11604938
A59: Wind power plan
A60: VPL 1 - Bến Tre
A61: Average volume (Q) | G61: =96*2/12 -> 16 | H61: 96 | I61: 96 | J61: 96 | K61: 96
A62: As percentage (%) of total volume | G62: =G61/T11 -> 0.24242424 | H62: =H61/U11 -> 0.11897385 | I62: =I61/V11 -> 0.11784925 | J62: =J61/W11 -> 0.11784925 | K62: =K61/X11 -> 0.11784925
A63: Real vloumne (Qr) | G63: =G61 -> 16 | H63: =H61*H64 -> 96 | I63: =I61*I64 -> 96 | J63: =J61*J64 -> 96 | K63: =K61*K64 -> 96
A64: Qr/Q | G64: =G63/G61 -> 1 | H64: =G64 -> 1 | I64: =H64 -> 1 | J64: =I64 -> 1 | K64: =J64 -> 1
A65: FIT price | G65: =9.8*23060/100000 -> 2.25988 | H65: =9.8*23060/100000 -> 2.25988 | I65: =9.8*23060/100000 -> 2.25988 | J65: =9.8*23060/100000 -> 2.25988 | K65: =9.8*23060/100000 -> 2.25988
A66: Revenue (YTD) | G66: =G65*G63 -> 36.15808 | H66: =H65*H63 -> 216.94848 | I66: =I65*I63 -> 216.94848 | J66: =J65*J63 -> 216.94848 | K66: =K65*K63 -> 216.94848
A67: As percentage (%) of solar revenue | G67: =G66/T10 -> 0.25463437 | H67: =H66/U10 -> 0.12867644 | I67: =I66/V10 -> 0.12731718 | J67: =J66/W10 -> 0.12731718 | K67: =K66/X10 -> 0.12731718
A69: Ia bang 1 - Gia Lai
A70: Average volume (Q) | G70: =146*2/12 -> 24.333333 | H70: 146 | I70: 146 | J70: 146 | K70: 146
A71: As percentage (%) of total volume | G71: =G70/T11 -> 0.36868687 | H71: =H70/U11 -> 0.1809394 | I71: =I70/V11 -> 0.17922907 | J71: =J70/W11 -> 0.17922907 | K71: =K70/X11 -> 0.17922907
A72: Real vloumne (Qr) | G72: =146*2/12 -> 24.333333 | H72: =H73*H70 -> 153.3 | I72: =I73*I70 -> 153.3 | J72: =J73*J70 -> 153.3 | K72: =K73*K70 -> 153.3
A73: Qr/Q | G73: =G72/G70 -> 1 | H73: =100%+5% -> 1.05 | I73: =100%+5% -> 1.05 | J73: =100%+5% -> 1.05 | K73: =100%+5% -> 1.05
A74: FIT price | G74: =8.5*23060/100000 -> 1.9601 | H74: =8.5*23060/100000 -> 1.9601 | I74: =8.5*23060/100000 -> 1.9601 | J74: =8.5*23060/100000 -> 1.9601 | K74: =8.5*23060/100000 -> 1.9601
A75: Revenue (YTD) | G75: =G72*G74 -> 47.695767 | H75: =H72*H74 -> 300.48333 | I75: =I72*I74 -> 300.48333 | J75: =J72*J74 -> 300.48333 | K75: =K72*K74 -> 300.48333
A76: As percentage (%) of solar revenue | G76: =G75/T10 -> 0.33588568 | H76: =H75/U10 -> 0.17822262 | I76: =I75/V10 -> 0.17633998 | J76: =J75/W10 -> 0.17633998 | K76: =K75/X10 -> 0.17633998
A78: Tân Phú Đông 2 - Tiền Giang
A79: Average volume (Q) | G79: =154/6 -> 25.666667 | H79: 154 | I79: 154 | J79: 154 | K79: 154
A80: As percentage (%) of total volume | G80: =G79/T11 -> 0.38888889 | H80: =H79/U11 -> 0.19085389 | I80: =I79/V11 -> 0.18904984 | J80: =J79/W11 -> 0.18904984 | K80: =K79/X11 -> 0.18904984
A81: Real vloumne (Qr) | G81: =154/6 -> 25.666667 | H81: =H79*H82 -> 154 | I81: =I79*I82 -> 161.7 | J81: =J79*J82 -> 161.7 | K81: =K79*K82 -> 161.7
A82: Qr/Q | G82: =G81/G79 -> 1 | H82: =G82 -> 1 | I82: =H82+5% -> 1.05 | J82: =I82 -> 1.05 | K82: =J82 -> 1.05
A83: FIT price | G83: =9.8*23060/100000 -> 2.25988 | H83: =9.8*23060/100000 -> 2.25988 | I83: =9.8*23060/100000 -> 2.25988 | J83: =9.8*23060/100000 -> 2.25988 | K83: =9.8*23060/100000 -> 2.25988
A84: Revenue (YTD) | G84: =G81*G83 -> 58.003587 | H84: =H81*H83 -> 348.02152 | I84: =I81*I83 -> 365.4226 | J84: =J81*J83 -> 365.4226 | K84: =K81*K83 -> 365.4226
A85: As percentage (%) of solar revenue | G85: =G84/T10 -> 0.40847596 | H85: =H84/U10 -> 0.20641846 | I85: =I84/V10 -> 0.21444988 | J85: =J84/W10 -> 0.21444988 | K85: =K84/X10 -> 0.21444988
A87: Tân Phú Đông 1 - Tiền Giang
A88: Average volume (Q) | H88: 307.6 | I88: 307.6 | J88: 307.6 | K88: 307.6
A89: As percentage (%) of total volume
A90: Real vloumne (Qr) | H90: =307.6 -> 307.6 | I90: =307.6 -> 307.6 | J90: =307.6 -> 307.6 | K90: =307.6 -> 307.6
A91: Qr/Q | H91: =H90/H88 -> 1 | I91: =I90/I88 -> 1 | J91: =J90/J88 -> 1 | K91: =K90/K88 -> 1
A92: FIT price | H92: =$H$83*0.9 -> 2.033892 | I92: =I83*0.9 -> 2.033892 | J92: =J83*0.9 -> 2.033892 | K92: =K83*0.9 -> 2.033892
A93: Revenue (YTD) | H93: =H90*H92 -> 625.62518 | I93: =I90*I92 -> 625.62518 | J93: =J90*J92 -> 625.62518 | K93: =K90*K92 -> 625.62518
A94: As percentage (%) of solar revenue | H94: =H93/U10 -> 0.37107069 | I94: =I93/V10 -> 0.36715093 | J94: =J93/W10 -> 0.36715093 | K94: =K93/X10 -> 0.36715093
A96: VPL 2 - Tiền Giang
A97: Average volume (Q) | H97: 96 | I97: 96 | J97: 96 | K97: 96
A98: As percentage (%) of total volume | H98: 1 | I98: 1 | J98: 1 | K98: 1
A99: Real vloumne (Qr) | H99: 96 | I99: 96 | J99: 96 | K99: 96
A100: Qr/Q | H100: =H99/H97 -> 1 | I100: =I99/I97 -> 1 | J100: =J99/J97 -> 1 | K100: =K99/K97 -> 1
A101: FIT price | H101: =$H$83*0.9 -> 2.033892 | I101: =$H$83*0.9 -> 2.033892 | J101: =$H$83*0.9 -> 2.033892 | K101: =$H$83*0.9 -> 2.033892
A102: Revenue (YTD) | H102: =H99*H101 -> 195.25363 | I102: =I99*I101 -> 195.25363 | J102: =J99*J101 -> 195.25363 | K102: =K99*K101 -> 195.25363
A103: As percentage (%) of solar revenue | H103: =H102/U10 -> 0.1158088 | I103: =I102/V10 -> 0.11458546 | J103: =J102/W10 -> 0.11458546 | K103: =K102/X10 -> 0.11458546
A105: Hydroelectric
A106: Average volume (Q, tr. kWh) | C106: =7+20+4+9+8+57+37+31+67+51+21+37+18 -> 367 | D106: =7+20+4+9+8+57+37+31+67+51+21+37+18 -> 367 | E106: =7+20+4+9+8+57+37+31+67+51+21+37+18 -> 367 | F106: =7+20+4+9+8+57+37+31+67+51+21+37+18 -> 367 | G106: =7+20+4+9+8+57+37+31+67+51+21+37+18 -> 367 | H106: =7+20+4+9+8+57+37+31+67+51+21+37+18 -> 367 | I106: =7+20+4+9+8+57+37+31+67+51+21+37+18 -> 367 | J106: =7+20+4+9+8+57+37+31+67+51+21+37+18 -> 367 | K106: =7+20+4+9+8+57+37+31+67+51+21+37+18 -> 367
A107: Real volume (Qr) | C107: 426 | D107: 363 | E107: =593-315 -> 278 | F107: 321 | G107: =G106*G108 -> 330.3 | H107: =H106*H108 -> 293.6 | I107: =I106*I108 -> 282.59 | J107: =J106*J108 -> 282.59 | K107: =K106*K108 -> 282.59
A108: Qr/Q | C108: =C107/C106 -> 1.1607629 | D108: =D107/D106 -> 0.98910082 | E108: =E107/E106 -> 0.75749319 | F108: =F107/F106 -> 0.8746594 | G108: =90% -> 0.9 | H108: =80% -> 0.8 | I108: =H108-3% -> 0.77 | J108: =I108 -> 0.77 | K108: =J108 -> 0.77
A109: FIT price | C109: =C110/C107 -> 1.1361502 | D109: =D110/D107 -> 1.2286501 | E109: =E110/E107 -> 1.3669065 | F109: =F110/F107 -> 1.2336449 | G109: =AVERAGE(D109:F109) -> 1.2764005 | H109: =G109 -> 1.2764005 | I109: =H109 -> 1.2764005 | J109: =I109 -> 1.2764005 | K109: =J109 -> 1.2764005
A110: Revenue (YTD) | C110: 484 | D110: 446 | E110: 380 | F110: =396 -> 396 | G110: =G109*G107 -> 421.59508 | H110: =H109*H107 -> 374.75118 | I110: =I109*I107 -> 360.69801 | J110: =J109*J107 -> 360.69801 | K110: =K109*K107 -> 360.69801
A113: Construction and other services
A114: Revenue | B114: 75 | C114: 55 | D114: 76 | E114: =48+55 -> 103 | F114: =140+14+48 -> 202 | G114: 71 | H114: =162 -> 162 | I114: 166 | J114: =166 -> 166 | K114: =168 -> 168
...

Sheet WACC
A1: DATE | B1: GEG | C1: VNI | D1: GEG return | E1: VNI-return
A2: 44539 | B2: 19550 | C2: 1463.54 | D2: =LN(B2/B3) -> 0.010282867 | E2: =LN(C2/C3) -> -0.0030291476 | G2: Beta | H2: =SLOPE(D2:D488,E2:E488) -> 0.74372848
A3: 44538 | B3: 19350 | C3: 1467.98 | D3: =LN(B3/B4) -> 0.0025873236 | E3: =LN(C3/C4) -> 0.010346396 | G3: Risk free rate | H3: =3.7% -> 0.037
A4: 44537 | B4: 19300 | C4: 1452.87 | D4: =LN(B4/B5) -> -0.01542447 | E4: =LN(C4/C5) -> 0.0042074251 | G4: Equity risk premium | H4: 0.0821
A5: 44536 | B5: 19600 | C5: 1446.77 | D5: =LN(B5/B6) -> 0.031090587 | E5: =LN(C5/C6) -> 0.023207992 | G5: D | H5: =(AVERAGE(BS!G21:K21)+AVERAGE(BS!G19:K19))/((SUM(BS!G17,BS!G25)+SUM(BS!H17,BS!H25)+SUM(BS!I17,BS!I25)+SUM(BS!J17,BS!J25)+SUM(BS!K17,BS!K25))/5) -> 0.57223053
A6: 44535 | B6: 19000 | C6: 1413.58 | D6: =LN(B6/B7) -> -0.046280753 | E6: =LN(C6/C7) -> -0.020820522 | G6: E | H6: =1-H5 -> 0.42776947
A7: 44532 | B7: 19900 | C7: 1443.32 | D7: =LN(B7/B8) -> -0.024815169 | E7: =LN(C7/C8) -> -0.026480249 | G7: Marginal tax rate | H7: 0.07
A8: 44531 | B8: 20400 | C8: 1482.05 | D8: =LN(B8/B9) -> 0.019802627 | E8: =LN(C8/C9) -> -0.0021164457 | G8: Cost of equity | H8: =H3+H2*H4 -> 0.098060108
A9: 44530 | B9: 20000 | C9: 1485.19 | D9: =LN(B9/B10) -> 0 | E9: =LN(C9/C10) -> 0.0045552324 | G9: Cost of debt | H9: =9% -> 0.09
A10: 44529 | B10: 20000 | C10: 1478.44 | D10: =LN(B10/B11) -> 0 | E10: =LN(C10/C11) -> -0.0043195445 | G10: WACC | H10: =H8*H6+H9*(1-H7)*H5 -> 0.089842816
A11: 44528 | B11: 20000 | C11: 1484.84 | D11: =LN(B11/B12) -> 0.0075282664 | E11: =LN(C11/C12) -> -0.0055005898
A12: 44525 | B12: 19850 | C12: 1493.03 | D12: =LN(B12/B13) -> 0.0075853714 | E12: =LN(C12/C13) -> -0.0051973502
A13: 44524 | B13: 19700 | C13: 1500.81 | D13: =LN(B13/B14) -> -0.012610508 | E13: =LN(C13/C14) -> 0.0079875194
A14: 44523 | B14: 19950 | C14: 1488.87 | D14: =LN(B14/B15) -> -0.012453461 | E14: =LN(C14/C15) -> 0.017097792
A15: 44522 | B15: 20200 | C15: 1463.63 | D15: =LN(B15/B16) -> 0.040409538 | E15: =LN(C15/C16) -> 0.011254447
A16: 44521 | B16: 19400 | C16: 1447.25 | D16: =LN(B16/B17) -> -0.05515182 | E16: =LN(C16/C17) -> -0.0035177302
A17: 44518 | B17: 20500 | C17: 1452.35 | D17: =LN(B17/B18) -> -0.042966036 | E17: =LN(C17/C18) -> -0.011963814
A18: 44517 | B18: 21400 | C18: 1469.83 | D18: =LN(B18/B19) -> 0 | E18: =LN(C18/C19) -> -0.0040873472
A19: 44516 | B19: 21400 | C19: 1475.85 | D19: =LN(B19/B20) -> 0 | E19: =LN(C19/C20) -> 0.0063895809
A20: 44515 | B20: 21400 | C20: 1466.45 | D20: =LN(B20/B21) -> -0.032186686 | E20: =LN(C20/C21) -> -0.0068773164
A21: 44514 | B21: 22100 | C21: 1476.57 | D21: =LN(B21/B22) -> -0.0045146804 | E21: =LN(C21/C22) -> 0.0021695365
A22: 44511 | B22: 22200 | C22: 1473.37 | D22: =LN(B22/B23) -> 0 | E22: =LN(C22/C23) -> 0.0075075632
... A487: 43832 | B487: 20697.35 | C487: 965.14 | D487: =LN(B487/B488) -> 0.011428835 | E487: =LN(C487/C488) -> -0.001584007
A488: 43831 | B488: 20462.15 | C488: 966.67 | D488: 0.003711 | E488: -0.0042

Sheet Owners equity
A1: PROJECTION | B1: 2016A | C1: 2017A | D1: 2018A | E1: 2019A | F1: 2020A | G1: 2021F | H1: 2022F | I1: 2023F | J1: 2024F | K1: 2025F
A2: OWNERS EQUITY | B2: =SUM(B8,B14,B20,B22,B32,B29) -> 1150.8 | C2: =SUM(C8,C14,C20,C22,C32,C29) -> 1317.9 | D2: =SUM(D8,D14,D20,D22,D32,D29) -> 2408 | E2: =SUM(E8,E14,E20,E22,E32,E29) -> 2579.7 | F2: =SUM(F8,F14,F20,F22,F32,F29) -> 3468 | G2: =SUM(G8,G14,G20,G22,G32,G29) -> 3981.5845 | H2: =SUM(H8,H14,H20,H22,H32,H29) -> 4412.2263 | I2: =SUM(I8,I14,I20,I22,I32,I29) -> 4942.5737 | ... K2: =SUM(K8,K14,K20,K22,K32,K29) -> 6053.3523
A3: Common stock
A4: Beginning of period | B4: 744.9 | C4: =B8 -> 744.9 | D4: =C8 -> 970.9 | E4: =D8 -> 1941.8 | F4: =E8 -> 2038.9 | G4: =F8 -> 2711.8 | H4: =G8 -> 2874.508 | I4: =H8 -> 2874.508 | J4: =I8 -> 2874.508 | K4: =J8 -> 2874.508
A5: Plus: new share issuances | B5: 0 | C5: 77.02 | D5: =D4 -> 970.9 | E5: 97.1 | F5: 509.7
A6: Plus: Stock based compensation | B6: 0 | C6: 149 | F6: 163.1
A7: Less: Treasury stock retired (enter as -) | B7: 0
A8: End of period | B8: =BS!B26 -> 744.9 | C8: =BS!C26 -> 970.9 | D8: =BS!D26 -> 1941.8 | E8: =BS!E26 -> 2038.9 | F8: =BS!F26 -> 2711.8 | G8: =F8*1.06 -> 2874.508 | H8: =G8 -> 2874.508 | I8: =$H$8 -> 2874.508 | J8: =$H$8 -> 2874.508 | K8: =$H$8 -> 2874.508
A10: Share premium
A11: Beginning of period | C11: =B14 -> 2 | D11: =C14 -> 28.9 | E11: =D14 -> 29 | F11: =E14 -> 38.7 | G11: =F14 -> 38.2 | H11: =G14 -> 38.2 | I11: =H14 -> 38.2 | J11: =I14 -> 38.2 | K11: =J14 -> 38.2
A12: Plus: new share issuances | C12: 27 | D12: 0.1 | E12: 9.7 | F12: -0.5
A13: Less: Treasury stock retired (enter as -)
A14: End of period | B14: =BS!B27 -> 2 | C14: =BS!C27 -> 28.9 | D14: =BS!D27 -> 29 | E14: =BS!E27 -> 38.7 | F14: =BS!F27 -> 38.2 | G14: =BS!G27 -> 38.2 | H14: =BS!H27 -> 38.2 | I14: =BS!I27 -> 38.2 | ... K14: =BS!K27 -> 38.2
A16: Treasury stock
A17: Beginning of period | C17: =B20 -> 0 | D17: =C20 -> 0 | E17: =D20 -> 0 | F17: =E20 -> 0 | G17: =F20 -> 0 | H17: =G20 -> 0 | I17: =H20 -> 0 | J17: =I20 -> 0 | K17: =J20 -> 0
A18: Less: Stock repurchases (enter as -)
A19: Plus: Stocks retired
A20: End of period | B20: =BS!B29 -> 0 | C20: =BS!C29 -> 0 | D20: =BS!D29 -> 0 | E20: =BS!E29 -> 0 | F20: =BS!F29 -> 0 | G20: =BS!G29 -> 0 | H20: =BS!H29 -> 0 | I20: =BS!I29 -> 0 | ... K20: =BS!K29 -> 0
A22: Development and investment fund | B22: ='INPUT-Y'!F107 -> 49.1 | C22: ='INPUT-Y'!G107 -> 56.3 | D22: ='INPUT-Y'!H107 -> 61 | E22: ='INPUT-Y'!I107 -> 78.8 | F22: ='INPUT-Y'!J107 -> 87.3 | G22: =F22*1.1 -> 96.03 | H22: =G22*1.1 -> 105.633 | I22: =H22*1.1 -> 116.1963 | J22: =I22*1.1 -> 127.81593 | K22: =J22*1.1 -> 140.59752
A24: Retained earnings
A25: Beginning of period | B25: ='INPUT-Y'!E110 -> 93.8 | C25: =B29 -> 168.4 | D25: =C29 -> 120 | E25: =D29 -> 145.1 | F25: =E29 -> 164.8 | G25: =F29 -> 220 | H25: =G29 -> 559.964 | I25: =H29 -> 978.71116 | J25: =I29 -> 1496.0891 | K25: =J29 -> 2027.3186
A26: Net income | B26: =IS!B18 -> 134.4 | C26: =IS!C18 -> 209.3 | D26: =IS!D18 -> 187.3 | E26: =IS!E18 -> 290.5 | F26: =IS!F18 -> 295 | G26: =IS!G18 -> 339.964 | H26: =IS!H18 -> 418.74716 | I26: =IS!I18 -> 517.3779 | ... K26: =IS!K18 -> 549.96853
A27: Common dividends
A28: Part of treasury stocks retired above common stocks & treasury stock
A29: Ending of period | B29: =BS!B31 -> 168.4 | C29: =BS!C31 -> 120 | D29: =BS!D31 -> 145.1 | E29: =BS!E31 -> 164.8 | F29: =BS!F31 -> 220 | G29: =SUM(G25:G28) -> 559.964 | H29: =SUM(H25:H28) -> 978.71116 | I29: =SUM(I25:I28) -> 1496.0891 | J29: =SUM(J25:J28) -> 2027.3186 | K29: =SUM(K25:K28) -> 2577.2871
A30: Dividend paid | G30: =G31*G8 -> 86.23524 | H30: =H31*H8 -> 0 | I30: =I31*I8 -> 0 | J30: =J31*J8 -> 0 | K30: =K31*K8 -> 0
A31: Cash dividend (%) | B31: =-'INPUT-Y'!C182/'INPUT-Y'!C99 -> 0.17861924 | C31: =-'INPUT-Y'!D182/'INPUT-Y'!D99 -> 0.041576584 | D31: =-'INPUT-Y'!E182/'INPUT-Y'!E99 -> 0.048731373 | E31: =-'INPUT-Y'!F182/'INPUT-Y'!F99 -> 0.053027252 | F31: =-'INPUT-Y'!G182/'INPUT-Y'!G99 -> 0.03038418 | G31: =3% -> 0.03 | H31: 0 | I31: 0 | J31: 0 | K31: 0
A32: Minority interest | B32: =BS!B32 -> 186.4 | C32: =BS!C32 -> 141.8 | D32: =BS!D32 -> 231.1 | E32: =BS!E32 -> 258.5 | F32: =BS!F32 -> 410.7 | G32: =BS!G32 -> 412.8825 | H32: =BS!H32 -> 415.17413 | I32: =BS!I32 -> 417.58033 | ... K32: =BS!K32 -> 422.75969

Sheet Debt
A1: DEBT WATERFALL
A2: LENDER | C2: Unit | D2: =E2-1 -> 2015 | E2: =F2-1 -> 2016 | F2: 2017 | G2: 2018 | H2: 2019 | I2: 2020 | J2: 2021 | K2: 2022 | L2: 2023 | M2: 2024 | N2: 2025 | O2: 2026
A3: VIETINBANK (CTG) | B3: Ending outstanding debt | D3: 77281115 | E3: =E5 -> 74210115 | F3: =F5 -> 68735115 | G3: =G5 -> 62780115 | H3: =H5 -> 56302115 | I3: =I5 -> 49256115 | J3: =J5 -> 39404892 | K3: =K5 -> 31523914 | L3: =L5 -> 23642935 | ... O3: =O5 -> 0
A4: CTG (i)
B5: Outstanding debt | C5: Million VNĐ | D5: 77281115 | E5: 74210115 | F5: 68735115 | G5: 62780115 | H5: 56302115 | I5: 49256115 | J5: =I5-J6 -> 39404892 | K5: =J5-K6 -> 31523914 | L5: =K5-L6 -> 23642935 | M5: =L5-M6 -> 15761957 | N5: =M5-N6 -> 7880978.4 | O5: =N5-O6 -> 0
B6: Principal payment | C6: Million VNĐ | E6: =D5-E5 -> 3071000 | F6: =E5-F5 -> 5475000 | G6: =F5-G5 -> 5955000 | H6: =G5-H5 -> 6478000 | I6: =H5-I5 -> 7046000 | J6: =I5/D59 -> 9851223 | K6: =J5/5 -> 7880978.4 | L6: =K5/4 -> 7880978.4 | M6: =L5/3 -> 7880978.4 | N6: =M5/2 -> 7880978.4 | O6: =N5/1 -> 7880978.4
B7: Interest rate | D7: 0.09 | E7: 0.09 | F7: 0.09 | G7: 0.09 | H7: 0.09 | I7: 0.09 | J7: 0.09 | K7: 0.09 | L7: 0.09 | M7: 0.09 | N7: 0.09 | O7: 0.09
B8: Interest expense | C8: Million VNĐ | E8: =D5*E7 -> 6955300.3 | F8: =E5*F7 -> 6678910.3 | G8: =F5*G7 -> 6186160.3 | H8: =G5*H7 -> 5650210.3 | I8: =H5*I7 -> 5067190.3 | J8: =I5*J7 -> 4433050.3 | K8: =J5*K7 -> 3546440.3 | L8: =K5*L7 -> 2837152.2 | ... O8: =N5*O7 -> 709288.06
A10: VIETCOMBANK (VCB) | B10: Ending outstanding debt | D10: =D11 -> 0 | E10: =E11 -> 0 | F10: =F11 -> 0 | G10: =G11 -> 531009004 | H10: =H11 -> 785800000 | I10: =750400000 -> 750400000 | J10: =J11 -> 675360000 | K10: =K11 -> 600320000 | L10: =L11 -> 525280000 | M10: =M11 -> 450240000 | N10: =N11 -> 375200000 | O10: =O11 -> 300160000
A11: VCB(i) | B11: Outstanding debt | C11: Million VNĐ | G11: =531009004 -> 531009004 | H11: =785800000 -> 785800000 | I11: =750400000 -> 750400000 | J11: =I11-J12 -> 675360000 | K11: =J11-K12 -> 600320000 | L11: =K11-L12 -> 525280000 | M11: =L11-M12 -> 450240000 | N11: =M11-N12 -> 375200000 | O11: =N11-O12 -> 300160000
B12: Principal payment | C12: Million VNĐ | E12: =D11-E11 -> 0 | F12: =E11-F11 -> 0 | H12: =MAX(G11-H11,0) -> 0 | I12: =MAX(H11-I11,0) -> 35400000 | J12: =$I$11/10 -> 75040000 | K12: =$I$11/10 -> 75040000 | L12: =$I$11/10 -> 75040000 | M12: =$I$11/10 -> 75040000 | N12: =$I$11/10 -> 75040000 | O12: =$I$11/10 -> 75040000
B13: Interest rate | G13: 0.078 | H13: 0.078 | I13: 0.095 | J13: 0.095 | K13: 0.095 | L13: 0.095 | M13: 0.095 | N13: 0.095 | O13: 0.095
B14: Interest expense | C14: Million VNĐ | H14: =G11*H13 -> 41418702 | I14: =H11*I13 -> 74651000 | J14: =I11*J13 -> 71288000 | K14: =J11*K13 -> 64159200 | L14: =K11*L13 -> 57030400 | M14: =L11*M13 -> 49901600 | N14: =M11*N13 -> 42772800 | O14: =N11*O13 -> 35644000
A15: VCB (ii) | B15: Ending outstanding debt | D15: =D16 -> 0 | E15: =E16 -> 0 | F15: =F16 -> 0 | G15: =G16 -> 0 | H15: =H16 -> 708834226 | I15: =I16 -> 664000000 | J15: =J16 -> 597600000 | K15: =K16 -> 531200000 | ... O15: =O16 -> 265600000
B16: Outstanding debt | C16: Million VNĐ | H16: 708834226 | I16: 664000000 | J16: =I16-J17 -> 597600000 | K16: =J16-K17 -> 531200000 | L16: =K16-L17 -> 464800000 | M16: =L16-M17 -> 398400000 | N16: =M16-N17 -> 332000000 | O16: =N16-O17 -> 265600000
B17: Principal payment | C17: Million VNĐ | I17: =H16-I16 -> 44834226 | J17: =$I$16/10 -> 66400000 | K17: =$I$16/10 -> 66400000 | L17: =$I$16/10 -> 66400000 | M17: =$I$16/10 -> 66400000 | N17: =$I$16/10 -> 66400000 | O17: =$I$16/10 -> 66400000
B18: Interest rate | H18: 0.078 | I18: 0.08 | J18: 0.081 | K18: 0.091 | L18: 0.091 | M18: 0.091 | N18: 0.091 | O18: 0.091
B19: Interest expense | C19: Million VNĐ | H19: =H18*H16 -> 55289070 | I19: =H16*I18 -> 56706738 | J19: =I16*J18 -> 53784000 | K19: =J16*K18 -> 54381600 | L19: =K16*L18 -> 48339200 | M19: =L16*M18 -> 42296800 | N19: =M16*N18 -> 36254400 | O19: =N16*O18 -> 30212000
A20: VCB(iii) | B20: Ending outstanding debt | J20: =J21+200000000 -> 1960000000 | K20: =K21 -> 1.6246154e+09 | L20: =L21 -> 1.4892308e+09 | M20: =M21 -> 1.3538462e+09 | N20: =N21 -> 1.2184615e+09 | O20: =O21 -> 1.0830769e+09
B21: Outstanding debt | C21: Million VNĐ | J21: =1760000000 -> 1760000000 | K21: =J21-K22 -> 1.6246154e+09 | L21: =K21-L22 -> 1.4892308e+09 | M21: =L21-M22 -> 1.3538462e+09 | N21: =M21-N22 -> 1.2184615e+09 | O21: =N21-O22 -> 1.0830769e+09
B22: Principal payment | C22: Million VNĐ | K22: =$J$21/13 -> 1.3538462e+08 | L22: =$J$21/13 -> 1.3538462e+08 | M22: =$J$21/13 -> 1.3538462e+08 | N22: =$J$21/13 -> 1.3538462e+08 | O22: =$J$21/13 -> 1.3538462e+08
B23: Interest rate | K23: 0.08 | L23: 0.085 | M23: 0.085 | N23: 0.085 | O23: 0.085
B24: Interest expense | C24: Million VNĐ | K24: =K23*J21 -> 140800000 | L24: =L23*K21 -> 1.3809231e+08 | M24: =M23*L21 -> 1.2658462e+08 | N24: =N23*M21 -> 1.1507692e+08 | O24: =O23*N21 -> 1.0356923e+08
A25: VCB (iv) | B25: Ending outstanding debt | D25: =D26 -> 0 | E25: =E26 -> 0 | F25: =F26 -> 0 | G25: =G26 -> 0 | H25: =H26 -> 600750000 | I25: =I26 -> 547350000 | J25: =J26 -> 4.9759091e+08 | K25: =K26 -> 4.4783182e+08 | ... O25: =O26 -> 2.4879545e+08
B26: Outstanding debt | C26: Million VNĐ | H26: 600750000 | I26: 547350000 | J26: =I26-J27 -> 4.9759091e+08 | K26: =J26-K27 -> 4.4783182e+08 | L26: =K26-L27 -> 3.9807273e+08 | M26: =L26-M27 -> 3.4831364e+08 | N26: =M26-N27 -> 2.9855455e+08 | O26: =N26-O27 -> 2.4879545e+08
B27: Principal payment | C27: Million VNĐ | I27: =MAX(H26-I26,0) -> 53400000 | J27: =$I$26/11 -> 49759091 | K27: =$I$26/11 -> 49759091 | L27: =$I$26/11 -> 49759091 | M27: =$I$26/11 -> 49759091 | N27: =$I$26/11 -> 49759091 | O27: =$I$26/11 -> 49759091
B28: Interest rate | H28: 0.068 | I28: 0.075 | J28: 0.085 | K28: 0.095 | L28: 0.095 | M28: 0.095 | N28: 0.095 | O28: 0.095
B29: Interest expense | C29: Million VNĐ | H29: =H26*H28 -> 40851000 | I29: =I26*I28 -> 41051250 | J29: =J26*J28 -> 42295227 | K29: =K26*K28 -> 42544023 | L29: =L26*L28 -> 37816909 | M29: =M26*M28 -> 33089795 | N29: =N26*N28 -> 28362682 | O29: =O26*O28 -> 23635568
A30: BIDV - Gia Dinh Branch (due 3/2029) | B30: Ending outstanding debt | D30: =D31 -> 0 | E30: =E31 -> 0 | F30: =F31 -> 0 | G30: =G31 -> 0 | H30: =H31 -> 0 | I30: =I31 -> 173128641 | J30: =J31 -> 1.5214335e+08 | K30: =K31 -> 1.3115806e+08 | ... M30: =M31 -> 89187482
B31: Outstanding debt | C31: Million VNĐ | I31: 173128641 | J31: =I31-J32 -> 1.5214335e+08 | K31: =J31-K32 -> 1.3115806e+08 | L31: =K31-L32 -> 1.1017277e+08 | M31: =L31-M32 -> 89187482 | N31: =M31-N32 -> 68202192 | O31: =N31-O32 -> 47216902
B32: Principal payment | C32: Million VNĐ | J32: =($I$31/99)*12 -> 20985290 | K32: =($I$31/99)*12 -> 20985290 | L32: =($I$31/99)*12 -> 20985290 | M32: =($I$31/99)*12 -> 20985290 | N32: =($I$31/99)*12 -> 20985290 | O32: =($I$31/99)*12 -> 20985290
B33: Interest rate | J33: 0.08 | K33: 0.08 | L33: 0.08 | M33: 0.08 | N33: 0.08 | O33: 0.08
B34: Interest expense | C34: Million VNĐ | I34: =H31*I33 -> 0 | J34: =I31*J33 -> 13850291 | K34: =J31*K33 -> 12171468 | L34: =K31*L33 -> 10492645 | M34: =L31*M33 -> 8813821.7 | N34: =M31*N33 -> 7134998.5 | O34: =N31*O33 -> 5456175.4
A36: AGRIBANK (due 9/2029) | B36: Ending outstanding debt | C36: Million VNĐ | G36: 415498000 | H36: 462000000 | I36: 431000000 | J36: =I36-J37 -> 377125000 | K36: =J36-K37 -> 323250000 | L36: =K36-L37 -> 269375000 | M36: =L36-M37 -> 215500000 | N36: =M36-N37 -> 161625000 | O36: =N36-O37 -> 107750000
B37: Principal payment | C37: Million VNĐ | F37: =E36-F36 -> 0 | H37: =MAX(G36-H36,0) -> 0 | I37: =MAX(H36-I36,0) -> 31000000 | J37: =$I$36/$D$66 -> 53875000 | K37: =$I$36/$D$66 -> 53875000 | L37: =$I$36/$D$66 -> 53875000 | M37: =$I$36/$D$66 -> 53875000 | N37: =$I$36/$D$66 -> 53875000 | O37: =$I$36/$D$66 -> 53875000
B38: Interest rate | G38: =F38 -> 0 | H38: =(6.8+2.5)% -> 0.093 | I38: =(6.8+2.7)% -> 0.095 | J38: =(4.9+2.7)% -> 0.076 | K38: =(4.9+2.7)% -> 0.076 | L38: =(4.9+2.7)% -> 0.076 | M38: =(4.9+2.7)% -> 0.076 | N38: =(4.9+2.7)% -> 0.076 | O38: =(4.9+2.7)% -> 0.076
B39: Interest expense | C39: Million VNĐ | H39: =G36*H38 -> 38641314 | I39: =H36*I38 -> 43890000 | J39: =I36*J38 -> 32756000 | K39: =J36*K38 -> 28661500 | L39: =K36*L38 -> 24567000 | M39: =L36*M38 -> 20472500 | N39: =M36*N38 -> 16378000 | O39: =N36*O38 -> 12283500
A41: WOORI BANK (2020 - due 12/2026) | B41: Outstanding debt | C41: Million VNĐ | I41: 406361320 | J41: =I41-J42 -> 325089056 | K41: =J41-K42 -> 243816792 | L41: =K41-L42 -> 162544528 | M41: =L41-M42 -> 81272264 | N41: =M41-N42 -> 0 | O41: 0
B42: Principal payment | C42: Million VNĐ | J42: =$I$41/5 -> 81272264 | K42: =$I$41/5 -> 81272264 | L42: =$I$41/5 -> 81272264 | M42: =$I$41/5 -> 81272264 | N42: =$I$41/5 -> 81272264 | O42: 0
B43: Interest rate | J43: 0.072 | K43: 0.072 | L43: 0.072 | M43: 0.072 | N43: 0.072 | O43: 0.072
B44: Interest expense | C44: Million VNĐ | J44: =J43*I41 -> 29258015 | K44: =K43*J41 -> 23406412 | L44: =L43*K41 -> 17554809 | M44: =M43*L41 -> 11703206 | N44: =N43*M41 -> 5851603 | O44: =O43*N41 -> 0
A45: BOND | B45: Bond outstanding at the beginning of the year | C45: VNĐ | G45: 300000000 | H45: 285000000 | I45: 489000000 | J45: 455000000 | K45: =J46 -> 3839000000 | L45: =K46 -> 6439000000 | M45: =L46 -> 4939000000 | N45: =M46 -> 3439000000 | O45: =N46 -> 1339000000
B46: Bond outstanding at the end of the year | C46: VNĐ | G46: =G45-G48 -> 285000000 | H46: =H45+H47-H48 -> 489000000 | I46: =I45+I47-I48 -> 455000000 | J46: =J45+J47-J48+400000000 -> 3839000000 | K46: =K45+K47-K48 -> 6439000000 | L46: =L45+L47-L48 -> 4939000000 | M46: =M45+M47-M48 -> 3439000000 | N46: =N45+N47-N48-100000000 -> 1339000000 | O46: =O45+O47-O48 -> -661000000
B47: Bond issuance | C47: VNĐ | G47: 0 | H47: 219000000 | I47: 200000000 | J47: =1500000000+700000000+1000000000 -> 3200000000 | K47: =1500000000+300000000+1000000000 -> 2800000000 | L47: =1000000000/2 -> 500000000 | M47: =1000000000/2 -> 500000000
B48: Principal payment | C48: VNĐ | G48: 15000000 | H48: 15000000 | I48: =231000000+3000000 -> 234000000 | J48: =219000000-3000000 -> 216000000 | K48: 200000000 | L48: =1000000000+1000000000 -> 2000000000 | M48: =L48 -> 2000000000 | N48: =M48 -> 2000000000 | O48: =N48 -> 2000000000
B49: Interest rate | G49: 0.078 | J49: 0.095 | K49: 0.095 | L49: 0.095 | M49: 0.095 | N49: 0.095 | O49: 0.095
B50: Interest expense | C50: VNĐ | G50: =G49*G45 -> 23400000 | H50: =7.8%*H45+12%*H47 -> 48510000 | I50: =10.5%*I47+12%*I45 -> 79680000 | J50: =I50 -> 79680000 | K50: =J49+(K47+J47)*9.5% -> 5.7e+08 | L50: =K50 -> 5.7e+08 | M50: =L50 -> 5.7e+08 | N50: =M50 -> 5.7e+08
A51: Total | B51: Year based
B52: Total Outstanding debt | C52: Million VNĐ | E52: =E3+E10+E15+E25+E30+E36+E46+E41 -> 74210115 | F52: =F3+F10+F15+F25+F30+F36+F46+F41 -> 68735115 | G52: =G3+G10+G15+G25+G30+G36+G46+G41 -> 1294287119 | H52: =H3+H10+H15+H25+H30+H36+H46+H41 -> 3102686341 | I52: =I3+I10+I15+I25+I30+I36+I46+I41 -> 3476496076 | J52: =J3+J10+J15+J25+J30+J36+J46+J41+J20-20000000-BS!H37/1000 +229000000 -> 8.6723132e+09 | K52: =K3+K10+K15+K25+K30+K36+K46+K41-1303900000+3000000000-107500000 -> 1.0336701e+10 | L52: =L3+L10+L15+L25+L30+L36+L46+L41-604000000+3432500000 -> 9.721388e+09 | M52: =M3+M10+M15+M25+M30+M36+M46+M41+127500000+3972500000 -> 9.1376753e+09 | N52: =N3+N10+N15+N25+N30+N36+N46+N41+900000000+4512500000 -> 7.9267605e+09 | O52: =O3+O10+O15+O25+O30+O36+O46+O41 -> 2.6130545e+08
B53: Current portion of LT debt | C53: Million VNĐ | E53: =E52-F52 -> 5475000 | F53: =F52-G52 -> -1225552004 | G53: =G52-H52 -> -1808399222 | H53: =H52-I52 -> -373809735 | I53: =I52-J52 -> -5.1958171e+09 | J53: =J52-K52 -> -1.6643874e+09 | K53: =K52-L52 -> 6.1531262e+08 | L53: =L52-M52 -> 5.8371262e+08 | ... N53: =N52-O52 -> 7.6654551e+09 | O53: 0
B54: LT Debt reported | C54: Million VNĐ | E54: =E52-E53 -> 68735115 | F54: =F52-F53 -> 1294287119 | G54: =G52-G53 -> 3102686341 | H54: =H52-H53 -> 3476496076 | I54: =I52-I53 -> 8.6723132e+09 | J54: =J52-J53 -> 1.0336701e+10 | K54: =K52-K53 -> 9.721388e+09 | L54: =L52-L53 -> 9.1376753e+09 | ... O54: =O52-O53 -> 2.6130545e+08
B55: Total Interest expense | C55: Million VNĐ | E55: =E8+E14+E19+E29+E34+E39+E44+E50 -> 6955300.3 | F55: =F8+F14+F19+F29+F34+F39+F44+F50 -> 6678910.3 | G55: =G8+G14+G19+G29+G34+G39+G44+G50 -> 29586160 | H55: =H8+H14+H19+H29+H34+H39+H44+H50 -> 2.303603e+08 | I55: =I8+I14+I19+I29+I34+I39+I44+I50 -> 3.0104618e+08 | J55: =J8+J14+J19+J29+J34+J39+J44+J50 -> 3.2734458e+08 | K55: =K8+K14+K19+K29+K34+K39+K44+K50 -> 7.9887064e+08 | L55: =L8+L14+L19+L29+L34+L39+L44+L50 -> 7.6863812e+08 | ... O55: =O8+O14+O19+O29+O34+O39+O44+O50 -> 1.0794053e+08
A58: TT | B58: Debt Contract | C58: Expired year | D58: Times till expiration
A59: 1 | B59: =A4 -> CTG (i) | C59: 2026 | D59: =C59-2021 -> 5
A60: 2 | B60: =A11 -> VCB(i) | C60: 2030 | D60: =C60-2021 -> 9
A61: 3 | B61: =A15 -> VCB (ii) | C61: 2030 | D61: =C61-2021 -> 9
A62: 4 | B62: =A20 -> VCB(iii) | C62: 2034 | D62: =C62-2021 -> 13
A63: 5 | B63: =A25 -> VCB (iv) | C63: 2031 | D63: =C63-2021 -> 10
A64: 6 | B64: =A30 -> BIDV - Gia Dinh Branch (due 3/2029) | C64: 2029 | D64: =C64-2021 -> 8
A65: 7 | B65: WOORI BANK | C65: 2026 | D65: =C65-2021 -> 5
A66: 8 | B66: AGRIBANK | C66: 2029 | D66: =C66-2021 -> 8

Sheet Financial ratios
A1: FINANCIAL RATIOS | B1: 2016 | C1: 2017 | D1: 2018 | E1: 2019 | F1: 2020 | G1: 2021F | H1: 2022F | I1: 2023F | J1: 2024F | K1: 2025F
A2: Profitability ratio
A3: Gross margin | B3: =IS!B6/IS!B$4 -> 0.50741771 | C3: =IS!C6/IS!C$4 -> 0.57837136 | D3: =IS!D6/IS!D$4 -> 0.54691689 | E3: =IS!E6/IS!E$4 -> 0.56037606 | F3: =IS!F6/IS!F$4 -> 0.5097357 | G3: =IS!G6/IS!G$4 -> 0.56630139 | H3: =IS!H6/IS!H$4 -> 0.47297911 | I3: =IS!I6/IS!I$4 -> 0.48222598 | ... K3: =IS!K6/IS!K$4 -> 0.47076162
A4: Profit margin | B4: =IS!B18/IS!B$4 -> 0.31154381 | C4: =IS!C18/IS!C$4 -> 0.38823966 | D4: =IS!D18/IS!D$4 -> 0.33476318 | E4: =IS!E18/IS!E$4 -> 0.25056063 | F4: =IS!F18/IS!F$4 -> 0.19739043 | G4: =IS!G18/IS!G$4 -> 0.23445793 | H4: =IS!H18/IS!H$4 -> 0.13159873 | I4: =IS!I18/IS!I$4 -> 0.15754504 | ... K4: =IS!K18/IS!K$4 -> 0.16670765
A5: ROE DuPont | B5: =B4*B10*B11 -> 0.11679847 | C5: =C4*C10*C11 -> 0.16408915 | D5: =D4*D10*D11 -> 0.11269866 | E5: =E4*E10*E11 -> 0.13693763 | F5: =F4*F10*F11 -> 0.090975787 | G5: =G4*G10*G11 -> 0.11057284 | H5: =H4*H10*H11 -> 0.097290409 | I5: =I4*I10*I11 -> 0.097511 | ... K5: =K4*K10*K11 -> 0.08445215
A6: ROA DuPont | B6: =B4*B10 -> 0.086614681 | C6: =C4*C10 -> 0.1303928 | D6: =D4*D10 -> 0.062234184 | E6: =E4*E10 -> 0.052230353 | F6: =F4*F10 -> 0.040588045 | G6: =G4*G10 -> 0.028583469 | H6: =H4*H10 -> 0.024248241 | I6: =I4*I10 -> 0.028269647 | ... K6: =K4*K10 -> 0.031916186
A7: EBIT/ Sales | B7: =(IS!B15-IS!B9)/IS!B4 -> 0.43648586 | C7: =(IS!C15-IS!C9)/IS!C4 -> 0.47263958 | D7: =(IS!D15-IS!D9)/IS!D4 -> 0.44164433 | E7: =(IS!E15-IS!E9)/IS!E4 -> 0.47334828 | F7: =(IS!F15-IS!F9)/IS!F4 -> 0.44362663 | G7: =(IS!G15-IS!G9)/IS!G4 -> 0.47967026 | H7: =(IS!H15-IS!H9)/IS!H4 -> 0.39274915 | I7: =(IS!I15-IS!I9)/IS!I4 -> 0.40364699 | ... K7: =(IS!K15-IS!K9)/IS!K4 -> 0.39032615
A8: NI/EBT | B8: =IS!B18/IS!B15 -> 0.90080429 | C8: =IS!C18/IS!C15 -> 0.90842014 | D8: =IS!D18/IS!D15 -> 0.90526825 | E8: =IS!E18/IS!E15 -> 0.95590655 | F8: =IS!F18/IS!F15 -> 0.95593001 | G8: =IS!G18/IS!G15 -> 0.92337035 | H8: =IS!H18/IS!H15 -> 0.9287801 | I8: =IS!I18/IS!I15 -> 0.92896757 | ... K8: =IS!K18/IS!K15 -> 0.94901857
A9: EBT / EBIT | B9: =IS!B15/(IS!B12-IS!B10) -> 1.0040377 | C9: =IS!C15/(IS!C12-IS!C10) -> 0.95920067 | D9: =IS!D15/(IS!D12-IS!D10) -> 0.99614829 | E9: =IS!E15/(IS!E12-IS!E10) -> 0.99672024 | F9: =IS!F15/(IS!F12-IS!F10) -> 1.0098168 | G9: =IS!G15/(IS!G12-IS!G10) -> 1.0092703 | H9: =IS!H15/(IS!H12-IS!H10) -> 1.0044117 | I9: =IS!I15/(IS!I12-IS!I10) -> 1.0027439 | ... K9: =IS!K15/(IS!K12-IS!K10) -> 1.0029344
A10: Assets turnover | B10: =IS!B4/AVERAGE(BS!B4,BS!A4) -> 0.27801766 | C10: =IS!C4/AVERAGE(BS!C4,BS!B4) -> 0.33585646 | D10: =IS!D4/AVERAGE(BS!D4,BS!C4) -> 0.1859051 | E10: =IS!E4/AVERAGE(BS!E4,BS!D4) -> 0.20845395 | F10: =IS!F4/AVERAGE(BS!F4,BS!E4) -> 0.20562316 | G10: =IS!G4/AVERAGE(BS!G4,BS!F4) -> 0.121913 | H10: =IS!H4/AVERAGE(BS!H4,BS!G4) -> 0.18425893 | I10: =IS!I4/AVERAGE(BS!I4,BS!H4) -> 0.17943851 | ... K10: =IS!K4/AVERAGE(BS!K4,BS!J4) -> 0.19145004
A11: A/E | B11: =BS!B4/BS!B25 -> 1.3484835 | C11: =BS!C4/BS!C25 -> 1.2584219 | D11: =BS!D4/BS!D25 -> 1.8108804 | E11: =BS!E4/BS!E25 -> 2.6218018 | F11: =BS!F4/BS!F25 -> 2.2414429 | G11: =BS!G4/BS!G25 -> 3.8684191 | H11: =BS!H4/BS!H25 -> 4.0122666 | I11: =BS!I4/BS!I25 -> 3.4493179 | ... K11: =BS!K4/BS!K25 -> 2.6460602
A12: Efficiency ratio
A13: Days of sales outstanding (DSO) | B13: =360/('INPUT-Y'!F123/AVERAGE('INPUT-Y'!E10:F10)) -> 266.20306 | C13: =360/('INPUT-Y'!G123/AVERAGE('INPUT-Y'!F10:G10)) -> 161.73623 | D13: =360/('INPUT-Y'!H123/AVERAGE('INPUT-Y'!G10:H10)) -> 152.13941 | E13: =360/('INPUT-Y'!I123/AVERAGE('INPUT-Y'!H10:I10)) -> 144.95946 | F13: =360/('INPUT-Y'!J123/AVERAGE('INPUT-Y'!I10:J10)) -> 255.84276 | G13: =BS!G49 -> 237.63734 | H13: =BS!H49 -> 219.63734 | I13: =BS!I49 -> 201.63734 | J13: =BS!J49 -> 183.63734 | K13: =BS!K49 -> 165.63734
A14: Days of inventory on hand (DOH) | B14: =360/B17 -> 27.444706 | C14: =360/C17 -> 33.576771 | D14: =360/D17 -> 36.142012 | E14: =360/E17 -> 119.71748 | F14: =360/F17 -> 114.55439 | G14: =BS!G54 -> 132.55439 | H14: =BS!H54 -> 87.309008 | I14: =BS!I54 -> 98.055455 | J14: =BS!J54 -> 110.43814 | K14: =BS!K54 -> 108.58228
A15: Days payable outstanding (DPO) | B15: =360*(AVERAGE(BS!B18,'INPUT-Y'!E68+'INPUT-Y'!E70+'INPUT-Y'!E72+'INPUT-Y'!E76+'INPUT-Y'!E75+'INPUT-Y'!E71+'INPUT-Y'!E69)/-IS!B5) -> 154.92706 | C15: =360*(AVERAGE(BS!C18,BS!B18)/-IS!C5) -> 148.40299 | D15: =360*(AVERAGE(BS!D18,BS!C18)/-IS!D5) -> 368.73373 | E15: =360*(AVERAGE(BS!E18,BS!D18)/-IS!E5) -> 248.82872 | F15: =360*(AVERAGE(BS!F18,BS!E18)/-IS!F5) -> 192.35704 | G15: =BS!G59 -> 858.74987 | H15: =BS!H59 -> 601.12491 | I15: =BS!I59 -> 480.89993 | J15: =BS!J59 -> 384.71994 | K15: =BS!K59 -> 307.77595
A16: Cash conversion cycle | B16: =B13+B14-B15 -> 138.72071 | C16: =C13+C14-C15 -> 46.910006 | D16: =D13+D14-D15 -> -180.45231 | E16: =E13+E14-E15 -> 15.84822 | F16: =F13+F14-F15 -> 178.04012 | G16: =G13+G14-G15 -> -488.55814 | H16: =H13+H14-H15 -> -294.17856 | I16: =I13+I14-I15 -> -181.20713 | ... K16: =K13+K14-K15 -> -33.55634
A17: COGS / Inventory | B17: =-IS!B5/AVERAGE(BS!A8:B8) -> 13.117284 | C17: =-IS!C5/AVERAGE(BS!B8:C8) -> 10.721698 | D17: =-IS!D5/AVERAGE(BS!C8:D8) -> 9.9607073 | E17: =-IS!E5/AVERAGE(BS!D8:E8) -> 3.0070796 | F17: =-IS!F5/AVERAGE(BS!E8:F8) -> 3.1426121 | G17: =-IS!G5/AVERAGE(BS!F8:G8) -> 3.2791578 | H17: =-IS!H5/AVERAGE(BS!G8:H8) -> 5.2548404 | I17: =-IS!I5/AVERAGE(BS!H8:I8) -> 3.9095698 | ... K17: =-IS!K5/AVERAGE(BS!J8:K8) -> 3.3096735
A18: Liquidity ratio
A19: Current ratio | B19: =SUM(BS!B5:B9)/SUM(BS!B18:B19,BS!B22) -> 2.2992603 | C19: =SUM(BS!C5:C9)/SUM(BS!C18:C19,BS!C22) -> 4.0256835 | D19: =SUM(BS!D5:D9)/SUM(BS!D18:D19,BS!D22) -> 2.2400729 | E19: =SUM(BS!E5:E9)/SUM(BS!E18:E19,BS!E22) -> 1.3714286 | F19: =SUM(BS!F5:F9)/SUM(BS!F18:F19,BS!F22) -> 1.565183 | G19: =SUM(BS!G5:G9)/SUM(BS!G18:G19,BS!G22) -> 0.59051537 | H19: =SUM(BS!H5:H9)/SUM(BS!H18:H19,BS!H22) -> 0.68760825 | I19: =SUM(BS!I5:I9)/SUM(BS!I18:I19,BS!I22) -> 0.77610154 | ... K19: =SUM(BS!K5:K9)/SUM(BS!K18:K19,BS!K22) -> 0.98645004
A20: Quick ratio | B20: =SUM(BS!B5:B7)/SUM(BS!B18:B19,BS!B22) -> 2.1856086 | C20: =SUM(BS!C5:C7)/SUM(BS!C18:C19,BS!C22) -> 3.7995029 | D20: =SUM(BS!D5:D7)/SUM(BS!D18:D19,BS!D22) -> 2.0162113 | E20: =SUM(BS!E5:E7)/SUM(BS!E18:E19,BS!E22) -> 0.9281106 | F20: =SUM(BS!F5:F7)/SUM(BS!F18:F19,BS!F22) -> 1.3808058 | G20: =SUM(BS!G5:G7)/SUM(BS!G18:G19,BS!G22) -> 0.49453686 | H20: =SUM(BS!H5:H7)/SUM(BS!H18:H19,BS!H22) -> 0.55455528 | I20: =SUM(BS!I5:I7)/SUM(BS!I18:I19,BS!I22) -> 0.60579034 | ... K20: =SUM(BS!K5:K7)/SUM(BS!K18:K19,BS!K22) -> 0.74905719
A21: Cash Ratio | B21: =BS!B5/SUM(BS!B18:B19,BS!B22) -> 0.45729657 | C21: =BS!C5/SUM(BS!C18:C19,BS!C22) -> 1.8475559 | D21: =BS!D5/SUM(BS!D18:D19,BS!D22) -> 1.1100182 | E21: =BS!E5/SUM(BS!E18:E19,BS!E22) -> 0.12142857 | F21: =BS!F5/SUM(BS!F18:F19,BS!F22) -> 0.11910626 | G21: =BS!G5/SUM(BS!G18:G19,BS!G22) -> 0.19528475 | H21: =BS!H5/SUM(BS!H18:H19,BS!H22) -> 0.010249884 | I21: =BS!I5/SUM(BS!I18:I19,BS!I22) -> 0.014831434 | ... K21: =BS!K5/SUM(BS!K18:K19,BS!K22) -> 0.14335697
A22: Debt/Assets Ratio | B22: =BS!B17/BS!B4 -> 0.25842624 | C22: =BS!C17/BS!C4 -> 0.20535391 | D22: =BS!D17/BS!D4 -> 0.44778242 | E22: =BS!E17/BS!E4 -> 0.61858292 | F22: =BS!F17/BS!F4 -> 0.55385882 | G22: =BS!G17/BS!G4 -> 0.74149647 | H22: =BS!H17/BS!H4 -> 0.75076432 | I22: =BS!I17/BS!I4 -> 0.71008761 | ... K22: =BS!K17/BS!K4 -> 0.62207965
A23: Debt/Equity Ratio | B23: =BS!B17/BS!B25 -> 0.34848353 | C23: =BS!C17/BS!C25 -> 0.25842185 | D23: =BS!D17/BS!D25 -> 0.8108804 | E23: =BS!E17/BS!E25 -> 1.6218018 | F23: =BS!F17/BS!F25 -> 1.2414429 | G23: =BS!G17/BS!G25 -> 2.8684191 | H23: =BS!H17/BS!H25 -> 3.0122666 | I23: =BS!I17/BS!I25 -> 2.4493179 | ... K23: =BS!K17/BS!K25 -> 1.6460602
A24: Short-term Debt/Equity Ratio | B24: =SUM(BS!B18:B19,BS!B22)/BS!B25 -> 0.12922569 | C24: =SUM(BS!C18:C19,BS!C22)/BS!C25 -> 0.091578149 | D24: =SUM(BS!D18:D19,BS!D22)/BS!D25 -> 0.22799003 | E24: =SUM(BS!E18:E19,BS!E22)/BS!E25 -> 0.33648628 | F24: =SUM(BS!F18:F19,BS!F22)/BS!F25 -> 0.32780645 | G24: =SUM(BS!G18:G19,BS!G22)/BS!G25 -> 0.7726219 | H24: =SUM(BS!H18:H19,BS!H22)/BS!H25 -> 0.77253165 | I24: =SUM(BS!I18:I19,BS!I22)/BS!I25 -> 0.59384274 | ... K24: =SUM(BS!K18:K19,BS!K22)/BS!K25 -> 0.39524722
A25: Long-term Debt/Equity Ratio | B25: =SUM(BS!B20:B21,BS!B23)/BS!B25 -> 0.23107674 | C25: =SUM(BS!C20:C21,BS!C23)/BS!C25 -> 0.17996965 | D25: =SUM(BS!D20:D21,BS!D23)/BS!D25 -> 0.59156977 | E25: =SUM(BS!E20:E21,BS!E23)/BS!E25 -> 1.2975655 | F25: =SUM(BS!F20:F21,BS!F23)/BS!F25 -> 0.92393091 | G25: =SUM(BS!G20:G21,BS!G23)/BS!G25 -> 2.0957972 | H25: =SUM(BS!H20:H21,BS!H23)/BS!H25 -> 2.239735 | I25: =SUM(BS!I20:I21,BS!I23)/BS!I25 -> 1.8554751 | ... K25: =SUM(BS!K20:K21,BS!K23)/BS!K25 -> 1.250813
A26: Interest coverage ratio | B26: =(IS!B12+(-IS!B9))/-IS!B9 -> 4.797954 | C26: =(IS!C12+(-IS!C9))/-IS!C9 -> 10.803279 | D26: =(IS!D12+(-IS!D9))/-IS!D9 -> 6.1517413 | E26: =(IS!E12+(-IS!E9))/-IS!E9 -> 2.242548 | F26: =(IS!F12+(-IS!F9))/-IS!F9 -> 1.8575056 | G26: =(IS!G12+(-IS!G9))/-IS!G9 -> 2.1103813 | H26: =(IS!H12+(-IS!H9))/-IS!H9 -> 1.5584849 | I26: =(IS!I12+(-IS!I9))/-IS!I9 -> 1.7184637 | ... K26: =(IS!K12+(-IS!K9))/-IS!K9 -> 1.8116843

Sheet Commonsize
A1: COMMONSIZE | B1: 2016A | C1: 2017A | D1: 2018A | E1: 2019A | F1: 2020A | G1: 2021F | H1: 2022F | I1: 2023F | J1: 2024F | K1: 2025F
B2: HISTORICAL | G2: FORECAST
A3: BALANCE SHEET
A4: TOTAL ASSET | B4: =BS!B4/BS!B4 -> 1 | C4: =BS!C4/BS!C4 -> 1 | D4: =BS!D4/BS!D4 -> 1 | E4: =BS!E4/BS!E4 -> 1 | F4: =BS!F4/BS!F4 -> 1 | G4: =BS!G4/BS!G4 -> 1 | H4: =BS!H4/BS!H4 -> 1 | I4: =BS!I4/BS!I4 -> 1 | ... K4: =BS!K4/BS!K4 -> 1
A5: Cash and Cash Equivalents | B5: =BS!B5/BS!B$4 -> 0.043822904 | C5: =BS!C5/BS!C$4 -> 0.13445074 | D5: =BS!D5/BS!D$4 -> 0.13975141 | E5: =BS!E5/BS!E$4 -> 0.015584339 | F5: =BS!F5/BS!F$4 -> 0.017419048 | G5: =BS!G5/BS!G$4 -> 0.039003342 | H5: =BS!H5/BS!H$4 -> 0.0019735378 | I5: =BS!I5/BS!I$4 -> 0.0025534149 | ... K5: =BS!K5/BS!K$4 -> 0.021413512
A6: Short term financial investment | B6: =BS!B6/BS!B$4 -> 0 | C6: =BS!C6/BS!C$4 -> 0.0049439286 | D6: =BS!D6/BS!D$4 -> 0.057790212 | E6: =BS!E6/BS!E$4 -> 0.001774308 | F6: =BS!F6/BS!F$4 -> 0 | G6: =BS!G6/BS!G$4 -> 0 | H6: =BS!H6/BS!H$4 -> 0 | I6: =BS!I6/BS!I$4 -> 0 | ... K6: =BS!K6/BS!K$4 -> 0
A7: Account Receivables | B7: =BS!B7/BS!B$4 -> 0.1656248 | C7: =BS!C7/BS!C$4 -> 0.13710358 | D7: =BS!D7/BS!D$4 -> 0.056299592 | E7: =BS!E7/BS!E$4 -> 0.10175656 | F7: =BS!F7/BS!F$4 -> 0.18452098 | G7: =BS!G7/BS!G$4 -> 0.059768273 | H7: =BS!H7/BS!H$4 -> 0.10480189 | I7: =BS!I7/BS!I$4 -> 0.10174089 | ... K7: =BS!K7/BS!K$4 -> 0.090474634
A8: Inventory | B8: =BS!B8/BS!B$4 -> 0.010440162 | C8: =BS!C8/BS!C$4 -> 0.015796455 | D8: =BS!D8/BS!D$4 -> 0.0056643581 | E8: =BS!E8/BS!E$4 -> 0.046472084 | F8: =BS!F8/BS!F$4 -> 0.019554618 | G8: =BS!G8/BS!G$4 -> 0.014458997 | H8: =BS!H8/BS!H$4 -> 0.021955829 | I8: =BS!I8/BS!I$4 -> 0.02561749 | ... K8: =BS!K8/BS!K$4 -> 0.031389101
A9: Other Current Assets | B9: =BS!B9/BS!B$4 -> 0.00045111813 | C9: =BS!C9/BS!C$4 -> 0.00066320994 | D9: =BS!D9/BS!D$4 -> 0.022519837 | E9: =BS!E9/BS!E$4 -> 0.01042406 | F9: =BS!F9/BS!F$4 -> 0.007410171 | G9: =BS!G9/BS!G$4 -> 0.0047103571 | H9: =BS!H9/BS!H$4 -> 0.0036625164 | I9: =BS!I9/BS!I$4 -> 0.0037036894 | ... K9: =BS!K9/BS!K$4 -> 0.0040707352
A10: Tangible Fixed Assets | B10: =BS!B10/BS!B$4 -> 0.74995167 | C10: =BS!C10/BS!C$4 -> 0.66767153 | D10: =BS!D10/BS!D$4 -> 0.6584415 | E10: =BS!E10/BS!E$4 -> 0.77473681 | F10: =BS!F10/BS!F$4 -> 0.68572384 | G10: =BS!G10/BS!G$4 -> 0.63139912 | H10: =BS!H10/BS!H$4 -> 0.80692356 | I10: =BS!I10/BS!I$4 -> 0.77429039 | ... K10: =BS!K10/BS!K$4 -> 0.72125743
A11: Financial leases fixed assets | B11: =BS!B11/BS!B$4 -> 0 | C11: =BS!C11/BS!C$4 -> 0 | D11: =BS!D11/BS!D$4 -> 0 | E11: =BS!E11/BS!E$4 -> 0 | F11: =BS!F11/BS!F$4 -> 0.0035764367 | G11: =BS!G11/BS!G$4 -> 0.0017359425 | H11: =BS!H11/BS!H$4 -> 0.001500756 | I11: =BS!I11/BS!I$4 -> 0.0015376897 | ... K11: =BS!K11/BS!K$4 -> 0.0016570422
A12: Intangible Fixed Asset | B12: =BS!B12/BS!B$4 -> 0.003608945 | C12: =BS!C12/BS!C$4 -> 0.0039792596 | D12: =BS!D12/BS!D$4 -> 0.0014676879 | E12: =BS!E12/BS!E$4 -> 0.0028388928 | F12: =BS!F12/BS!F$4 -> 0.002148435 | G12: =BS!G12/BS!G$4 -> 0.00047813546 | H12: =BS!H12/BS!H$4 -> 0.00054445844 | I12: =BS!I12/BS!I$4 -> 0.00060712579 | ... K12: =BS!K12/BS!K$4 -> 0.00061938154
A13: Construction in progress | B13: =BS!B13/BS!B$4 -> 0.003608945 | C13: =BS!C13/BS!C$4 -> 0.010852526 | D13: =BS!D13/BS!D$4 -> 0.049488602 | E13: =BS!E13/BS!E$4 -> 0.038857346 | F13: =BS!F13/BS!F$4 -> 0.069650461 | G13: =BS!G13/BS!G$4 -> 0.23977861 | H13: =BS!H13/BS!H$4 -> 0.051144468 | I13: =BS!I13/BS!I$4 -> 0.082271932 | ... K13: =BS!K13/BS!K$4 -> 0.12084487
A14: Long term Finacial Investments | B14: =BS!B14/BS!B$4 -> 0.00012889089 | C14: =BS!C14/BS!C$4 -> 0 | D14: =BS!D14/BS!D$4 -> 0 | E14: =BS!E14/BS!E$4 -> 0.0003844334 | F14: =BS!F14/BS!F$4 -> 0 | G14: =BS!G14/BS!G$4 -> 0.0054326257 | H14: =BS!H14/BS!H$4 -> 0.0046966104 | I14: =BS!I14/BS!I$4 -> 0.0048121945 | ... K14: =BS!K14/BS!K$4 -> 0.0051857077
A15: Other long term assets | B15: =BS!B15/BS!B$4 -> 0.021911452 | C15: =BS!C15/BS!C$4 -> 0.01796696 | D15: =BS!D15/BS!D$4 -> 0.0083704077 | E15: =BS!E15/BS!E$4 -> 0.0070824462 | F15: =BS!F15/BS!F$4 -> 0.0066640079 | G15: =BS!G15/BS!G$4 -> 0.0032345978 | H15: =BS!H15/BS!H$4 -> 0.0027963726 | I15: =BS!I15/BS!I$4 -> 0.0028651916 | ... K15: =BS!K15/BS!K$4 -> 0.0030875823
A17: LIABILITIES | B17: =BS!B17/BS!B$4 -> 0.25842624 | C17: =BS!C17/BS!C$4 -> 0.20535391 | D17: =BS!D17/BS!D$4 -> 0.44778242 | E17: =BS!E17/BS!E$4 -> 0.61858292 | F17: =BS!F17/BS!F$4 -> 0.55385882 | G17: =BS!G17/BS!G$4 -> 0.74149647 | H17: =BS!H17/BS!H$4 -> 0.75076432 | I17: =BS!I17/BS!I$4 -> 0.71008761 | ... K17: =BS!K17/BS!K$4 -> 0.62207965
... A32: Minority interest | B32: =BS!B32/BS!B$4 -> 0.12012631 | C32: =BS!C32/BS!C$4 -> 0.08549379 | D32: =BS!D32/BS!D$4 -> 0.052997294 | E32: =BS!E32/BS!E$4 -> 0.038221552 | F32: =BS!F32/BS!F$4 -> 0.052836063 | G32: =BS!G32/BS!G$4 -> 0.025782024 | H32: =BS!H32/BS!H$4 -> 0.022412772 | I32: =BS!I32/BS!I$4 -> 0.023097445 | ... K32: =BS!K32/BS!K$4 -> 0.025198945
A35: INCOME STATEMENT | B35: HISTORICAL | G35: FORECAST
A37: Net Sales | B37: 1 | C37: 1 | D37: 1 | E37: 1 | F37: 1 | G37: 1 | H37: 1 | I37: 1 | J37: 1 | K37: 1
A38: Cost of goods sold | B38: -0.49258229 | C38: -0.42162864 | D38: -0.45308311 | E38: -0.43962394 | F38: -0.4902643 | G38: -0.43373935 | H38: -0.52701281 | I38: -0.51781878 | J38: -0.52373588 | K38: -0.5292514
A39: Gross profit | B39: 0.50741771 | C39: 0.57837136 | D39: 0.54691689 | E39: 0.56037606 | F39: 0.5097357 | G39: 0.56626065 | H39: 0.47298719 | I39: 0.48218122 | J39: 0.47626412 | K39: 0.4707486
A40: Financial income | B40: 0.062123319 | C40: 0.033388982 | D40: 0.034852547 | E40: 0.020872865 | F40: 0.020408163 | G40: 0.025377858 | H40: 0.022219629 | I40: 0.02266855 | J40: 0.023422013 | K40: 0.022770064
A41: Financial Expenses | B41: -0.10616597 | C41: -0.045631608 | D41: -0.073458445 | E41: -0.22235639 | F41: -0.24837738 | G41: -0.23706177 | H41: -0.26232747 | I41: -0.24531214 | J41: -0.2357151 | K41: -0.22588779
A42: Of which: Interest Expenses | B42: -0.090635141 | C42: -0.04526062 | D42: -0.071849866 | E42: -0.21122995 | F42: -0.23713617 | G42: -0.22582055 | H42: -0.25108625 | I42: -0.23407093 | J42: -0.22447388 | K42: -0.21464658
A43: Selling Expenses | B43: -0.00023180343 | C43: -0.0018549434 | D43: -0.0010723861 | E43: -0.00051750906 | F43: -0.0011375042 | G43: -0.0009091331 | H43: -0.00085471545 | I43: -0.00096711758 | J43: -0.00091032204 | K43: -0.00091071835
A44: General and admin expenses | B44: -0.11891516 | C44: -0.12075682 | D44: -0.13690795 | E44: -0.095911678 | F44: -0.076480428 | G44: -0.10310002 | H44: -0.091830709 | I44: -0.090470386 | J44: -0.095133705 | K44: -0.092478267
A45: Net Profit/Loss from Operating activities | B45: 0.34422809 | C45: 0.44370247 | D45: 0.37015192 | E45: 0.26246334 | F45: 0.2033456 | G45: 0.25056759 | H45: 0.14019393 | I45: 0.16810012 | J45: 0.16792701 | K45: 0.17424189
A46: Other profits/(loss) | B46: 0.001622624 | C46: -0.016138008 | D46: -0.00035746202 | E46: -0.00025875453 | F46: 0.0031448645 | G46: 0.0032423221 | H46: 0.0014772171 | I46: 0.0014312761 | J46: 0.001428791 | K46: 0.0014245655
A47: Profit or lost from join venture companies | B47: 0 | C47: 0 | D47: 0 | E47: 0 | F47: 0 | G47: 0 | H47: 0 | I47: 0 | J47: 0 | K47: 0
A48: Total profit before tax | B48: 0.34585072 | C48: 0.42737896 | D48: 0.36979446 | E48: 0.26211834 | F48: 0.20649047 | G48: 0.25380991 | H48: 0.14167114 | I48: 0.1695314 | J48: 0.1693558 | K48: 0.17566645
... A53: Net profit after tax attributable to parent company shareholders | B53: 0.22044506 | C53: 0.2852903 | D53: 0.25862377 | E53: 0.21649129 | F53: 0.17223152 | G53: 0.20683501 | H53: 0.11932354 | I53: 0.1456633 | J53: 0.14963355 | K53: 0.15488202

Sheet Báo cáo thu nhập
A1: GEG | B1: 2020 | C1: 2019 | D1: 2018 | E1: 2017 | F1: 2016 | G1: 2015 | H1: 2014 | I1: 2013 | J1: 2012
A2: Đơn vị kiểm toán | B2: PwC | C2: PwC | D2: PwC | E2: PwC | F2: EY | G2: EY | H2: EY | I2: AAC | J2: -
A3: Ý kiến kiểm toán | B3: Chấp nhận toàn phần | C3: Chấp nhận toàn phần | D3: Chấp nhận toàn phần | E3: Chấp nhận toàn phần | F3: Chấp nhận toàn phần | G3: Chấp nhận toàn phần | H3: Chấp nhận toàn phần | I3: Chấp nhận toàn phần | J3: -
A4: 1. Doanh thu bán hàng và cung cấp dịch vụ | B4: 1494.5 | C4: 1159.4 | D4: 559.5 | E4: 539.1 | F4: 431.4 | G4: 354.4 | H4: 338.8 | I4: 307.9
A5: 2. Các khoản giảm trừ doanh thu | B5: 1.2 | C5: 0 | D5: 0 | E5: 0 | F5: 0 | G5: 0 | H5: 0 | I5: 0
A6: 3. Doanh thu thuần | B6: 1493.3 | C6: 1159.4 | D6: 559.5 | E6: 539.1 | F6: 431.4 | G6: 354.4 | H6: 338.8 | I6: 307.9
A7: 4. Giá vốn hàng bán | B7: 732.7 | C7: 509.7 | D7: 253.5 | E7: 227.3 | F7: 212.5 | G7: 157.3 | H7: 134.5 | I7: 118.2
A8: 5. Lợi nhuận gộp | B8: 760.7 | C8: 649.7 | D8: 306 | E8: 311.8 | F8: 218.9 | G8: 197 | H8: 204.3 | I8: 189.7
A9: 6. Doanh thu hoạt động tài chính | B9: 30.5 | C9: 24.2 | D9: 19.5 | E9: 18 | F9: 26.8 | G9: 34.4 | H9: 44.6 | I9: 33.8
A10: 7. Chi phí tài chính | B10: 371.2 | C10: 257.8 | D10: 41.1 | E10: 24.6 | F10: 45.8 | G10: 41.4 | H10: 76.3 | I10: 97.9
A11: - Trong đó: Chi phí lãi vay | B11: 354.4 | C11: 244.9 | D11: 40.2 | E11: 24.4 | F11: 39.1 | G11: 41.1 | H11: 59.5 | I11: 78.3
A12: 8. Lãi/(lỗ) từ công ty liên doanh, liên kết | B12: 0 | C12: 0 | D12: 0 | E12: 0 | F12: 0 | G12: 0 | H12: 0 | I12: 6.5
A13: 9. Chi phí bán hàng | B13: 1.7 | C13: 0.6 | D13: 0.6 | E13: 1 | F13: 0.1 | G13: 0 | H13: 0.2 | I13: 0
A14: 10. Chi phí quản lý doanh nghiệp | B14: 114.3 | C14: 111.2 | D14: 76.6 | E14: 65.1 | F14: 51.3 | G14: 42.1 | H14: 40.4 | I14: 30.3
A15: 11. Lợi nhuận thuần từ hoạt động kinh doanh | B15: 303.9 | C15: 304.3 | D15: 207.1 | E15: 239.2 | F15: 148.5 | G15: 147.8 | H15: 132.1 | I15: 101.8
... A24: 20. Lợi nhuận sau thuế của công ty mẹ | B24: 257.4 | C24: 251 | D24: 144.7 | E24: 153.8 | F24: 95.1 | G24: 92.7 | H24: 76 | I24: 52

Sheet Lưu chuyển tiền tệ
A1: GEG | B1: 2020 | C1: 2019 | D1: 2018 | E1: 2017 | F1: 2016 | G1: 2015 | H1: 2014 | I1: 2013 | J1: 2012
A2: Đơn vị kiểm toán | B2: PwC | C2: PwC | D2: PwC | E2: PwC | F2: EY | G2: EY | H2: EY | I2: AAC | J2: -
A3: Ý kiến kiểm toán | B3: Chấp nhận toàn phần | C3: Chấp nhận toàn phần | D3: Chấp nhận toàn phần | E3: Chấp nhận toàn phần | F3: Chấp nhận toàn phần | G3: Chấp nhận toàn phần | H3: Chấp nhận toàn phần | I3: Chấp nhận toàn phần | J3: -
A4: I. LƯU CHUYỂN TIỀN TỪ HOẠT ĐỘNG KINH DOANH | B4: 420.6 | C4: -332.8 | D4: 141.1 | E4: 243.8 | F4: 168.4 | G4: 71.9 | H4: 345.1 | I4: 66.9
A5: 1. Lợi nhuận trước thuế | B5: 308.6 | C5: 303.9 | D5: 206.9 | E5: 230.4 | F5: 149.2 | G5: 148.5 | H5: 0 | I5: 0
A6: 2. Điều chỉnh cho các khoản: | B6: 0 | C6: 0 | D6: 0 | E6: 0 | F6: 0 | G6: 0 | H6: 0 | I6: 0
A7: Khấu hao TSCĐ và BĐSĐT | B7: 354 | C7: 285 | D7: 97.5 | E7: 79.5 | F7: 79.8 | G7: 74 | H7: 0 | I7: 0
A8: Các khoản dự phòng | B8: -0.4 | C8: 0.5 | D8: 0.3 | E8: 0.3 | F8: 0 | G8: -0.4 | H8: 0 | I8: 0
A9: (Lãi)/lỗ từ hoạt động đầu tư | B9: -25.8 | C9: -23.7 | D9: -19.1 | E9: -11.2 | F9: -27.1 | G9: -34.5 | H9: 0 | I9: 0
A10: (Lãi)/lỗ từ chênh lệch tỷ giá hối đoái chưa thực hiện | B10: 1.4 | C10: 0.5 | D10: 0.8 | E10: 0 | F10: 0 | G10: 0.2 | H10: 0 | I10: 0
A11: (Lãi)/lỗ từ thanh lý/xoá sổ tài sản cố định và xây dựng cơ bản dở dang | B11: 0 | C11: 0 | D11: 0 | E11: 0 | F11: 0 | G11: 0 | H11: 0 | I11: 0
A12: Chi phí lãi vay | B12: 357.9 | C12: 247.3 | D12: 40.2 | E12: 24.4 | F12: 39.1 | G12: 41.1 | H12: 0 | I12: 0
A13: Các khoản điều chỉnh khác | B13: 0 | C13: 0 | D13: 0 | E13: 0 | F13: 0.9 | G13: 0 | H13: 0 | I13: 0
A14: Thu nhập từ lãi tiền gửi | B14: 0 | C14: 0 | D14: 0 | E14: 0 | F14: 0 | G14: 0 | H14: 0 | I14: 0
A15: Phân bổ lợi thế thương mại | B15: 0 | C15: 0 | D15: 0 | E15: 0 | F15: 0 | G15: 0 | H15: 0 | I15: 0
... A46: VI. Tiền và tương đương tiền cuối kỳ | B46: 135.4 | C46: 105.4 | D46: 609.4 | E46: 223 | F46: 68 | G46: 88.7 | H46: 97.8 | I46: 30.1
